Workbook

Sheet README
C2: Análisis financiero de causa raíz sobre la erosión de márgenes en un negocio de repostería artesanal
D5: Meta SMART:
C6: Este negocio no ha tenido actividad desde octubre de 2025 debido a una reubicación geográfica. El objetivo es que durante el primer
C7: trimestre de reactivación operativa, se alcance un Margen Bruto mínimo del 65%, esto, a través de una reingeniería de las recetas
C8: y una actualización dinámica de los precios.
N31: * El MGB se redujo un 5.86% respecto al año anterior.
D35: Para entender dicha erosión (que en volumen de ventas se tradujo al 8.41%), este análisis pretende responder las siguiente preguntas:
D58: Los análisis cuantitativos llevados a cabo en este proyecto, permiten traducir estas variables numéricas en un panorama estratégico. En seguida se
D59: muestra la matriz FODA, la cual sintetiza los hallazgos en la base de datos los cuales serán la base para el plan de acción y el relanzamiento
D60: comercial.
D86: Metodología (ETL)
D88: Unificación de medidas. Se homogenizaron las métricas | I88: Unión de datos. Se vincularon listas de precios antiguos
D89: para asegurar una comparación objetiva en ambos años. | I89: y nuevos para crear una visión completa del historial del
I90: negocio.
D91: Auditoría de datos. Se detectaron valores nulos y se
D92: completaron con la información correspondiente, | I92: Modelado. Se creó una tabla maestra la cual es un motor | R92: 🔡
D93: asegurando que los cálculos sean precisos. | I93: de escenarios dinámicos para el análisis de sensibilidad.
D96: Glosario
D98: CV | E98: Costo de Ventas | G98: SMV | H98: Sales Mix Variance
D99: ETL | E99: Extract, Transform, Load | G99: TotalCV | H99: Total Costo de Ventas
D100: GO | E100: Gastos Opercionales | G100: UB | H100: Utilidad Bruta
D101: ID | E101: Identificación de productos | G101: UN | H101: Utilidad Neta
D102: IT | E102: Ingresos Totales | G102: UO | H102: Utilidad Operativa
D103: MGB | E103: Margen de Ganancia Bruta | G103: VariaciónMoM | H103: Variación Month over Month
D104: MixVtas$ | E104: Mix Ventas Ingresos Totales | G104: VariaciónWoW | H104: Variación Week over Week
D105: MixVtasQ | E105: Mix Ventas Quantity | G105: VariaciónYoY | H105: Variación Year over Year
D106: MU | E106: Margen Unitario

Sheet Insights&Resultados
B2: ¿Qué productos mantuvieron la RENTABILIDAD del negocio?
B19: El 62.5% de los productos ofertados generan poco más del 80% de Utilidad Bruta.
B20: Negocio estable por la alta rentabilidad de los productos estrella, utilidades diversificadas, esto reduce el riesgo operativo pero se pueden optimizar los productos que
B21: aportan menos valor. Requiere atender ciertas áreas para que así siga en el futuro, estas son:
B22: - La merma de los productos más vendidos, ya que esto afecta mucho el MGB.
B23: - Implementar estrategias con los productos menos vendidos y con un MGB bajo.
B24: - Establecer acciones para lograr subir el PV, ya que el CV subió más del triple en su mayoría.
B28: ¿El nulo aumento de casi todos los PRECIOS DE VENTA fue la única causa de la disminución del MARGEN DE GANANCIA BRUTO?
B31: Escenario B (PV 2025 VS CV 2024) | F31: ="Margen Bruto General "& B31 -> Margen Bruto General Escenario B (PV 2025 VS CV 2024)
B34: PV (promedio) | C34: =IF($B$31="2025 (Real)",(AVERAGE('Maestro de productos 2025'!$D$189:$D$196)),IF($B$31="Escenario A (PV 2025+10% VS CV 2025)",(AVERAGE('Maestro de productos 2025'!$D$189:$D$196)*1.1),(AVERAGE('Maestro de productos 2025'!$D$189:$D$196)))) -> 17.625
G35: Real 2025 | H35: =README!$G$14 -> 0.59264977
B36: CV (promedio) | C36: =IF($B$31="2025 (Real)",AVERAGE('Maestro de productos 2025'!$E$189:$E$196),IF($B$31="Escenario A (PV 2025+10% VS CV 2025)",AVERAGE('Maestro de productos 2025'!$E$189:$E$196),AVERAGE('Maestro de productos 2024'!$E$189:$E$196))) -> 6.1195789 | G36: =$B$31 -> Escenario B (PV 2025 VS CV 2024) | H36: =$C$38 -> 0.65631956
B38: MGB | C38: =IF($B$31="2025 (Real)",README!G14,IF($B$31="Escenario A (PV 2025+10% VS CV 2025)",(('Dashboard de rentabilidad'!$C$33-'Dashboard de rentabilidad'!$D$31)/'Dashboard de rentabilidad'!$C$33),('Dashboard de rentabilidad'!$P$58-'Dashboard de rentabilidad'!$Q$58)/'Dashboard de rentabilidad'!$P$58)) -> 0.65631956
B40: Conclusión | C40: =IF($B$31="2025 (Real)","Margen bajo",IF($B$31="Escenario A (PV 2025+10% VS CV 2025)","Margen recuperado con solo aumentar 10% el PV","La inflación fue la causa raíz de la baja del MGB")) -> La inflación fue la causa raíz de la baja del MGB
B43: El análisis de sensibilidad actúa como validación matemática de la Causa Raíz
B44: En el Escenario B (PV 2025 VS CV 2024, se puede comprobar que la estructura
B45: operativa era sana, pero el entorno macroeconómico externo y aunado a la
B46: falta de acoplar los precios de venta fueron los detonantes de la caída del
B47: MGB.
B51: Teniendo en cuenta que el 62.5% de los productos conforman más del 80% de la Utilidad Bruta (ver gráficos de arriba), se tendrá que hacer una reestructuración
B52: de dichos productos para aumentar el PV, bajar mermas, así como también se deberá buscar distintos proveedores con el fin de mejorar costos y subir el MGB.
B53: Aunado a esto, hubo una disminución del 8.41% en el volumen de ventas y aunque tuvo un impacto en la caída del MGB, no fue tan grande la repercusión como sí
B54: lo fue la inflación.
B58: ¿Qué recetas necesitan REESTRUTURACIÓN?
B61: Producto | C61: MGB | D61: Estatus | E61: Acciones
B62: ID-3824 | C62: ='Maestro de productos 2025'!M189/'Maestro de productos 2025'!J189 -> 0.5928256 | D62: =IFS( OR(C62 < 0.45,'Maestro de productos 2025'!G189 < 'Maestro de productos 2025'!$G$198), "🟧 Crítico (Revisar Costos o Rotación)", AND(C62 >= 0.6,'Maestro de productos 2025'!G189 >= 'Maestro de productos 2025'!$G$198), "🟪 Excelente (Alta Rentabilidad y Ventas)", TRUE, "🟨 Estable / Alerta (Monitorear Estrategia)" ) -> 🟨 Estable / Alerta (Monitorear Estrategia) | E62: Abastecimiento estratégico, evitar que no haya inventario ni bajar la calidad
B63: ID-3825 | C63: ='Maestro de productos 2025'!M190/'Maestro de productos 2025'!J190 -> 0.58941974 | D63: =IFS( OR(C63 < 0.45,'Maestro de productos 2025'!G190 < 'Maestro de productos 2025'!$G$198), "🟧 Crítico (Revisar Costos o Rotación)", AND(C63 >= 0.6,'Maestro de productos 2025'!G190 >= 'Maestro de productos 2025'!$G$198), "🟪 Excelente (Alta Rentabilidad y Ventas)", TRUE, "🟨 Estable / Alerta (Monitorear Estrategia)" ) -> 🟨 Estable / Alerta (Monitorear Estrategia) | E63: Reingeniería del producto para reducir la merma operativa. Aumentar ventas.
B64: ID-3826 | C64: ='Maestro de productos 2025'!M191/'Maestro de productos 2025'!J191 -> 0.59634383 | D64: =IFS( OR(C64 < 0.45,'Maestro de productos 2025'!G191 < 'Maestro de productos 2025'!$G$198), "🟧 Crítico (Revisar Costos o Rotación)", AND(C64 >= 0.6,'Maestro de productos 2025'!G191 >= 'Maestro de productos 2025'!$G$198), "🟪 Excelente (Alta Rentabilidad y Ventas)", TRUE, "🟨 Estable / Alerta (Monitorear Estrategia)" ) -> 🟨 Estable / Alerta (Monitorear Estrategia) | E64: Abastecimiento estratégico. Aumentar ventas.
B65: ID-3827 | C65: ='Maestro de productos 2025'!M192/'Maestro de productos 2025'!J192 -> 0.55546007 | D65: =IFS( OR(C65 < 0.45,'Maestro de productos 2025'!G192 < 'Maestro de productos 2025'!$G$198), "🟧 Crítico (Revisar Costos o Rotación)", AND(C65 >= 0.6,'Maestro de productos 2025'!G192 >= 'Maestro de productos 2025'!$G$198), "🟪 Excelente (Alta Rentabilidad y Ventas)", TRUE, "🟨 Estable / Alerta (Monitorear Estrategia)" ) -> 🟨 Estable / Alerta (Monitorear Estrategia) | E65: Abastecimiento estratégico. Aumentar ventas y mejorar proceso de producción.
B66: ID-3828 | C66: ='Maestro de productos 2025'!M193/'Maestro de productos 2025'!J193 -> 0.60193566 | D66: =IFS( OR(C66 < 0.45,'Maestro de productos 2025'!G193 < 'Maestro de productos 2025'!$G$198), "🟧 Crítico (Revisar Costos o Rotación)", AND(C66 >= 0.6,'Maestro de productos 2025'!G193 >= 'Maestro de productos 2025'!$G$198), "🟪 Excelente (Alta Rentabilidad y Ventas)", TRUE, "🟨 Estable / Alerta (Monitorear Estrategia)" ) -> 🟪 Excelente (Alta Rentabilidad y Ventas) | E66: Abastecimiento estratégico
B67: ID-3829 | C67: ='Maestro de productos 2025'!M194/'Maestro de productos 2025'!J194 -> 0.59879238 | D67: =IFS( OR(C67 < 0.45,'Maestro de productos 2025'!G194 < 'Maestro de productos 2025'!$G$198), "🟧 Crítico (Revisar Costos o Rotación)", AND(C67 >= 0.6,'Maestro de productos 2025'!G194 >= 'Maestro de productos 2025'!$G$198), "🟪 Excelente (Alta Rentabilidad y Ventas)", TRUE, "🟨 Estable / Alerta (Monitorear Estrategia)" ) -> 🟧 Crítico (Revisar Costos o Rotación) | E67: Urge incrementar volumen de ventas / ingeniería de valor.
B68: ID-3830 | C68: ='Maestro de productos 2025'!M195/'Maestro de productos 2025'!J195 -> 0.58838362 | D68: =IFS( OR(C68 < 0.45,'Maestro de productos 2025'!G195 < 'Maestro de productos 2025'!$G$198), "🟧 Crítico (Revisar Costos o Rotación)", AND(C68 >= 0.6,'Maestro de productos 2025'!G195 >= 'Maestro de productos 2025'!$G$198), "🟪 Excelente (Alta Rentabilidad y Ventas)", TRUE, "🟨 Estable / Alerta (Monitorear Estrategia)" ) -> 🟧 Crítico (Revisar Costos o Rotación) | E68: Urge incrementar volumen de ventas / ingeniería de valor.
B69: ID-3831 | C69: ='Maestro de productos 2025'!M196/'Maestro de productos 2025'!J196 -> 0.605512 | D69: =IFS( OR(C69 < 0.45,'Maestro de productos 2025'!G196 < 'Maestro de productos 2025'!$G$198), "🟧 Crítico (Revisar Costos o Rotación)", AND(C69 >= 0.6,'Maestro de productos 2025'!G196 >= 'Maestro de productos 2025'!$G$198), "🟪 Excelente (Alta Rentabilidad y Ventas)", TRUE, "🟨 Estable / Alerta (Monitorear Estrategia)" ) -> 🟪 Excelente (Alta Rentabilidad y Ventas) | E69: Abastecimiento estratégico. Aumentar ventas.
B71: El producto ID-3827 necesita atención urgente, ya que al pertenecer al 62.5% anteriomente descrito, es de los productos que contribuyen más al MGB, y se consideran
B72: parte esencial de la rentabilidad del negocio pero los costos y tiempos de producción necesitan atención urgente. Tomando estos puntos a consideración, se llegó a la
B73: conclusión que un abastecimiento estratégico bastará para llegar a la meta en los 3 meses programados.
B75: Los dos productos con el peor rendimiento, ID3829 e ID-3830, mantuvieron un margen unitario más saludable pero no fue suficiente, sus ventas bajaron drásticamente,
B76: ya que la relación costo-producto no convencieron a los clientes.
B80: CONCLUSIÓN
B82: Se concluye que la erosión del 3.69% anual del Margen de Ganancia Bruta, se debió a la inflación acelerada sobre los insumos y el bajo aumento y desigualdad de los
B83: precios de venta de cada producto; no existió una deficiencia operativa.
B85: HALLAZGOS CLAVE
B86: - El negocio es estable, bastaba con subir un 10% el precio de venta para mantener el MGB por arriba del 60%.
B87: - Ya que la utilidad bruta depende del 62.5% de los productos, se requieren acciones para seguir conservándolos en el catálogo .
B88: - Existen dos productos críticos, los cuales se tendrán que reevaluar tanto su preparación como costeo. Con el tiempo se determinará si otorgan solidez al negocio.
... B93: costo de los insumos, cualquier variación inflacionaria deberá reflejarse en el precio al consumidor.

Sheet Análisis Descriptivo
A1: ID | B1: Producto | C1: PV | D1: CV | E1: MU | F1: TotalCV | G1: IT | H1: UB | I1: IT(semanal) | J1: VariacionWoW(I) | K1: MGB(semanal) | L1: UB(semanal) | M1: VariacionWoW(UB) | N1: IT(mensual) | O1: VariacionMoM(I) | P1: MGB(mensual) | Q1: UB(mensual) | R1: VariacionMoM(UB) | S1: IT(anual) | T1: VariacionYoY(I) | U1: MGB(anual) | V1: UB(anual) | W1: VariacionYoY(UB)
A2: {=XLOOKUP($B2,'Maestro de productos 2024'!$A$3:$A$163,'Maestro de productos 2024'!$B$3:$B$163,0)} -> ID-3824 | B2: Galletas chocochips | C2: {=XLOOKUP(B2,'Maestro de productos 2024'!$B$189:$B$196,'Maestro de productos 2024'!$D$189:$D$196,"No encontrado",0)} -> 10 | D2: {=XLOOKUP(B2,'Maestro de productos 2024'!$B$189:$B$196,'Maestro de productos 2024'!$E$189:$E$196,"No encontrado",0)} -> 3.3375513 | E2: =C2-D2 -> 6.6624487 | F2: =('Base de datos transacciones'!$H2)*$D2 -> 106.80164 | G2: ='Base de datos transacciones'!$H2*$C2 -> 320 | H2: =G2-F2 -> 213.19836 | I2: =SUM(G2) -> 320 | K2: =(I2-(SUM(F2)))/I2 -> 0.66624487 | L2: =I2-(SUM(F2)) -> 213.19836
A3: {=XLOOKUP($B3,'Maestro de productos 2024'!$A$3:$A$163,'Maestro de productos 2024'!$B$3:$B$163,0)} -> ID-3824 | B3: Galletas chocochips | C3: {=XLOOKUP(B3,'Maestro de productos 2024'!$B$189:$B$196,'Maestro de productos 2024'!$D$189:$D$196,"No encontrado",0)} -> 10 | D3: {=XLOOKUP(B3,'Maestro de productos 2024'!$B$189:$B$196,'Maestro de productos 2024'!$E$189:$E$196,"No encontrado",0)} -> 3.3375513 | E3: =C3-D3 -> 6.6624487 | F3: =('Base de datos transacciones'!$H3)*$D3 -> 213.60328 | G3: ='Base de datos transacciones'!$H3*$C3 -> 640 | H3: =G3-F3 -> 426.39672 | I3: =SUM(G3) -> 640 | J3: =((I3-I2)/I2) -> 1 | K3: =(I3-(SUM(F3)))/I3 -> 0.66624487 | L3: =I3-(SUM(F3)) -> 426.39672 | M3: =((L3-L2)/L2) -> 1 | N3: =SUM(G2:G3) -> 960 | P3: =(N3-SUM(F2:F3))/N3 -> 0.66624487 | Q3: =N3-(SUM(F2:F3)) -> 639.59508
A4: {=XLOOKUP($B4,'Maestro de productos 2024'!$A$3:$A$163,'Maestro de productos 2024'!$B$3:$B$163,0)} -> ID-3826 | B4: Brownie triple chocolate | C4: {=XLOOKUP(B4,'Maestro de productos 2024'!$B$189:$B$196,'Maestro de productos 2024'!$D$189:$D$196,"No encontrado",0)} -> 20 | D4: {=XLOOKUP(B4,'Maestro de productos 2024'!$B$189:$B$196,'Maestro de productos 2024'!$E$189:$E$196,"No encontrado",0)} -> 7.1039722 | E4: =C4-D4 -> 12.896028 | F4: =('Base de datos transacciones'!$H4)*$D4 -> 127.8715 | G4: ='Base de datos transacciones'!$H4*$C4 -> 360 | H4: =G4-F4 -> 232.1285 | I4: =SUM(G4) -> 360 | J4: =((I4-I3)/I3) -> -0.4375 | K4: =(I4-(SUM(F4)))/I4 -> 0.64480139 | L4: =I4-(SUM(F4)) -> 232.1285 | M4: =((L4-L3)/L3) -> -0.45560439
A5: {=XLOOKUP($B5,'Maestro de productos 2024'!$A$3:$A$163,'Maestro de productos 2024'!$B$3:$B$163,0)} -> ID-3827 | B5: Galletas danesas | C5: {=XLOOKUP(B5,'Maestro de productos 2024'!$B$189:$B$196,'Maestro de productos 2024'!$D$189:$D$196,"No encontrado",0)} -> 7 | D5: {=XLOOKUP(B5,'Maestro de productos 2024'!$B$189:$B$196,'Maestro de productos 2024'!$E$189:$E$196,"No encontrado",0)} -> 2.6234601 | E5: =C5-D5 -> 4.3765399 | F5: =('Base de datos transacciones'!$H5)*$D5 -> 91.821103 | G5: ='Base de datos transacciones'!$H5*$C5 -> 245 | H5: =G5-F5 -> 153.1789 | I5: =SUM(G5) -> 245 | J5: =((I5-I4)/I4) -> -0.31944444 | K5: =(I5-(SUM(F5)))/I5 -> 0.62521999 | L5: =I5-(SUM(F5)) -> 153.1789 | M5: =((L5-L4)/L4) -> -0.34011163
A6: {=XLOOKUP($B6,'Maestro de productos 2024'!$A$3:$A$163,'Maestro de productos 2024'!$B$3:$B$163,0)} -> ID-3824 | B6: Galletas chocochips | C6: {=XLOOKUP(B6,'Maestro de productos 2024'!$B$189:$B$196,'Maestro de productos 2024'!$D$189:$D$196,"No encontrado",0)} -> 10 | D6: {=XLOOKUP(B6,'Maestro de productos 2024'!$B$189:$B$196,'Maestro de productos 2024'!$E$189:$E$196,"No encontrado",0)} -> 3.3375513 | E6: =C6-D6 -> 6.6624487 | F6: =('Base de datos transacciones'!$H6)*$D6 -> 213.60328 | G6: ='Base de datos transacciones'!$H6*$C6 -> 640 | H6: =G6-F6 -> 426.39672
A7: {=XLOOKUP($B7,'Maestro de productos 2024'!$A$3:$A$163,'Maestro de productos 2024'!$B$3:$B$163,0)} -> ID-3825 | B7: Mini cheesecake | C7: {=XLOOKUP(B7,'Maestro de productos 2024'!$B$189:$B$196,'Maestro de productos 2024'!$D$189:$D$196,"No encontrado",0)} -> 20 | D7: {=XLOOKUP(B7,'Maestro de productos 2024'!$B$189:$B$196,'Maestro de productos 2024'!$E$189:$E$196,"No encontrado",0)} -> 7.6091462 | E7: =C7-D7 -> 12.390854 | F7: =('Base de datos transacciones'!$H7)*$D7 -> 121.74634 | G7: ='Base de datos transacciones'!$H7*$C7 -> 320 | H7: =G7-F7 -> 198.25366 | I7: =SUM(G6:G7) -> 960 | J7: =((I7-I5)/I5) -> 2.9183673 | K7: =(I7-(SUM(F6:F7)))/I7 -> 0.65067748 | L7: =I7-(SUM(F6:F7)) -> 624.65038 | M7: =((L7-L5)/L5) -> 3.077914
A8: {=XLOOKUP($B8,'Maestro de productos 2024'!$A$3:$A$163,'Maestro de productos 2024'!$B$3:$B$163,0)} -> ID-3826 | B8: Brownie triple chocolate | C8: {=XLOOKUP(B8,'Maestro de productos 2024'!$B$189:$B$196,'Maestro de productos 2024'!$D$189:$D$196,"No encontrado",0)} -> 20 | D8: {=XLOOKUP(B8,'Maestro de productos 2024'!$B$189:$B$196,'Maestro de productos 2024'!$E$189:$E$196,"No encontrado",0)} -> 7.1039722 | E8: =C8-D8 -> 12.896028 | F8: =('Base de datos transacciones'!$H8)*$D8 -> 255.743 | G8: ='Base de datos transacciones'!$H8*$C8 -> 720 | H8: =G8-F8 -> 464.257
A9: {=XLOOKUP($B9,'Maestro de productos 2024'!$A$3:$A$163,'Maestro de productos 2024'!$B$3:$B$163,0)} -> ID-3827 | B9: Galletas danesas | C9: {=XLOOKUP(B9,'Maestro de productos 2024'!$B$189:$B$196,'Maestro de productos 2024'!$D$189:$D$196,"No encontrado",0)} -> 7 | D9: {=XLOOKUP(B9,'Maestro de productos 2024'!$B$189:$B$196,'Maestro de productos 2024'!$E$189:$E$196,"No encontrado",0)} -> 2.6234601 | E9: =C9-D9 -> 4.3765399 | F9: =('Base de datos transacciones'!$H9)*$D9 -> 91.821103 | G9: ='Base de datos transacciones'!$H9*$C9 -> 245 | H9: =G9-F9 -> 153.1789 | I9: =SUM(G8:G9) -> 965 | J9: =((I9-I7)/I7) -> 0.0052083333 | K9: =(I9-(SUM(F8:F9)))/I9 -> 0.63982995 | L9: =I9-(SUM(F8:F9)) -> 617.4359 | M9: =((L9-L7)/L7) -> -0.01154963 | N9: =SUM(G4:G9) -> 2530 | O9: =((N9-N3)/N3) -> 1.6354167 | P9: =(N9-SUM(F4:F9))/N9 -> 0.64323861 | Q9: =N9-(SUM(F4:F9)) -> 1627.3937 | R9: =((Q9-Q3)/Q3) -> 1.5444124
A10: {=XLOOKUP($B10,'Maestro de productos 2024'!$A$3:$A$163,'Maestro de productos 2024'!$B$3:$B$163,0)} -> ID-3828 | B10: Muffins de yogurt | C10: {=XLOOKUP(B10,'Maestro de productos 2024'!$B$189:$B$196,'Maestro de productos 2024'!$D$189:$D$196,"No encontrado",0)} -> 20 | D10: {=XLOOKUP(B10,'Maestro de productos 2024'!$B$189:$B$196,'Maestro de productos 2024'!$E$189:$E$196,"No encontrado",0)} -> 7.3010641 | E10: =C10-D10 -> 12.698936 | F10: =('Base de datos transacciones'!$H10)*$D10 -> 175.22554 | G10: ='Base de datos transacciones'!$H10*$C10 -> 480 | H10: =G10-F10 -> 304.77446
A11: {=XLOOKUP($B11,'Maestro de productos 2024'!$A$3:$A$163,'Maestro de productos 2024'!$B$3:$B$163,0)} -> ID-3824 | B11: Galletas chocochips | C11: {=XLOOKUP(B11,'Maestro de productos 2024'!$B$189:$B$196,'Maestro de productos 2024'!$D$189:$D$196,"No encontrado",0)} -> 10 | D11: {=XLOOKUP(B11,'Maestro de productos 2024'!$B$189:$B$196,'Maestro de productos 2024'!$E$189:$E$196,"No encontrado",0)} -> 3.3375513 | E11: =C11-D11 -> 6.6624487 | F11: =('Base de datos transacciones'!$H11)*$D11 -> 100.12654 | G11: ='Base de datos transacciones'!$H11*$C11 -> 300 | H11: =G11-F11 -> 199.87346 | I11: =SUM(G10:G11) -> 780 | J11: =((I11-I9)/I9) -> -0.19170984 | K11: =(I11-(SUM(F10:F11)))/I11 -> 0.64698452 | L11: =I11-(SUM(F10:F11)) -> 504.64792 | M11: =((L11-L9)/L9) -> -0.18267155
A12: {=XLOOKUP($B12,'Maestro de productos 2024'!$A$3:$A$163,'Maestro de productos 2024'!$B$3:$B$163,0)} -> ID-3825 | B12: Mini cheesecake | C12: {=XLOOKUP(B12,'Maestro de productos 2024'!$B$189:$B$196,'Maestro de productos 2024'!$D$189:$D$196,"No encontrado",0)} -> 20 | D12: {=XLOOKUP(B12,'Maestro de productos 2024'!$B$189:$B$196,'Maestro de productos 2024'!$E$189:$E$196,"No encontrado",0)} -> 7.6091462 | E12: =C12-D12 -> 12.390854 | F12: =('Base de datos transacciones'!$H12)*$D12 -> 121.74634 | G12: ='Base de datos transacciones'!$H12*$C12 -> 320 | H12: =G12-F12 -> 198.25366
A13: {=XLOOKUP($B13,'Maestro de productos 2024'!$A$3:$A$163,'Maestro de productos 2024'!$B$3:$B$163,0)} -> ID-3824 | B13: Galletas chocochips | C13: {=XLOOKUP(B13,'Maestro de productos 2024'!$B$189:$B$196,'Maestro de productos 2024'!$D$189:$D$196,"No encontrado",0)} -> 10 | D13: {=XLOOKUP(B13,'Maestro de productos 2024'!$B$189:$B$196,'Maestro de productos 2024'!$E$189:$E$196,"No encontrado",0)} -> 3.3375513 | E13: =C13-D13 -> 6.6624487 | F13: =('Base de datos transacciones'!$H13)*$D13 -> 106.80164 | G13: ='Base de datos transacciones'!$H13*$C13 -> 320 | H13: =G13-F13 -> 213.19836 | I13: =SUM(G12:G13) -> 640 | J13: =((I13-I11)/I11) -> -0.17948718 | K13: =(I13-(SUM(F12:F13)))/I13 -> 0.64289378 | L13: =I13-(SUM(F12:F13)) -> 411.45202 | M13: =((L13-L11)/L11) -> -0.1846751
A14: {=XLOOKUP($B14,'Maestro de productos 2024'!$A$3:$A$163,'Maestro de productos 2024'!$B$3:$B$163,0)} -> ID-3826 | B14: Brownie triple chocolate | C14: {=XLOOKUP(B14,'Maestro de productos 2024'!$B$189:$B$196,'Maestro de productos 2024'!$D$189:$D$196,"No encontrado",0)} -> 20 | D14: {=XLOOKUP(B14,'Maestro de productos 2024'!$B$189:$B$196,'Maestro de productos 2024'!$E$189:$E$196,"No encontrado",0)} -> 7.1039722 | E14: =C14-D14 -> 12.896028 | F14: =('Base de datos transacciones'!$H14)*$D14 -> 127.8715 | G14: ='Base de datos transacciones'!$H14*$C14 -> 360 | H14: =G14-F14 -> 232.1285
A15: {=XLOOKUP($B15,'Maestro de productos 2024'!$A$3:$A$163,'Maestro de productos 2024'!$B$3:$B$163,0)} -> ID-3828 | B15: Muffins de yogurt | C15: {=XLOOKUP(B15,'Maestro de productos 2024'!$B$189:$B$196,'Maestro de productos 2024'!$D$189:$D$196,"No encontrado",0)} -> 20 | D15: {=XLOOKUP(B15,'Maestro de productos 2024'!$B$189:$B$196,'Maestro de productos 2024'!$E$189:$E$196,"No encontrado",0)} -> 7.3010641 | E15: =C15-D15 -> 12.698936 | F15: =('Base de datos transacciones'!$H15)*$D15 -> 175.22554 | G15: ='Base de datos transacciones'!$H15*$C15 -> 480 | H15: =G15-F15 -> 304.77446 | I15: =SUM(G14:G15) -> 840 | J15: =((I15-I13)/I13) -> 0.3125 | K15: =(I15-(SUM(F14:F15)))/I15 -> 0.63917019 | L15: =I15-(SUM(F14:F15)) -> 536.90296 | M15: =((L15-L13)/L13) -> 0.30489811
A16: {=XLOOKUP($B16,'Maestro de productos 2024'!$A$3:$A$163,'Maestro de productos 2024'!$B$3:$B$163,0)} -> ID-3828 | B16: Muffins de yogurt | C16: {=XLOOKUP(B16,'Maestro de productos 2024'!$B$189:$B$196,'Maestro de productos 2024'!$D$189:$D$196,"No encontrado",0)} -> 20 | D16: {=XLOOKUP(B16,'Maestro de productos 2024'!$B$189:$B$196,'Maestro de productos 2024'!$E$189:$E$196,"No encontrado",0)} -> 7.3010641 | E16: =C16-D16 -> 12.698936 | F16: =('Base de datos transacciones'!$H16)*$D16 -> 87.612769 | G16: ='Base de datos transacciones'!$H16*$C16 -> 240 | H16: =G16-F16 -> 152.38723
A17: {=XLOOKUP($B17,'Maestro de productos 2024'!$A$3:$A$163,'Maestro de productos 2024'!$B$3:$B$163,0)} -> ID-3824 | B17: Galletas chocochips | C17: {=XLOOKUP(B17,'Maestro de productos 2024'!$B$189:$B$196,'Maestro de productos 2024'!$D$189:$D$196,"No encontrado",0)} -> 10 | D17: {=XLOOKUP(B17,'Maestro de productos 2024'!$B$189:$B$196,'Maestro de productos 2024'!$E$189:$E$196,"No encontrado",0)} -> 3.3375513 | E17: =C17-D17 -> 6.6624487 | F17: =('Base de datos transacciones'!$H17)*$D17 -> 96.788987 | G17: ='Base de datos transacciones'!$H17*$C17 -> 290 | H17: =G17-F17 -> 193.21101 | I17: =SUM(G16:G17) -> 530 | J17: =((I17-I15)/I15) -> -0.36904762 | K17: =(I17-(SUM(F16:F17)))/I17 -> 0.65207216 | L17: =I17-(SUM(F16:F17)) -> 345.59824 | M17: =((L17-L15)/L15) -> -0.35631153
A18: {=XLOOKUP($B18,'Maestro de productos 2024'!$A$3:$A$163,'Maestro de productos 2024'!$B$3:$B$163,0)} -> ID-3825 | B18: Mini cheesecake | C18: {=XLOOKUP(B18,'Maestro de productos 2024'!$B$189:$B$196,'Maestro de productos 2024'!$D$189:$D$196,"No encontrado",0)} -> 20 | D18: {=XLOOKUP(B18,'Maestro de productos 2024'!$B$189:$B$196,'Maestro de productos 2024'!$E$189:$E$196,"No encontrado",0)} -> 7.6091462 | E18: =C18-D18 -> 12.390854 | F18: =('Base de datos transacciones'!$H18)*$D18 -> 106.52805 | G18: ='Base de datos transacciones'!$H18*$C18 -> 280 | H18: =G18-F18 -> 173.47195
A19: {=XLOOKUP($B19,'Maestro de productos 2024'!$A$3:$A$163,'Maestro de productos 2024'!$B$3:$B$163,0)} -> ID-3827 | B19: Galletas danesas | C19: {=XLOOKUP(B19,'Maestro de productos 2024'!$B$189:$B$196,'Maestro de productos 2024'!$D$189:$D$196,"No encontrado",0)} -> 7 | D19: {=XLOOKUP(B19,'Maestro de productos 2024'!$B$189:$B$196,'Maestro de productos 2024'!$E$189:$E$196,"No encontrado",0)} -> 2.6234601 | E19: =C19-D19 -> 4.3765399 | F19: =('Base de datos transacciones'!$H19)*$D19 -> 91.821103 | G19: ='Base de datos transacciones'!$H19*$C19 -> 245 | H19: =G19-F19 -> 153.1789 | I19: =SUM(G18:G19) -> 525 | J19: =((I19-I17)/I17) -> -0.0094339623 | K19: =(I19-(SUM(F18:F19)))/I19 -> 0.6221921 | L19: =I19-(SUM(F18:F19)) -> 326.65085 | M19: =((L19-L17)/L17) -> -0.054824913 | N19: =SUM(G10:G19) -> 3315 | O19: =((N19-N9)/N9) -> 0.31027668 | P19: =(N19-SUM(F10:F19))/N19 -> 0.64110166 | Q19: =N19-(SUM(F10:F19)) -> 2125.252 | R19: =((Q19-Q9)/Q9) -> 0.30592372
A20: {=XLOOKUP($B20,'Maestro de productos 2024'!$A$3:$A$163,'Maestro de productos 2024'!$B$3:$B$163,0)} -> ID-3827 | B20: Galletas danesas | C20: {=XLOOKUP(B20,'Maestro de productos 2024'!$B$189:$B$196,'Maestro de productos 2024'!$D$189:$D$196,"No encontrado",0)} -> 7 | D20: {=XLOOKUP(B20,'Maestro de productos 2024'!$B$189:$B$196,'Maestro de productos 2024'!$E$189:$E$196,"No encontrado",0)} -> 2.6234601 | E20: =C20-D20 -> 4.3765399 | F20: =('Base de datos transacciones'!$H20)*$D20 -> 89.197642 | G20: ='Base de datos transacciones'!$H20*$C20 -> 238 | H20: =G20-F20 -> 148.80236
A21: {=XLOOKUP($B21,'Maestro de productos 2024'!$A$3:$A$163,'Maestro de productos 2024'!$B$3:$B$163,0)} -> ID-3826 | B21: Brownie triple chocolate | C21: {=XLOOKUP(B21,'Maestro de productos 2024'!$B$189:$B$196,'Maestro de productos 2024'!$D$189:$D$196,"No encontrado",0)} -> 20 | D21: {=XLOOKUP(B21,'Maestro de productos 2024'!$B$189:$B$196,'Maestro de productos 2024'!$E$189:$E$196,"No encontrado",0)} -> 7.1039722 | E21: =C21-D21 -> 12.896028 | F21: =('Base de datos transacciones'!$H21)*$D21 -> 127.8715 | G21: ='Base de datos transacciones'!$H21*$C21 -> 360 | H21: =G21-F21 -> 232.1285 | I21: =SUM(G20:G21) -> 598 | J21: =((I21-I19)/I19) -> 0.13904762 | K21: =(I21-(SUM(F20:F21)))/I21 -> 0.63700812 | L21: =I21-(SUM(F20:F21)) -> 380.93086 | M21: =((L21-L19)/L19) -> 0.16617133
A22: {=XLOOKUP($B22,'Maestro de productos 2024'!$A$3:$A$163,'Maestro de productos 2024'!$B$3:$B$163,0)} -> ID-3828 | B22: Muffins de yogurt | C22: {=XLOOKUP(B22,'Maestro de productos 2024'!$B$189:$B$196,'Maestro de productos 2024'!$D$189:$D$196,"No encontrado",0)} -> 20 | D22: {=XLOOKUP(B22,'Maestro de productos 2024'!$B$189:$B$196,'Maestro de productos 2024'!$E$189:$E$196,"No encontrado",0)} -> 7.3010641 | E22: =C22-D22 -> 12.698936 | F22: =('Base de datos transacciones'!$H22)*$D22 -> 175.22554 | G22: ='Base de datos transacciones'!$H22*$C22 -> 480 | H22: =G22-F22 -> 304.77446
A23: {=XLOOKUP($B23,'Maestro de productos 2024'!$A$3:$A$163,'Maestro de productos 2024'!$B$3:$B$163,0)} -> ID-3824 | B23: Galletas chocochips | C23: {=XLOOKUP(B23,'Maestro de productos 2024'!$B$189:$B$196,'Maestro de productos 2024'!$D$189:$D$196,"No encontrado",0)} -> 10 | D23: {=XLOOKUP(B23,'Maestro de productos 2024'!$B$189:$B$196,'Maestro de productos 2024'!$E$189:$E$196,"No encontrado",0)} -> 3.3375513 | E23: =C23-D23 -> 6.6624487 | F23: =('Base de datos transacciones'!$H23)*$D23 -> 106.80164 | G23: ='Base de datos transacciones'!$H23*$C23 -> 320 | H23: =G23-F23 -> 213.19836 | I23: =SUM(G22:G23) -> 800 | J23: =((I23-I21)/I21) -> 0.33779264 | K23: =(I23-(SUM(F22:F23)))/I23 -> 0.64746603 | L23: =I23-(SUM(F22:F23)) -> 517.97282 | M23: =((L23-L21)/L21) -> 0.35975548
A24: {=XLOOKUP($B24,'Maestro de productos 2024'!$A$3:$A$163,'Maestro de productos 2024'!$B$3:$B$163,0)} -> ID-3826 | B24: Brownie triple chocolate | C24: {=XLOOKUP(B24,'Maestro de productos 2024'!$B$189:$B$196,'Maestro de productos 2024'!$D$189:$D$196,"No encontrado",0)} -> 20 | D24: {=XLOOKUP(B24,'Maestro de productos 2024'!$B$189:$B$196,'Maestro de productos 2024'!$E$189:$E$196,"No encontrado",0)} -> 7.1039722 | E24: =C24-D24 -> 12.896028 | F24: =('Base de datos transacciones'!$H24)*$D24 -> 255.743 | G24: ='Base de datos transacciones'!$H24*$C24 -> 720 | H24: =G24-F24 -> 464.257
A25: {=XLOOKUP($B25,'Maestro de productos 2024'!$A$3:$A$163,'Maestro de productos 2024'!$B$3:$B$163,0)} -> ID-3829 | B25: Besos de nuez | C25: {=XLOOKUP(B25,'Maestro de productos 2024'!$B$189:$B$196,'Maestro de productos 2024'!$D$189:$D$196,"No encontrado",0)} -> 7 | D25: {=XLOOKUP(B25,'Maestro de productos 2024'!$B$189:$B$196,'Maestro de productos 2024'!$E$189:$E$196,"No encontrado",0)} -> 2.9898436 | E25: =C25-D25 -> 4.0101564 | F25: =('Base de datos transacciones'!$H25)*$D25 -> 149.49218 | G25: ='Base de datos transacciones'!$H25*$C25 -> 350 | H25: =G25-F25 -> 200.50782 | I25: =SUM(G24:G25) -> 1070 | J25: =((I25-I23)/I23) -> 0.3375 | K25: =(I25-(SUM(F24:F25)))/I25 -> 0.62127553 | L25: =I25-(SUM(F24:F25)) -> 664.76482 | M25: =((L25-L23)/L23) -> 0.28339711
A26: {=XLOOKUP($B26,'Maestro de productos 2024'!$A$3:$A$163,'Maestro de productos 2024'!$B$3:$B$163,0)} -> ID-3828 | B26: Muffins de yogurt | C26: {=XLOOKUP(B26,'Maestro de productos 2024'!$B$189:$B$196,'Maestro de productos 2024'!$D$189:$D$196,"No encontrado",0)} -> 20 | D26: {=XLOOKUP(B26,'Maestro de productos 2024'!$B$189:$B$196,'Maestro de productos 2024'!$E$189:$E$196,"No encontrado",0)} -> 7.3010641 | E26: =C26-D26 -> 12.698936 | F26: =('Base de datos transacciones'!$H26)*$D26 -> 175.22554 | G26: ='Base de datos transacciones'!$H26*$C26 -> 480 | H26: =G26-F26 -> 304.77446
A27: {=XLOOKUP($B27,'Maestro de productos 2024'!$A$3:$A$163,'Maestro de productos 2024'!$B$3:$B$163,0)} -> ID-3826 | B27: Brownie triple chocolate | C27: {=XLOOKUP(B27,'Maestro de productos 2024'!$B$189:$B$196,'Maestro de productos 2024'!$D$189:$D$196,"No encontrado",0)} -> 20 | D27: {=XLOOKUP(B27,'Maestro de productos 2024'!$B$189:$B$196,'Maestro de productos 2024'!$E$189:$E$196,"No encontrado",0)} -> 7.1039722 | E27: =C27-D27 -> 12.896028 | F27: =('Base de datos transacciones'!$H27)*$D27 -> 106.55958 | G27: ='Base de datos transacciones'!$H27*$C27 -> 300 | H27: =G27-F27 -> 193.44042 | I27: =SUM(G26:G27) -> 780 | J27: =((I27-I25)/I25) -> -0.27102804 | K27: =(I27-(SUM(F26:F27)))/I27 -> 0.63873702 | L27: =I27-(SUM(F26:F27)) -> 498.21488 | M27: =((L27-L25)/L25) -> -0.25053965 | N27: =SUM(G20:G27) -> 3248 | O27: =((N27-N19)/N19) -> -0.020211161 | P27: =(N27-SUM(F20:F27))/N27 -> 0.63481631 | Q27: =N27-(SUM(F20:F27)) -> 2061.8834 | R27: =((Q27-Q19)/Q19) -> -0.029816991
A28: {=XLOOKUP($B28,'Maestro de productos 2024'!$A$3:$A$163,'Maestro de productos 2024'!$B$3:$B$163,0)} -> ID-3827 | B28: Galletas danesas | C28: {=XLOOKUP(B28,'Maestro de productos 2024'!$B$189:$B$196,'Maestro de productos 2024'!$D$189:$D$196,"No encontrado",0)} -> 7 | D28: {=XLOOKUP(B28,'Maestro de productos 2024'!$B$189:$B$196,'Maestro de productos 2024'!$E$189:$E$196,"No encontrado",0)} -> 2.6234601 | E28: =C28-D28 -> 4.3765399 | F28: =('Base de datos transacciones'!$H28)*$D28 -> 76.080342 | G28: ='Base de datos transacciones'!$H28*$C28 -> 203 | H28: =G28-F28 -> 126.91966
A29: {=XLOOKUP($B29,'Maestro de productos 2024'!$A$3:$A$163,'Maestro de productos 2024'!$B$3:$B$163,0)} -> ID-3825 | B29: Mini cheesecake | C29: {=XLOOKUP(B29,'Maestro de productos 2024'!$B$189:$B$196,'Maestro de productos 2024'!$D$189:$D$196,"No encontrado",0)} -> 20 | D29: {=XLOOKUP(B29,'Maestro de productos 2024'!$B$189:$B$196,'Maestro de productos 2024'!$E$189:$E$196,"No encontrado",0)} -> 7.6091462 | E29: =C29-D29 -> 12.390854 | F29: =('Base de datos transacciones'!$H29)*$D29 -> 121.74634 | G29: ='Base de datos transacciones'!$H29*$C29 -> 320 | H29: =G29-F29 -> 198.25366 | I29: =SUM(G28:G29) -> 523 | J29: =((I29-I27)/I27) -> -0.32948718 | K29: =(I29-(SUM(F28:F29)))/I29 -> 0.62174631 | L29: =I29-(SUM(F28:F29)) -> 325.17332 | M29: =((L29-L27)/L27) -> -0.34732315
A30: {=XLOOKUP($B30,'Maestro de productos 2024'!$A$3:$A$163,'Maestro de productos 2024'!$B$3:$B$163,0)} -> ID-3824 | B30: Galletas chocochips | C30: {=XLOOKUP(B30,'Maestro de productos 2024'!$B$189:$B$196,'Maestro de productos 2024'!$D$189:$D$196,"No encontrado",0)} -> 10 | D30: {=XLOOKUP(B30,'Maestro de productos 2024'!$B$189:$B$196,'Maestro de productos 2024'!$E$189:$E$196,"No encontrado",0)} -> 3.3375513 | E30: =C30-D30 -> 6.6624487 | F30: =('Base de datos transacciones'!$H30)*$D30 -> 106.80164 | G30: ='Base de datos transacciones'!$H30*$C30 -> 320 | H30: =G30-F30 -> 213.19836
A31: {=XLOOKUP($B31,'Maestro de productos 2024'!$A$3:$A$163,'Maestro de productos 2024'!$B$3:$B$163,0)} -> ID-3829 | B31: Besos de nuez | C31: {=XLOOKUP(B31,'Maestro de productos 2024'!$B$189:$B$196,'Maestro de productos 2024'!$D$189:$D$196,"No encontrado",0)} -> 7 | D31: {=XLOOKUP(B31,'Maestro de productos 2024'!$B$189:$B$196,'Maestro de productos 2024'!$E$189:$E$196,"No encontrado",0)} -> 2.9898436 | E31: =C31-D31 -> 4.0101564 | F31: =('Base de datos transacciones'!$H31)*$D31 -> 134.54296 | G31: ='Base de datos transacciones'!$H31*$C31 -> 315 | H31: =G31-F31 -> 180.45704 | I31: =SUM(G30:G31) -> 635 | J31: =((I31-I29)/I29) -> 0.21414914 | K31: =(I31-(SUM(F30:F31)))/I31 -> 0.61992976 | L31: =I31-(SUM(F30:F31)) -> 393.6554 | M31: =((L31-L29)/L29) -> 0.21060178
A32: {=XLOOKUP($B32,'Maestro de productos 2024'!$A$3:$A$163,'Maestro de productos 2024'!$B$3:$B$163,0)} -> ID-3828 | B32: Muffins de yogurt | C32: {=XLOOKUP(B32,'Maestro de productos 2024'!$B$189:$B$196,'Maestro de productos 2024'!$D$189:$D$196,"No encontrado",0)} -> 20 | D32: {=XLOOKUP(B32,'Maestro de productos 2024'!$B$189:$B$196,'Maestro de productos 2024'!$E$189:$E$196,"No encontrado",0)} -> 7.3010641 | E32: =C32-D32 -> 12.698936 | F32: =('Base de datos transacciones'!$H32)*$D32 -> 175.22554 | G32: ='Base de datos transacciones'!$H32*$C32 -> 480 | H32: =G32-F32 -> 304.77446
A33: {=XLOOKUP($B33,'Maestro de productos 2024'!$A$3:$A$163,'Maestro de productos 2024'!$B$3:$B$163,0)} -> ID-3826 | B33: Brownie triple chocolate | C33: {=XLOOKUP(B33,'Maestro de productos 2024'!$B$189:$B$196,'Maestro de productos 2024'!$D$189:$D$196,"No encontrado",0)} -> 20 | D33: {=XLOOKUP(B33,'Maestro de productos 2024'!$B$189:$B$196,'Maestro de productos 2024'!$E$189:$E$196,"No encontrado",0)} -> 7.1039722 | E33: =C33-D33 -> 12.896028 | F33: =('Base de datos transacciones'!$H33)*$D33 -> 113.66356 | G33: ='Base de datos transacciones'!$H33*$C33 -> 320 | H33: =G33-F33 -> 206.33644 | I33: =SUM(G32:G33) -> 800 | J33: =((I33-I31)/I31) -> 0.25984252 | K33: =(I33-(SUM(F32:F33)))/I33 -> 0.63888863 | L33: =I33-(SUM(F32:F33)) -> 511.11091 | M33: =((L33-L31)/L31) -> 0.29837139
A34: {=XLOOKUP($B34,'Maestro de productos 2024'!$A$3:$A$163,'Maestro de productos 2024'!$B$3:$B$163,0)} -> ID-3830 | B34: Flan de queso crema | C34: {=XLOOKUP(B34,'Maestro de productos 2024'!$B$189:$B$196,'Maestro de productos 2024'!$D$189:$D$196,"No encontrado",0)} -> 25 | D34: {=XLOOKUP(B34,'Maestro de productos 2024'!$B$189:$B$196,'Maestro de productos 2024'!$E$189:$E$196,"No encontrado",0)} -> 10.936667 | E34: =C34-D34 -> 14.063333 | F34: =('Base de datos transacciones'!$H34)*$D34 -> 196.86 | G34: ='Base de datos transacciones'!$H34*$C34 -> 450 | H34: =G34-F34 -> 253.14
A35: {=XLOOKUP($B35,'Maestro de productos 2024'!$A$3:$A$163,'Maestro de productos 2024'!$B$3:$B$163,0)} -> ID-3827 | B35: Galletas danesas | C35: {=XLOOKUP(B35,'Maestro de productos 2024'!$B$189:$B$196,'Maestro de productos 2024'!$D$189:$D$196,"No encontrado",0)} -> 7 | D35: {=XLOOKUP(B35,'Maestro de productos 2024'!$B$189:$B$196,'Maestro de productos 2024'!$E$189:$E$196,"No encontrado",0)} -> 2.6234601 | E35: =C35-D35 -> 4.3765399 | F35: =('Base de datos transacciones'!$H35)*$D35 -> 78.703802 | G35: ='Base de datos transacciones'!$H35*$C35 -> 210 | H35: =G35-F35 -> 131.2962 | I35: =SUM(G34:G35) -> 660 | J35: =((I35-I33)/I33) -> -0.175 | K35: =(I35-(SUM(F34:F35)))/I35 -> 0.58247909 | L35: =I35-(SUM(F34:F35)) -> 384.4362 | M35: =((L35-L33)/L33) -> -0.24784192
A36: {=XLOOKUP($B36,'Maestro de productos 2024'!$A$3:$A$163,'Maestro de productos 2024'!$B$3:$B$163,0)} -> ID-3825 | B36: Mini cheesecake | C36: {=XLOOKUP(B36,'Maestro de productos 2024'!$B$189:$B$196,'Maestro de productos 2024'!$D$189:$D$196,"No encontrado",0)} -> 20 | D36: {=XLOOKUP(B36,'Maestro de productos 2024'!$B$189:$B$196,'Maestro de productos 2024'!$E$189:$E$196,"No encontrado",0)} -> 7.6091462 | E36: =C36-D36 -> 12.390854 | F36: =('Base de datos transacciones'!$H36)*$D36 -> 121.74634 | G36: ='Base de datos transacciones'!$H36*$C36 -> 320 | H36: =G36-F36 -> 198.25366 | N36: =SUM(G28:G36) -> 2938 | O36: =((N36-N27)/N27) -> -0.09544335 | P36: =(N36-SUM(F28:F36))/N36 -> 0.61696034 | Q36: =N36-(SUM(F28:F36)) -> 1812.6295 | R36: =((Q36-Q27)/Q27) -> -0.12088652
A37: {=XLOOKUP($B37,'Maestro de productos 2024'!$A$3:$A$163,'Maestro de productos 2024'!$B$3:$B$163,0)} -> ID-3829 | B37: Besos de nuez | C37: {=XLOOKUP(B37,'Maestro de productos 2024'!$B$189:$B$196,'Maestro de productos 2024'!$D$189:$D$196,"No encontrado",0)} -> 7 | D37: {=XLOOKUP(B37,'Maestro de productos 2024'!$B$189:$B$196,'Maestro de productos 2024'!$E$189:$E$196,"No encontrado",0)} -> 2.9898436 | E37: =C37-D37 -> 4.0101564 | F37: =('Base de datos transacciones'!$H37)*$D37 -> 149.49218 | G37: ='Base de datos transacciones'!$H37*$C37 -> 350 | H37: =G37-F37 -> 200.50782 | I37: =SUM(G36:G37) -> 670 | J37: =((I37-I35)/I35) -> 0.015151515 | K37: =(I37-(SUM(F36:F37)))/I37 -> 0.59516639 | L37: =I37-(SUM(F36:F37)) -> 398.76148 | M37: =((L37-L35)/L35) -> 0.037263096
A38: {=XLOOKUP($B38,'Maestro de productos 2024'!$A$3:$A$163,'Maestro de productos 2024'!$B$3:$B$163,0)} -> ID-3824 | B38: Galletas chocochips | C38: {=XLOOKUP(B38,'Maestro de productos 2024'!$B$189:$B$196,'Maestro de productos 2024'!$D$189:$D$196,"No encontrado",0)} -> 10 | D38: {=XLOOKUP(B38,'Maestro de productos 2024'!$B$189:$B$196,'Maestro de productos 2024'!$E$189:$E$196,"No encontrado",0)} -> 3.3375513 | E38: =C38-D38 -> 6.6624487 | F38: =('Base de datos transacciones'!$H38)*$D38 -> 106.80164 | G38: ='Base de datos transacciones'!$H38*$C38 -> 320 | H38: =G38-F38 -> 213.19836
A39: {=XLOOKUP($B39,'Maestro de productos 2024'!$A$3:$A$163,'Maestro de productos 2024'!$B$3:$B$163,0)} -> ID-3828 | B39: Muffins de yogurt | C39: {=XLOOKUP(B39,'Maestro de productos 2024'!$B$189:$B$196,'Maestro de productos 2024'!$D$189:$D$196,"No encontrado",0)} -> 20 | D39: {=XLOOKUP(B39,'Maestro de productos 2024'!$B$189:$B$196,'Maestro de productos 2024'!$E$189:$E$196,"No encontrado",0)} -> 7.3010641 | E39: =C39-D39 -> 12.698936 | F39: =('Base de datos transacciones'!$H39)*$D39 -> 175.22554 | G39: ='Base de datos transacciones'!$H39*$C39 -> 480 | H39: =G39-F39 -> 304.77446 | I39: =SUM(G38:G39) -> 800 | J39: =((I39-I37)/I37) -> 0.19402985 | K39: =(I39-(SUM(F38:F39)))/I39 -> 0.64746603 | L39: =I39-(SUM(F38:F39)) -> 517.97282 | M39: =((L39-L37)/L37) -> 0.298954
A40: {=XLOOKUP($B40,'Maestro de productos 2024'!$A$3:$A$163,'Maestro de productos 2024'!$B$3:$B$163,0)} -> ID-3826 | B40: Brownie triple chocolate | C40: {=XLOOKUP(B40,'Maestro de productos 2024'!$B$189:$B$196,'Maestro de productos 2024'!$D$189:$D$196,"No encontrado",0)} -> 20 | D40: {=XLOOKUP(B40,'Maestro de productos 2024'!$B$189:$B$196,'Maestro de productos 2024'!$E$189:$E$196,"No encontrado",0)} -> 7.1039722 | E40: =C40-D40 -> 12.896028 | F40: =('Base de datos transacciones'!$H40)*$D40 -> 127.8715 | G40: ='Base de datos transacciones'!$H40*$C40 -> 360 | H40: =G40-F40 -> 232.1285
A41: {=XLOOKUP($B41,'Maestro de productos 2024'!$A$3:$A$163,'Maestro de productos 2024'!$B$3:$B$163,0)} -> ID-3830 | B41: Flan de queso crema | C41: {=XLOOKUP(B41,'Maestro de productos 2024'!$B$189:$B$196,'Maestro de productos 2024'!$D$189:$D$196,"No encontrado",0)} -> 25 | D41: {=XLOOKUP(B41,'Maestro de productos 2024'!$B$189:$B$196,'Maestro de productos 2024'!$E$189:$E$196,"No encontrado",0)} -> 10.936667 | E41: =C41-D41 -> 14.063333 | F41: =('Base de datos transacciones'!$H41)*$D41 -> 174.98667 | G41: ='Base de datos transacciones'!$H41*$C41 -> 400 | H41: =G41-F41 -> 225.01333 | I41: =SUM(G40:G41) -> 760 | J41: =((I41-I39)/I39) -> -0.05 | K41: =(I41-(SUM(F40:F41)))/I41 -> 0.60150241 | L41: =I41-(SUM(F40:F41)) -> 457.14183 | M41: =((L41-L39)/L39) -> -0.1174405
A42: {=XLOOKUP($B42,'Maestro de productos 2024'!$A$3:$A$163,'Maestro de productos 2024'!$B$3:$B$163,0)} -> ID-3825 | B42: Mini cheesecake | C42: {=XLOOKUP(B42,'Maestro de productos 2024'!$B$189:$B$196,'Maestro de productos 2024'!$D$189:$D$196,"No encontrado",0)} -> 20 | D42: {=XLOOKUP(B42,'Maestro de productos 2024'!$B$189:$B$196,'Maestro de productos 2024'!$E$189:$E$196,"No encontrado",0)} -> 7.6091462 | E42: =C42-D42 -> 12.390854 | F42: =('Base de datos transacciones'!$H42)*$D42 -> 121.74634 | G42: ='Base de datos transacciones'!$H42*$C42 -> 320 | H42: =G42-F42 -> 198.25366
A43: {=XLOOKUP($B43,'Maestro de productos 2024'!$A$3:$A$163,'Maestro de productos 2024'!$B$3:$B$163,0)} -> ID-3828 | B43: Muffins de yogurt | C43: {=XLOOKUP(B43,'Maestro de productos 2024'!$B$189:$B$196,'Maestro de productos 2024'!$D$189:$D$196,"No encontrado",0)} -> 20 | D43: {=XLOOKUP(B43,'Maestro de productos 2024'!$B$189:$B$196,'Maestro de productos 2024'!$E$189:$E$196,"No encontrado",0)} -> 7.3010641 | E43: =C43-D43 -> 12.698936 | F43: =('Base de datos transacciones'!$H43)*$D43 -> 175.22554 | G43: ='Base de datos transacciones'!$H43*$C43 -> 480 | H43: =G43-F43 -> 304.77446 | I43: =SUM(G42:G43) -> 800 | J43: =((I43-I41)/I41) -> 0.052631579 | K43: =(I43-(SUM(F42:F43)))/I43 -> 0.62878515 | L43: =I43-(SUM(F42:F43)) -> 503.02812 | M43: =((L43-L41)/L41) -> 0.10037648
A44: {=XLOOKUP($B44,'Maestro de productos 2024'!$A$3:$A$163,'Maestro de productos 2024'!$B$3:$B$163,0)} -> ID-3829 | B44: Besos de nuez | C44: {=XLOOKUP(B44,'Maestro de productos 2024'!$B$189:$B$196,'Maestro de productos 2024'!$D$189:$D$196,"No encontrado",0)} -> 7 | D44: {=XLOOKUP(B44,'Maestro de productos 2024'!$B$189:$B$196,'Maestro de productos 2024'!$E$189:$E$196,"No encontrado",0)} -> 2.9898436 | E44: =C44-D44 -> 4.0101564 | F44: =('Base de datos transacciones'!$H44)*$D44 -> 149.49218 | G44: ='Base de datos transacciones'!$H44*$C44 -> 350 | H44: =G44-F44 -> 200.50782
A45: {=XLOOKUP($B45,'Maestro de productos 2024'!$A$3:$A$163,'Maestro de productos 2024'!$B$3:$B$163,0)} -> ID-3827 | B45: Galletas danesas | C45: {=XLOOKUP(B45,'Maestro de productos 2024'!$B$189:$B$196,'Maestro de productos 2024'!$D$189:$D$196,"No encontrado",0)} -> 7 | D45: {=XLOOKUP(B45,'Maestro de productos 2024'!$B$189:$B$196,'Maestro de productos 2024'!$E$189:$E$196,"No encontrado",0)} -> 2.6234601 | E45: =C45-D45 -> 4.3765399 | F45: =('Base de datos transacciones'!$H45)*$D45 -> 86.574182 | G45: ='Base de datos transacciones'!$H45*$C45 -> 231 | H45: =G45-F45 -> 144.42582 | I45: =SUM(G44:G45) -> 581 | J45: =((I45-I43)/I43) -> -0.27375 | K45: =(I45-(SUM(F44:F45)))/I45 -> 0.59368957 | L45: =I45-(SUM(F44:F45)) -> 344.93364 | M45: =((L45-L43)/L43) -> -0.31428558 | N45: =SUM(G37:G45) -> 3291 | O45: =((N45-N36)/N36) -> 0.12014976 | P45: =(N45-SUM(F37:F45))/N45 -> 0.6148843 | Q45: =N45-(SUM(F37:F45)) -> 2023.5842 | R45: =((Q45-Q36)/Q36) -> 0.11638052
A46: {=XLOOKUP($B46,'Maestro de productos 2024'!$A$3:$A$163,'Maestro de productos 2024'!$B$3:$B$163,0)} -> ID-3824 | B46: Galletas chocochips | C46: {=XLOOKUP(B46,'Maestro de productos 2024'!$B$189:$B$196,'Maestro de productos 2024'!$D$189:$D$196,"No encontrado",0)} -> 10 | D46: {=XLOOKUP(B46,'Maestro de productos 2024'!$B$189:$B$196,'Maestro de productos 2024'!$E$189:$E$196,"No encontrado",0)} -> 3.3375513 | E46: =C46-D46 -> 6.6624487 | F46: =('Base de datos transacciones'!$H46)*$D46 -> 93.451436 | G46: ='Base de datos transacciones'!$H46*$C46 -> 280 | H46: =G46-F46 -> 186.54856
A47: {=XLOOKUP($B47,'Maestro de productos 2024'!$A$3:$A$163,'Maestro de productos 2024'!$B$3:$B$163,0)} -> ID-3825 | B47: Mini cheesecake | C47: {=XLOOKUP(B47,'Maestro de productos 2024'!$B$189:$B$196,'Maestro de productos 2024'!$D$189:$D$196,"No encontrado",0)} -> 20 | D47: {=XLOOKUP(B47,'Maestro de productos 2024'!$B$189:$B$196,'Maestro de productos 2024'!$E$189:$E$196,"No encontrado",0)} -> 7.6091462 | E47: =C47-D47 -> 12.390854 | F47: =('Base de datos transacciones'!$H47)*$D47 -> 106.52805 | G47: ='Base de datos transacciones'!$H47*$C47 -> 280 | H47: =G47-F47 -> 173.47195 | I47: =SUM(G46:G47) -> 560 | J47: =((I47-I45)/I45) -> -0.036144578 | K47: =(I47-(SUM(F46:F47)))/I47 -> 0.64289378 | L47: =I47-(SUM(F46:F47)) -> 360.02052 | M47: =((L47-L45)/L45) -> 0.043738496
A48: {=XLOOKUP($B48,'Maestro de productos 2024'!$A$3:$A$163,'Maestro de productos 2024'!$B$3:$B$163,0)} -> ID-3831 | B48: Muffin de chocolate | C48: {=XLOOKUP(B48,'Maestro de productos 2024'!$B$189:$B$196,'Maestro de productos 2024'!$D$189:$D$196,"No encontrado",0)} -> 20 | D48: {=XLOOKUP(B48,'Maestro de productos 2024'!$B$189:$B$196,'Maestro de productos 2024'!$E$189:$E$196,"No encontrado",0)} -> 7.0549267 | E48: =C48-D48 -> 12.945073 | F48: =('Base de datos transacciones'!$H48)*$D48 -> 197.53795 | G48: ='Base de datos transacciones'!$H48*$C48 -> 560 | H48: =G48-F48 -> 362.46205
A49: {=XLOOKUP($B49,'Maestro de productos 2024'!$A$3:$A$163,'Maestro de productos 2024'!$B$3:$B$163,0)} -> ID-3826 | B49: Brownie triple chocolate | C49: {=XLOOKUP(B49,'Maestro de productos 2024'!$B$189:$B$196,'Maestro de productos 2024'!$D$189:$D$196,"No encontrado",0)} -> 20 | D49: {=XLOOKUP(B49,'Maestro de productos 2024'!$B$189:$B$196,'Maestro de productos 2024'!$E$189:$E$196,"No encontrado",0)} -> 7.1039722 | E49: =C49-D49 -> 12.896028 | F49: =('Base de datos transacciones'!$H49)*$D49 -> 127.8715 | G49: ='Base de datos transacciones'!$H49*$C49 -> 360 | H49: =G49-F49 -> 232.1285 | I49: =SUM(G48:G49) -> 920 | J49: =((I49-I47)/I47) -> 0.64285714 | K49: =(I49-(SUM(F48:F49)))/I49 -> 0.64629408 | L49: =I49-(SUM(F48:F49)) -> 594.59055 | M49: =((L49-L47)/L47) -> 0.6515463
A50: {=XLOOKUP($B50,'Maestro de productos 2024'!$A$3:$A$163,'Maestro de productos 2024'!$B$3:$B$163,0)} -> ID-3828 | B50: Muffins de yogurt | C50: {=XLOOKUP(B50,'Maestro de productos 2024'!$B$189:$B$196,'Maestro de productos 2024'!$D$189:$D$196,"No encontrado",0)} -> 20 | D50: {=XLOOKUP(B50,'Maestro de productos 2024'!$B$189:$B$196,'Maestro de productos 2024'!$E$189:$E$196,"No encontrado",0)} -> 7.3010641 | E50: =C50-D50 -> 12.698936 | F50: =('Base de datos transacciones'!$H50)*$D50 -> 87.612769 | G50: ='Base de datos transacciones'!$H50*$C50 -> 240 | H50: =G50-F50 -> 152.38723
A51: {=XLOOKUP($B51,'Maestro de productos 2024'!$A$3:$A$163,'Maestro de productos 2024'!$B$3:$B$163,0)} -> ID-3827 | B51: Galletas danesas | C51: {=XLOOKUP(B51,'Maestro de productos 2024'!$B$189:$B$196,'Maestro de productos 2024'!$D$189:$D$196,"No encontrado",0)} -> 7 | D51: {=XLOOKUP(B51,'Maestro de productos 2024'!$B$189:$B$196,'Maestro de productos 2024'!$E$189:$E$196,"No encontrado",0)} -> 2.6234601 | E51: =C51-D51 -> 4.3765399 | F51: =('Base de datos transacciones'!$H51)*$D51 -> 78.703802 | G51: ='Base de datos transacciones'!$H51*$C51 -> 210 | H51: =G51-F51 -> 131.2962 | I51: =SUM(G50:G51) -> 450 | J51: =((I51-I49)/I49) -> -0.51086957 | K51: =(I51-(SUM(F50:F51)))/I51 -> 0.63040762 | L51: =I51-(SUM(F50:F51)) -> 283.68343 | M51: =((L51-L49)/L49) -> -0.52289281
A52: {=XLOOKUP($B52,'Maestro de productos 2024'!$A$3:$A$163,'Maestro de productos 2024'!$B$3:$B$163,0)} -> ID-3824 | B52: Galletas chocochips | C52: {=XLOOKUP(B52,'Maestro de productos 2024'!$B$189:$B$196,'Maestro de productos 2024'!$D$189:$D$196,"No encontrado",0)} -> 10 | D52: {=XLOOKUP(B52,'Maestro de productos 2024'!$B$189:$B$196,'Maestro de productos 2024'!$E$189:$E$196,"No encontrado",0)} -> 3.3375513 | E52: =C52-D52 -> 6.6624487 | F52: =('Base de datos transacciones'!$H52)*$D52 -> 106.80164 | G52: ='Base de datos transacciones'!$H52*$C52 -> 320 | H52: =G52-F52 -> 213.19836
A53: {=XLOOKUP($B53,'Maestro de productos 2024'!$A$3:$A$163,'Maestro de productos 2024'!$B$3:$B$163,0)} -> ID-3830 | B53: Flan de queso crema | C53: {=XLOOKUP(B53,'Maestro de productos 2024'!$B$189:$B$196,'Maestro de productos 2024'!$D$189:$D$196,"No encontrado",0)} -> 25 | D53: {=XLOOKUP(B53,'Maestro de productos 2024'!$B$189:$B$196,'Maestro de productos 2024'!$E$189:$E$196,"No encontrado",0)} -> 10.936667 | E53: =C53-D53 -> 14.063333 | F53: =('Base de datos transacciones'!$H53)*$D53 -> 164.05 | G53: ='Base de datos transacciones'!$H53*$C53 -> 375 | H53: =G53-F53 -> 210.95 | I53: =SUM(G52:G53) -> 695 | J53: =((I53-I51)/I51) -> 0.54444444 | K53: =(I53-(SUM(F52:F53)))/I53 -> 0.61028541 | L53: =I53-(SUM(F52:F53)) -> 424.14836 | M53: =((L53-L51)/L51) -> 0.49514676 | N53: =SUM(G46:G53) -> 2625 | O53: =((N53-N45)/N45) -> -0.2023701 | P53: =(N53-SUM(F46:F53))/N53 -> 0.63331156 | Q53: =N53-(SUM(F46:F53)) -> 1662.4429 | R53: =((Q53-Q45)/Q45) -> -0.17846619
A54: {=XLOOKUP($B54,'Maestro de productos 2024'!$A$3:$A$163,'Maestro de productos 2024'!$B$3:$B$163,0)} -> ID-3829 | B54: Besos de nuez | C54: {=XLOOKUP(B54,'Maestro de productos 2024'!$B$189:$B$196,'Maestro de productos 2024'!$D$189:$D$196,"No encontrado",0)} -> 7 | D54: {=XLOOKUP(B54,'Maestro de productos 2024'!$B$189:$B$196,'Maestro de productos 2024'!$E$189:$E$196,"No encontrado",0)} -> 2.9898436 | E54: =C54-D54 -> 4.0101564 | F54: =('Base de datos transacciones'!$H54)*$D54 -> 143.51249 | G54: ='Base de datos transacciones'!$H54*$C54 -> 336 | H54: =G54-F54 -> 192.48751
A55: {=XLOOKUP($B55,'Maestro de productos 2024'!$A$3:$A$163,'Maestro de productos 2024'!$B$3:$B$163,0)} -> ID-3824 | B55: Galletas chocochips | C55: {=XLOOKUP(B55,'Maestro de productos 2024'!$B$189:$B$196,'Maestro de productos 2024'!$D$189:$D$196,"No encontrado",0)} -> 10 | D55: {=XLOOKUP(B55,'Maestro de productos 2024'!$B$189:$B$196,'Maestro de productos 2024'!$E$189:$E$196,"No encontrado",0)} -> 3.3375513 | E55: =C55-D55 -> 6.6624487 | F55: =('Base de datos transacciones'!$H55)*$D55 -> 106.80164 | G55: ='Base de datos transacciones'!$H55*$C55 -> 320 | H55: =G55-F55 -> 213.19836 | I55: =SUM(G54:G55) -> 656 | J55: =((I55-I53)/I53) -> -0.056115108 | K55: =(I55-(SUM(F54:F55)))/I55 -> 0.61842358 | L55: =I55-(SUM(F54:F55)) -> 405.68587 | M55: =((L55-L53)/L53) -> -0.043528383
A56: {=XLOOKUP($B56,'Maestro de productos 2024'!$A$3:$A$163,'Maestro de productos 2024'!$B$3:$B$163,0)} -> ID-3828 | B56: Muffins de yogurt | C56: {=XLOOKUP(B56,'Maestro de productos 2024'!$B$189:$B$196,'Maestro de productos 2024'!$D$189:$D$196,"No encontrado",0)} -> 20 | D56: {=XLOOKUP(B56,'Maestro de productos 2024'!$B$189:$B$196,'Maestro de productos 2024'!$E$189:$E$196,"No encontrado",0)} -> 7.3010641 | E56: =C56-D56 -> 12.698936 | F56: =('Base de datos transacciones'!$H56)*$D56 -> 175.22554 | G56: ='Base de datos transacciones'!$H56*$C56 -> 480 | H56: =G56-F56 -> 304.77446
A57: {=XLOOKUP($B57,'Maestro de productos 2024'!$A$3:$A$163,'Maestro de productos 2024'!$B$3:$B$163,0)} -> ID-3826 | B57: Brownie triple chocolate | C57: {=XLOOKUP(B57,'Maestro de productos 2024'!$B$189:$B$196,'Maestro de productos 2024'!$D$189:$D$196,"No encontrado",0)} -> 20 | D57: {=XLOOKUP(B57,'Maestro de productos 2024'!$B$189:$B$196,'Maestro de productos 2024'!$E$189:$E$196,"No encontrado",0)} -> 7.1039722 | E57: =C57-D57 -> 12.896028 | F57: =('Base de datos transacciones'!$H57)*$D57 -> 127.8715 | G57: ='Base de datos transacciones'!$H57*$C57 -> 360 | H57: =G57-F57 -> 232.1285 | I57: =SUM(G56:G57) -> 840 | J57: =((I57-I55)/I55) -> 0.2804878 | K57: =(I57-(SUM(F56:F57)))/I57 -> 0.63917019 | L57: =I57-(SUM(F56:F57)) -> 536.90296 | M57: =((L57-L55)/L55) -> 0.32344507
A58: {=XLOOKUP($B58,'Maestro de productos 2024'!$A$3:$A$163,'Maestro de productos 2024'!$B$3:$B$163,0)} -> ID-3828 | B58: Muffins de yogurt | C58: {=XLOOKUP(B58,'Maestro de productos 2024'!$B$189:$B$196,'Maestro de productos 2024'!$D$189:$D$196,"No encontrado",0)} -> 20 | D58: {=XLOOKUP(B58,'Maestro de productos 2024'!$B$189:$B$196,'Maestro de productos 2024'!$E$189:$E$196,"No encontrado",0)} -> 7.3010641 | E58: =C58-D58 -> 12.698936 | F58: =('Base de datos transacciones'!$H58)*$D58 -> 87.612769 | G58: ='Base de datos transacciones'!$H58*$C58 -> 240 | H58: =G58-F58 -> 152.38723
A59: {=XLOOKUP($B59,'Maestro de productos 2024'!$A$3:$A$163,'Maestro de productos 2024'!$B$3:$B$163,0)} -> ID-3824 | B59: Galletas chocochips | C59: {=XLOOKUP(B59,'Maestro de productos 2024'!$B$189:$B$196,'Maestro de productos 2024'!$D$189:$D$196,"No encontrado",0)} -> 10 | D59: {=XLOOKUP(B59,'Maestro de productos 2024'!$B$189:$B$196,'Maestro de productos 2024'!$E$189:$E$196,"No encontrado",0)} -> 3.3375513 | E59: =C59-D59 -> 6.6624487 | F59: =('Base de datos transacciones'!$H59)*$D59 -> 106.80164 | G59: ='Base de datos transacciones'!$H59*$C59 -> 320 | H59: =G59-F59 -> 213.19836 | I59: =SUM(G58:G59) -> 560 | J59: =((I59-I57)/I57) -> -0.33333333 | K59: =(I59-(SUM(F58:F59)))/I59 -> 0.65283141 | L59: =I59-(SUM(F58:F59)) -> 365.58559 | M59: =((L59-L57)/L57) -> -0.31908442
A60: {=XLOOKUP($B60,'Maestro de productos 2024'!$A$3:$A$163,'Maestro de productos 2024'!$B$3:$B$163,0)} -> ID-3829 | B60: Besos de nuez | C60: {=XLOOKUP(B60,'Maestro de productos 2024'!$B$189:$B$196,'Maestro de productos 2024'!$D$189:$D$196,"No encontrado",0)} -> 7 | D60: {=XLOOKUP(B60,'Maestro de productos 2024'!$B$189:$B$196,'Maestro de productos 2024'!$E$189:$E$196,"No encontrado",0)} -> 2.9898436 | E60: =C60-D60 -> 4.0101564 | F60: =('Base de datos transacciones'!$H60)*$D60 -> 143.51249 | G60: ='Base de datos transacciones'!$H60*$C60 -> 336 | H60: =G60-F60 -> 192.48751
A61: {=XLOOKUP($B61,'Maestro de productos 2024'!$A$3:$A$163,'Maestro de productos 2024'!$B$3:$B$163,0)} -> ID-3825 | B61: Mini cheesecake | C61: {=XLOOKUP(B61,'Maestro de productos 2024'!$B$189:$B$196,'Maestro de productos 2024'!$D$189:$D$196,"No encontrado",0)} -> 20 | D61: {=XLOOKUP(B61,'Maestro de productos 2024'!$B$189:$B$196,'Maestro de productos 2024'!$E$189:$E$196,"No encontrado",0)} -> 7.6091462 | E61: =C61-D61 -> 12.390854 | F61: =('Base de datos transacciones'!$H61)*$D61 -> 121.74634 | G61: ='Base de datos transacciones'!$H61*$C61 -> 320 | H61: =G61-F61 -> 198.25366 | I61: =SUM(G60:G61) -> 656 | J61: =((I61-I59)/I59) -> 0.17142857 | K61: =(I61-(SUM(F60:F61)))/I61 -> 0.59564202 | L61: =I61-(SUM(F60:F61)) -> 390.74117 | M61: =((L61-L59)/L59) -> 0.068808998
A62: {=XLOOKUP($B62,'Maestro de productos 2024'!$A$3:$A$163,'Maestro de productos 2024'!$B$3:$B$163,0)} -> ID-3824 | B62: Galletas chocochips | C62: {=XLOOKUP(B62,'Maestro de productos 2024'!$B$189:$B$196,'Maestro de productos 2024'!$D$189:$D$196,"No encontrado",0)} -> 10 | D62: {=XLOOKUP(B62,'Maestro de productos 2024'!$B$189:$B$196,'Maestro de productos 2024'!$E$189:$E$196,"No encontrado",0)} -> 3.3375513 | E62: =C62-D62 -> 6.6624487 | F62: =('Base de datos transacciones'!$H62)*$D62 -> 100.12654 | G62: ='Base de datos transacciones'!$H62*$C62 -> 300 | H62: =G62-F62 -> 199.87346 | N62: =SUM(G54:G62) -> 3012 | O62: =((N62-N53)/N53) -> 0.14742857 | P62: =(N62-SUM(F54:F62))/N62 -> 0.63040805 | Q62: =N62-(SUM(F54:F62)) -> 1898.789 | R62: =((Q62-Q53)/Q53) -> 0.14216801
A63: {=XLOOKUP($B63,'Maestro de productos 2024'!$A$3:$A$163,'Maestro de productos 2024'!$B$3:$B$163,0)} -> ID-3828 | B63: Muffins de yogurt | C63: {=XLOOKUP(B63,'Maestro de productos 2024'!$B$189:$B$196,'Maestro de productos 2024'!$D$189:$D$196,"No encontrado",0)} -> 20 | D63: {=XLOOKUP(B63,'Maestro de productos 2024'!$B$189:$B$196,'Maestro de productos 2024'!$E$189:$E$196,"No encontrado",0)} -> 7.3010641 | E63: =C63-D63 -> 12.698936 | F63: =('Base de datos transacciones'!$H63)*$D63 -> 175.22554 | G63: ='Base de datos transacciones'!$H63*$C63 -> 480 | H63: =G63-F63 -> 304.77446 | I63: =SUM(G62:G63) -> 780 | J63: =((I63-I61)/I61) -> 0.18902439 | K63: =(I63-(SUM(F62:F63)))/I63 -> 0.64698452 | L63: =I63-(SUM(F62:F63)) -> 504.64792 | M63: =((L63-L61)/L61) -> 0.2915146
A64: {=XLOOKUP($B64,'Maestro de productos 2024'!$A$3:$A$163,'Maestro de productos 2024'!$B$3:$B$163,0)} -> ID-3827 | B64: Galletas danesas | C64: {=XLOOKUP(B64,'Maestro de productos 2024'!$B$189:$B$196,'Maestro de productos 2024'!$D$189:$D$196,"No encontrado",0)} -> 7 | D64: {=XLOOKUP(B64,'Maestro de productos 2024'!$B$189:$B$196,'Maestro de productos 2024'!$E$189:$E$196,"No encontrado",0)} -> 2.6234601 | E64: =C64-D64 -> 4.3765399 | F64: =('Base de datos transacciones'!$H64)*$D64 -> 86.574182 | G64: ='Base de datos transacciones'!$H64*$C64 -> 231 | H64: =G64-F64 -> 144.42582
A65: {=XLOOKUP($B65,'Maestro de productos 2024'!$A$3:$A$163,'Maestro de productos 2024'!$B$3:$B$163,0)} -> ID-3826 | B65: Brownie triple chocolate | C65: {=XLOOKUP(B65,'Maestro de productos 2024'!$B$189:$B$196,'Maestro de productos 2024'!$D$189:$D$196,"No encontrado",0)} -> 20 | D65: {=XLOOKUP(B65,'Maestro de productos 2024'!$B$189:$B$196,'Maestro de productos 2024'!$E$189:$E$196,"No encontrado",0)} -> 7.1039722 | E65: =C65-D65 -> 12.896028 | F65: =('Base de datos transacciones'!$H65)*$D65 -> 127.8715 | G65: ='Base de datos transacciones'!$H65*$C65 -> 360 | H65: =G65-F65 -> 232.1285 | I65: =SUM(G64:G65) -> 591 | J65: =((I65-I63)/I63) -> -0.24230769 | K65: =(I65-(SUM(F64:F65)))/I65 -> 0.63714775 | L65: =I65-(SUM(F64:F65)) -> 376.55432 | M65: =((L65-L63)/L63) -> -0.25382767
A66: {=XLOOKUP($B66,'Maestro de productos 2024'!$A$3:$A$163,'Maestro de productos 2024'!$B$3:$B$163,0)} -> ID-3831 | B66: Muffin de chocolate | C66: {=XLOOKUP(B66,'Maestro de productos 2024'!$B$189:$B$196,'Maestro de productos 2024'!$D$189:$D$196,"No encontrado",0)} -> 20 | D66: {=XLOOKUP(B66,'Maestro de productos 2024'!$B$189:$B$196,'Maestro de productos 2024'!$E$189:$E$196,"No encontrado",0)} -> 7.0549267 | E66: =C66-D66 -> 12.945073 | F66: =('Base de datos transacciones'!$H66)*$D66 -> 98.768974 | G66: ='Base de datos transacciones'!$H66*$C66 -> 280 | H66: =G66-F66 -> 181.23103
A67: {=XLOOKUP($B67,'Maestro de productos 2024'!$A$3:$A$163,'Maestro de productos 2024'!$B$3:$B$163,0)} -> ID-3828 | B67: Muffins de yogurt | C67: {=XLOOKUP(B67,'Maestro de productos 2024'!$B$189:$B$196,'Maestro de productos 2024'!$D$189:$D$196,"No encontrado",0)} -> 20 | D67: {=XLOOKUP(B67,'Maestro de productos 2024'!$B$189:$B$196,'Maestro de productos 2024'!$E$189:$E$196,"No encontrado",0)} -> 7.3010641 | E67: =C67-D67 -> 12.698936 | F67: =('Base de datos transacciones'!$H67)*$D67 -> 175.22554 | G67: ='Base de datos transacciones'!$H67*$C67 -> 480 | H67: =G67-F67 -> 304.77446 | I67: =SUM(G66:G67) -> 760 | J67: =((I67-I65)/I65) -> 0.28595601 | K67: =(I67-(SUM(F66:F67)))/I67 -> 0.6394809 | L67: =I67-(SUM(F66:F67)) -> 486.00549 | M67: =((L67-L65)/L65) -> 0.29066502
A68: {=XLOOKUP($B68,'Maestro de productos 2024'!$A$3:$A$163,'Maestro de productos 2024'!$B$3:$B$163,0)} -> ID-3824 | B68: Galletas chocochips | C68: {=XLOOKUP(B68,'Maestro de productos 2024'!$B$189:$B$196,'Maestro de productos 2024'!$D$189:$D$196,"No encontrado",0)} -> 10 | D68: {=XLOOKUP(B68,'Maestro de productos 2024'!$B$189:$B$196,'Maestro de productos 2024'!$E$189:$E$196,"No encontrado",0)} -> 3.3375513 | E68: =C68-D68 -> 6.6624487 | F68: =('Base de datos transacciones'!$H68)*$D68 -> 106.80164 | G68: ='Base de datos transacciones'!$H68*$C68 -> 320 | H68: =G68-F68 -> 213.19836
A69: {=XLOOKUP($B69,'Maestro de productos 2024'!$A$3:$A$163,'Maestro de productos 2024'!$B$3:$B$163,0)} -> ID-3830 | B69: Flan de queso crema | C69: {=XLOOKUP(B69,'Maestro de productos 2024'!$B$189:$B$196,'Maestro de productos 2024'!$D$189:$D$196,"No encontrado",0)} -> 25 | D69: {=XLOOKUP(B69,'Maestro de productos 2024'!$B$189:$B$196,'Maestro de productos 2024'!$E$189:$E$196,"No encontrado",0)} -> 10.936667 | E69: =C69-D69 -> 14.063333 | F69: =('Base de datos transacciones'!$H69)*$D69 -> 196.86 | G69: ='Base de datos transacciones'!$H69*$C69 -> 450 | H69: =G69-F69 -> 253.14 | I69: =SUM(G68:G69) -> 770 | J69: =((I69-I67)/I67) -> 0.013157895 | K69: =(I69-(SUM(F68:F69)))/I69 -> 0.60563423 | L69: =I69-(SUM(F68:F69)) -> 466.33836 | M69: =((L69-L67)/L67) -> -0.040466885
A70: {=XLOOKUP($B70,'Maestro de productos 2024'!$A$3:$A$163,'Maestro de productos 2024'!$B$3:$B$163,0)} -> ID-3828 | B70: Muffins de yogurt | C70: {=XLOOKUP(B70,'Maestro de productos 2024'!$B$189:$B$196,'Maestro de productos 2024'!$D$189:$D$196,"No encontrado",0)} -> 20 | D70: {=XLOOKUP(B70,'Maestro de productos 2024'!$B$189:$B$196,'Maestro de productos 2024'!$E$189:$E$196,"No encontrado",0)} -> 7.3010641 | E70: =C70-D70 -> 12.698936 | F70: =('Base de datos transacciones'!$H70)*$D70 -> 87.612769 | G70: ='Base de datos transacciones'!$H70*$C70 -> 240 | H70: =G70-F70 -> 152.38723
A71: {=XLOOKUP($B71,'Maestro de productos 2024'!$A$3:$A$163,'Maestro de productos 2024'!$B$3:$B$163,0)} -> ID-3825 | B71: Mini cheesecake | C71: {=XLOOKUP(B71,'Maestro de productos 2024'!$B$189:$B$196,'Maestro de productos 2024'!$D$189:$D$196,"No encontrado",0)} -> 20 | D71: {=XLOOKUP(B71,'Maestro de productos 2024'!$B$189:$B$196,'Maestro de productos 2024'!$E$189:$E$196,"No encontrado",0)} -> 7.6091462 | E71: =C71-D71 -> 12.390854 | F71: =('Base de datos transacciones'!$H71)*$D71 -> 114.13719 | G71: ='Base de datos transacciones'!$H71*$C71 -> 300 | H71: =G71-F71 -> 185.86281 | I71: =SUM(G70:G71) -> 540 | J71: =((I71-I69)/I69) -> -0.2987013 | K71: =(I71-(SUM(F70:F71)))/I71 -> 0.62638896 | L71: =I71-(SUM(F70:F71)) -> 338.25004 | M71: =((L71-L69)/L69) -> -0.27466821 | N71: =SUM(G63:G71) -> 3141 | O71: =((N71-N62)/N62) -> 0.042828685 | P71: =(N71-SUM(F63:F71))/N71 -> 0.62780091 | Q71: =N71-(SUM(F63:F71)) -> 1971.9227 | R71: =((Q71-Q62)/Q62) -> 0.038515924
A72: {=XLOOKUP($B72,'Maestro de productos 2024'!$A$3:$A$163,'Maestro de productos 2024'!$B$3:$B$163,0)} -> ID-3829 | B72: Besos de nuez | C72: {=XLOOKUP(B72,'Maestro de productos 2024'!$B$189:$B$196,'Maestro de productos 2024'!$D$189:$D$196,"No encontrado",0)} -> 7 | D72: {=XLOOKUP(B72,'Maestro de productos 2024'!$B$189:$B$196,'Maestro de productos 2024'!$E$189:$E$196,"No encontrado",0)} -> 2.9898436 | E72: =C72-D72 -> 4.0101564 | F72: =('Base de datos transacciones'!$H72)*$D72 -> 128.56327 | G72: ='Base de datos transacciones'!$H72*$C72 -> 301 | H72: =G72-F72 -> 172.43673
A73: {=XLOOKUP($B73,'Maestro de productos 2024'!$A$3:$A$163,'Maestro de productos 2024'!$B$3:$B$163,0)} -> ID-3824 | B73: Galletas chocochips | C73: {=XLOOKUP(B73,'Maestro de productos 2024'!$B$189:$B$196,'Maestro de productos 2024'!$D$189:$D$196,"No encontrado",0)} -> 10 | D73: {=XLOOKUP(B73,'Maestro de productos 2024'!$B$189:$B$196,'Maestro de productos 2024'!$E$189:$E$196,"No encontrado",0)} -> 3.3375513 | E73: =C73-D73 -> 6.6624487 | F73: =('Base de datos transacciones'!$H73)*$D73 -> 106.80164 | G73: ='Base de datos transacciones'!$H73*$C73 -> 320 | H73: =G73-F73 -> 213.19836 | I73: =SUM(G72:G73) -> 621 | J73: =((I73-I71)/I71) -> 0.15 | K73: =(I73-(SUM(F72:F73)))/I73 -> 0.62099047 | L73: =I73-(SUM(F72:F73)) -> 385.63508 | M73: =((L73-L71)/L71) -> 0.14008882
A74: {=XLOOKUP($B74,'Maestro de productos 2024'!$A$3:$A$163,'Maestro de productos 2024'!$B$3:$B$163,0)} -> ID-3826 | B74: Brownie triple chocolate | C74: {=XLOOKUP(B74,'Maestro de productos 2024'!$B$189:$B$196,'Maestro de productos 2024'!$D$189:$D$196,"No encontrado",0)} -> 20 | D74: {=XLOOKUP(B74,'Maestro de productos 2024'!$B$189:$B$196,'Maestro de productos 2024'!$E$189:$E$196,"No encontrado",0)} -> 7.1039722 | E74: =C74-D74 -> 12.896028 | F74: =('Base de datos transacciones'!$H74)*$D74 -> 127.8715 | G74: ='Base de datos transacciones'!$H74*$C74 -> 360 | H74: =G74-F74 -> 232.1285
A75: {=XLOOKUP($B75,'Maestro de productos 2024'!$A$3:$A$163,'Maestro de productos 2024'!$B$3:$B$163,0)} -> ID-3829 | B75: Besos de nuez | C75: {=XLOOKUP(B75,'Maestro de productos 2024'!$B$189:$B$196,'Maestro de productos 2024'!$D$189:$D$196,"No encontrado",0)} -> 7 | D75: {=XLOOKUP(B75,'Maestro de productos 2024'!$B$189:$B$196,'Maestro de productos 2024'!$E$189:$E$196,"No encontrado",0)} -> 2.9898436 | E75: =C75-D75 -> 4.0101564 | F75: =('Base de datos transacciones'!$H75)*$D75 -> 149.49218 | G75: ='Base de datos transacciones'!$H75*$C75 -> 350 | H75: =G75-F75 -> 200.50782 | I75: =SUM(G74:G75) -> 710 | J75: =((I75-I73)/I73) -> 0.14331723 | K75: =(I75-(SUM(F74:F75)))/I75 -> 0.60934693 | L75: =I75-(SUM(F74:F75)) -> 432.63632 | M75: =((L75-L73)/L73) -> 0.12188008
A76: {=XLOOKUP($B76,'Maestro de productos 2024'!$A$3:$A$163,'Maestro de productos 2024'!$B$3:$B$163,0)} -> ID-3828 | B76: Muffins de yogurt | C76: {=XLOOKUP(B76,'Maestro de productos 2024'!$B$189:$B$196,'Maestro de productos 2024'!$D$189:$D$196,"No encontrado",0)} -> 20 | D76: {=XLOOKUP(B76,'Maestro de productos 2024'!$B$189:$B$196,'Maestro de productos 2024'!$E$189:$E$196,"No encontrado",0)} -> 7.3010641 | E76: =C76-D76 -> 12.698936 | F76: =('Base de datos transacciones'!$H76)*$D76 -> 175.22554 | G76: ='Base de datos transacciones'!$H76*$C76 -> 480 | H76: =G76-F76 -> 304.77446
A77: {=XLOOKUP($B77,'Maestro de productos 2024'!$A$3:$A$163,'Maestro de productos 2024'!$B$3:$B$163,0)} -> ID-3830 | B77: Flan de queso crema | C77: {=XLOOKUP(B77,'Maestro de productos 2024'!$B$189:$B$196,'Maestro de productos 2024'!$D$189:$D$196,"No encontrado",0)} -> 25 | D77: {=XLOOKUP(B77,'Maestro de productos 2024'!$B$189:$B$196,'Maestro de productos 2024'!$E$189:$E$196,"No encontrado",0)} -> 10.936667 | E77: =C77-D77 -> 14.063333 | F77: =('Base de datos transacciones'!$H77)*$D77 -> 174.98667 | G77: ='Base de datos transacciones'!$H77*$C77 -> 400 | H77: =G77-F77 -> 225.01333 | I77: =SUM(G76:G77) -> 880 | J77: =((I77-I75)/I75) -> 0.23943662 | K77: =(I77-(SUM(F76:F77)))/I77 -> 0.60203159 | L77: =I77-(SUM(F76:F77)) -> 529.78779 | M77: =((L77-L75)/L75) -> 0.22455691
A78: {=XLOOKUP($B78,'Maestro de productos 2024'!$A$3:$A$163,'Maestro de productos 2024'!$B$3:$B$163,0)} -> ID-3825 | B78: Mini cheesecake | C78: {=XLOOKUP(B78,'Maestro de productos 2024'!$B$189:$B$196,'Maestro de productos 2024'!$D$189:$D$196,"No encontrado",0)} -> 20 | D78: {=XLOOKUP(B78,'Maestro de productos 2024'!$B$189:$B$196,'Maestro de productos 2024'!$E$189:$E$196,"No encontrado",0)} -> 7.6091462 | E78: =C78-D78 -> 12.390854 | F78: =('Base de datos transacciones'!$H78)*$D78 -> 121.74634 | G78: ='Base de datos transacciones'!$H78*$C78 -> 320 | H78: =G78-F78 -> 198.25366 | I78: =SUM(G78) -> 320 | J78: =(I78-I77)/I77 -> -0.63636364 | K78: =(I78-(SUM(F78)))/I78 -> 0.61954269 | L78: =I78-(SUM(F78)) -> 198.25366 | M78: =((L78-L77)/L77) -> -0.62578666 | N78: =SUM(G72:G78) -> 2531 | O78: =((N78-N71)/N71) -> -0.19420567 | P78: =(N78-SUM(F72:F78))/N78 -> 0.61094937 | Q78: =N78-(SUM(F72:F78)) -> 1546.3129 | R78: =((Q78-Q71)/Q71) -> -0.21583494 | S78: =SUM(G2:G78) -> 27591 | U78: =(S78-(SUM(F2:F78)))/S78 -> 0.62954606 | V78: =S78-(SUM(F2:F78)) -> 17369.805
A79: ID | B79: Producto | C79: PV | D79: CV | E79: MU | F79: TotalCV | G79: IT | H79: UB | I79: IT(semanal) | J79: VariacionWoW(I) | N79: IT(Mensual) | O79: VariacionMoM(I) | P79: MGB(Mensual) | Q79: UB(mensual) | R79: VariacionMoM(UB) | S79: IT(Anual) | T79: VariacionYoY(I) | U79: MGB(anual) | V79: UB(anual) | W79: VariacioYoY(UB)
A80: {=XLOOKUP($B80,'Maestro de productos 2024'!$A$3:$A$163,'Maestro de productos 2024'!$B$3:$B$163,0)} -> ID-3828 | B80: Muffins de yogurt | C80: {=XLOOKUP(B80,'Maestro de productos 2025'!$B$189:$B$196,'Maestro de productos 2025'!$D$189:$D$196,"No encontrado",0)} -> 21 | D80: {=XLOOKUP(B80,'Maestro de productos 2025'!$B$189:$B$196,'Maestro de productos 2025'!$E$189:$E$196,"No encontrado",0)} -> 8.3593511 | E80: =C80-D80 -> 12.640649 | F80: =('Base de datos transacciones'!$H80)*$D80 -> 200.62443 | G80: ='Base de datos transacciones'!$H80*$C80 -> 504 | H80: =G80-F80 -> 303.37557 | I80: =SUM(G80) -> 504 | J80: =(I80-I78)/I78 -> 0.575 | K80: =(I80-(SUM(F80)))/I80 -> 0.60193566 | L80: =I80-(SUM(F80)) -> 303.37557 | M80: =((L80-L78)/L78) -> 0.53023945
A81: {=XLOOKUP($B81,'Maestro de productos 2024'!$A$3:$A$163,'Maestro de productos 2024'!$B$3:$B$163,0)} -> ID-3831 | B81: Muffin de chocolate | C81: {=XLOOKUP(B81,'Maestro de productos 2025'!$B$189:$B$196,'Maestro de productos 2025'!$D$189:$D$196,"No encontrado",0)} -> 20 | D81: {=XLOOKUP(B81,'Maestro de productos 2025'!$B$189:$B$196,'Maestro de productos 2025'!$E$189:$E$196,"No encontrado",0)} -> 7.8897601 | E81: =C81-D81 -> 12.11024 | F81: =('Base de datos transacciones'!$H81)*$D81 -> 110.45664 | G81: ='Base de datos transacciones'!$H81*$C81 -> 280 | H81: =G81-F81 -> 169.54336
A82: {=XLOOKUP($B82,'Maestro de productos 2024'!$A$3:$A$163,'Maestro de productos 2024'!$B$3:$B$163,0)} -> ID-3825 | B82: Mini cheesecake | C82: {=XLOOKUP(B82,'Maestro de productos 2025'!$B$189:$B$196,'Maestro de productos 2025'!$D$189:$D$196,"No encontrado",0)} -> 25 | D82: {=XLOOKUP(B82,'Maestro de productos 2025'!$B$189:$B$196,'Maestro de productos 2025'!$E$189:$E$196,"No encontrado",0)} -> 10.264506 | E82: =C82-D82 -> 14.735494 | F82: =('Base de datos transacciones'!$H82)*$D82 -> 164.2321 | G82: ='Base de datos transacciones'!$H82*$C82 -> 400 | H82: =G82-F82 -> 235.7679 | I82: =SUM(G81:G82) -> 680 | J82: =((I82-I80)/I80) -> 0.34920635 | K82: =(I82-(SUM(F81:F82)))/I82 -> 0.59604596 | L82: =I82-(SUM(F81:F82)) -> 405.31126 | M82: =((L82-L80)/L80) -> 0.33600491
A83: {=XLOOKUP($B83,'Maestro de productos 2024'!$A$3:$A$163,'Maestro de productos 2024'!$B$3:$B$163,0)} -> ID-3824 | B83: Galletas chocochips | C83: {=XLOOKUP(B83,'Maestro de productos 2025'!$B$189:$B$196,'Maestro de productos 2025'!$D$189:$D$196,"No encontrado",0)} -> 10 | D83: {=XLOOKUP(B83,'Maestro de productos 2025'!$B$189:$B$196,'Maestro de productos 2025'!$E$189:$E$196,"No encontrado",0)} -> 4.071744 | E83: =C83-D83 -> 5.928256 | F83: =('Base de datos transacciones'!$H83)*$D83 -> 101.7936 | G83: ='Base de datos transacciones'!$H83*$C83 -> 250 | H83: =G83-F83 -> 148.2064
A84: {=XLOOKUP($B84,'Maestro de productos 2024'!$A$3:$A$163,'Maestro de productos 2024'!$B$3:$B$163,0)} -> ID-3829 | B84: Besos de nuez | C84: {=XLOOKUP(B84,'Maestro de productos 2025'!$B$189:$B$196,'Maestro de productos 2025'!$D$189:$D$196,"No encontrado",0)} -> 9 | D84: {=XLOOKUP(B84,'Maestro de productos 2025'!$B$189:$B$196,'Maestro de productos 2025'!$E$189:$E$196,"No encontrado",0)} -> 3.6108686 | E84: =C84-D84 -> 5.3891314 | F84: =('Base de datos transacciones'!$H84)*$D84 -> 162.48909 | G84: ='Base de datos transacciones'!$H84*$C84 -> 405 | H84: =G84-F84 -> 242.51091 | I84: =SUM(G83:G84) -> 655 | J84: =((I84-I82)/I82) -> -0.036764706 | K84: =(I84-(SUM(F83:F84)))/I84 -> 0.59651498 | L84: =I84-(SUM(F83:F84)) -> 390.71731 | M84: =((L84-L82)/L82) -> -0.036006753
A85: {=XLOOKUP($B85,'Maestro de productos 2024'!$A$3:$A$163,'Maestro de productos 2024'!$B$3:$B$163,0)} -> ID-3828 | B85: Muffins de yogurt | C85: {=XLOOKUP(B85,'Maestro de productos 2025'!$B$189:$B$196,'Maestro de productos 2025'!$D$189:$D$196,"No encontrado",0)} -> 21 | D85: {=XLOOKUP(B85,'Maestro de productos 2025'!$B$189:$B$196,'Maestro de productos 2025'!$E$189:$E$196,"No encontrado",0)} -> 8.3593511 | E85: =C85-D85 -> 12.640649 | F85: =('Base de datos transacciones'!$H85)*$D85 -> 100.31221 | G85: ='Base de datos transacciones'!$H85*$C85 -> 252 | H85: =G85-F85 -> 151.68779
A86: {=XLOOKUP($B86,'Maestro de productos 2024'!$A$3:$A$163,'Maestro de productos 2024'!$B$3:$B$163,0)} -> ID-3827 | B86: Galletas danesas | C86: {=XLOOKUP(B86,'Maestro de productos 2025'!$B$189:$B$196,'Maestro de productos 2025'!$D$189:$D$196,"No encontrado",0)} -> 7 | D86: {=XLOOKUP(B86,'Maestro de productos 2025'!$B$189:$B$196,'Maestro de productos 2025'!$E$189:$E$196,"No encontrado",0)} -> 3.1117795 | E86: =C86-D86 -> 3.8882205 | F86: =('Base de datos transacciones'!$H86)*$D86 -> 96.465165 | G86: ='Base de datos transacciones'!$H86*$C86 -> 217 | H86: =G86-F86 -> 120.53484 | I86: =SUM(G85:G86) -> 469 | J86: =((I86-I84)/I84) -> -0.28396947 | K86: =(I86-(SUM(F85:F86)))/I86 -> 0.58043203 | L86: =I86-(SUM(F85:F86)) -> 272.22262 | M86: =((L86-L84)/L84) -> -0.30327474
A87: {=XLOOKUP($B87,'Maestro de productos 2024'!$A$3:$A$163,'Maestro de productos 2024'!$B$3:$B$163,0)} -> ID-3830 | B87: Flan de queso crema | C87: {=XLOOKUP(B87,'Maestro de productos 2025'!$B$189:$B$196,'Maestro de productos 2025'!$D$189:$D$196,"No encontrado",0)} -> 29 | D87: {=XLOOKUP(B87,'Maestro de productos 2025'!$B$189:$B$196,'Maestro de productos 2025'!$E$189:$E$196,"No encontrado",0)} -> 11.936875 | E87: =C87-D87 -> 17.063125 | F87: =('Base de datos transacciones'!$H87)*$D87 -> 214.86375 | G87: ='Base de datos transacciones'!$H87*$C87 -> 522 | H87: =G87-F87 -> 307.13625
A88: {=XLOOKUP($B88,'Maestro de productos 2024'!$A$3:$A$163,'Maestro de productos 2024'!$B$3:$B$163,0)} -> ID-3826 | B88: Brownie triple chocolate | C88: {=XLOOKUP(B88,'Maestro de productos 2025'!$B$189:$B$196,'Maestro de productos 2025'!$D$189:$D$196,"No encontrado",0)} -> 20 | D88: {=XLOOKUP(B88,'Maestro de productos 2025'!$B$189:$B$196,'Maestro de productos 2025'!$E$189:$E$196,"No encontrado",0)} -> 8.0731235 | E88: =C88-D88 -> 11.926877 | F88: =('Base de datos transacciones'!$H88)*$D88 -> 145.31622 | G88: ='Base de datos transacciones'!$H88*$C88 -> 360 | H88: =G88-F88 -> 214.68378 | I88: =SUM(G87:G88) -> 882 | J88: =((I88-I86)/I86) -> 0.88059701 | K88: =(I88-(SUM(F87:F88)))/I88 -> 0.59163268 | L88: =I88-(SUM(F87:F88)) -> 521.82003 | M88: =((L88-L86)/L86) -> 0.91688708 | N88: =SUM(G80:G88) -> 3190 | O88: =((N88-N78)/N78) -> 0.26037139 | P88: =(N88-SUM(F80:F88))/N88 -> 0.59355699 | Q88: =N88-(SUM(F80:F88)) -> 1893.4468 | R88: =((Q88-Q78)/Q78) -> 0.2244914
A89: {=XLOOKUP($B89,'Maestro de productos 2024'!$A$3:$A$163,'Maestro de productos 2024'!$B$3:$B$163,0)} -> ID-3824 | B89: Galletas chocochips | C89: {=XLOOKUP(B89,'Maestro de productos 2025'!$B$189:$B$196,'Maestro de productos 2025'!$D$189:$D$196,"No encontrado",0)} -> 10 | D89: {=XLOOKUP(B89,'Maestro de productos 2025'!$B$189:$B$196,'Maestro de productos 2025'!$E$189:$E$196,"No encontrado",0)} -> 4.071744 | E89: =C89-D89 -> 5.928256 | F89: =('Base de datos transacciones'!$H89)*$D89 -> 130.29581 | G89: ='Base de datos transacciones'!$H89*$C89 -> 320 | H89: =G89-F89 -> 189.70419
A90: {=XLOOKUP($B90,'Maestro de productos 2024'!$A$3:$A$163,'Maestro de productos 2024'!$B$3:$B$163,0)} -> ID-3828 | B90: Muffins de yogurt | C90: {=XLOOKUP(B90,'Maestro de productos 2025'!$B$189:$B$196,'Maestro de productos 2025'!$D$189:$D$196,"No encontrado",0)} -> 21 | D90: {=XLOOKUP(B90,'Maestro de productos 2025'!$B$189:$B$196,'Maestro de productos 2025'!$E$189:$E$196,"No encontrado",0)} -> 8.3593511 | E90: =C90-D90 -> 12.640649 | F90: =('Base de datos transacciones'!$H90)*$D90 -> 200.62443 | G90: ='Base de datos transacciones'!$H90*$C90 -> 504 | H90: =G90-F90 -> 303.37557 | I90: =SUM(G89:G90) -> 824 | J90: =((I90-I88)/I88) -> -0.065759637 | K90: =(I90-(SUM(F89:F90)))/I90 -> 0.59839777 | L90: =I90-(SUM(F89:F90)) -> 493.07977 | M90: =((L90-L88)/L88) -> -0.055076964
A91: {=XLOOKUP($B91,'Maestro de productos 2024'!$A$3:$A$163,'Maestro de productos 2024'!$B$3:$B$163,0)} -> ID-3828 | B91: Muffins de yogurt | C91: {=XLOOKUP(B91,'Maestro de productos 2025'!$B$189:$B$196,'Maestro de productos 2025'!$D$189:$D$196,"No encontrado",0)} -> 21 | D91: {=XLOOKUP(B91,'Maestro de productos 2025'!$B$189:$B$196,'Maestro de productos 2025'!$E$189:$E$196,"No encontrado",0)} -> 8.3593511 | E91: =C91-D91 -> 12.640649 | F91: =('Base de datos transacciones'!$H91)*$D91 -> 100.31221 | G91: ='Base de datos transacciones'!$H91*$C91 -> 252 | H91: =G91-F91 -> 151.68779
A92: {=XLOOKUP($B92,'Maestro de productos 2024'!$A$3:$A$163,'Maestro de productos 2024'!$B$3:$B$163,0)} -> ID-3827 | B92: Galletas danesas | C92: {=XLOOKUP(B92,'Maestro de productos 2025'!$B$189:$B$196,'Maestro de productos 2025'!$D$189:$D$196,"No encontrado",0)} -> 7 | D92: {=XLOOKUP(B92,'Maestro de productos 2025'!$B$189:$B$196,'Maestro de productos 2025'!$E$189:$E$196,"No encontrado",0)} -> 3.1117795 | E92: =C92-D92 -> 3.8882205 | F92: =('Base de datos transacciones'!$H92)*$D92 -> 99.576944 | G92: ='Base de datos transacciones'!$H92*$C92 -> 224 | H92: =G92-F92 -> 124.42306 | I92: =SUM(G91:G92) -> 476 | J92: =((I92-I90)/I90) -> -0.4223301 | K92: =(I92-(SUM(F91:F92)))/I92 -> 0.58006479 | L92: =I92-(SUM(F91:F92)) -> 276.11084 | M92: =((L92-L90)/L90) -> -0.44002804
A93: {=XLOOKUP($B93,'Maestro de productos 2024'!$A$3:$A$163,'Maestro de productos 2024'!$B$3:$B$163,0)} -> ID-3824 | B93: Galletas chocochips | C93: {=XLOOKUP(B93,'Maestro de productos 2025'!$B$189:$B$196,'Maestro de productos 2025'!$D$189:$D$196,"No encontrado",0)} -> 10 | D93: {=XLOOKUP(B93,'Maestro de productos 2025'!$B$189:$B$196,'Maestro de productos 2025'!$E$189:$E$196,"No encontrado",0)} -> 4.071744 | E93: =C93-D93 -> 5.928256 | F93: =('Base de datos transacciones'!$H93)*$D93 -> 122.15232 | G93: ='Base de datos transacciones'!$H93*$C93 -> 300 | H93: =G93-F93 -> 177.84768
A94: {=XLOOKUP($B94,'Maestro de productos 2024'!$A$3:$A$163,'Maestro de productos 2024'!$B$3:$B$163,0)} -> ID-3829 | B94: Besos de nuez | C94: {=XLOOKUP(B94,'Maestro de productos 2025'!$B$189:$B$196,'Maestro de productos 2025'!$D$189:$D$196,"No encontrado",0)} -> 9 | D94: {=XLOOKUP(B94,'Maestro de productos 2025'!$B$189:$B$196,'Maestro de productos 2025'!$E$189:$E$196,"No encontrado",0)} -> 3.6108686 | E94: =C94-D94 -> 5.3891314 | F94: =('Base de datos transacciones'!$H94)*$D94 -> 126.3804 | G94: ='Base de datos transacciones'!$H94*$C94 -> 315 | H94: =G94-F94 -> 188.6196 | I94: =SUM(G93:G94) -> 615 | J94: =((I94-I92)/I92) -> 0.29201681 | K94: =(I94-(SUM(F93:F94)))/I94 -> 0.59588176 | L94: =I94-(SUM(F93:F94)) -> 366.46728 | M94: =((L94-L92)/L92) -> 0.32724697
A95: {=XLOOKUP($B95,'Maestro de productos 2024'!$A$3:$A$163,'Maestro de productos 2024'!$B$3:$B$163,0)} -> ID-3825 | B95: Mini cheesecake | C95: {=XLOOKUP(B95,'Maestro de productos 2025'!$B$189:$B$196,'Maestro de productos 2025'!$D$189:$D$196,"No encontrado",0)} -> 25 | D95: {=XLOOKUP(B95,'Maestro de productos 2025'!$B$189:$B$196,'Maestro de productos 2025'!$E$189:$E$196,"No encontrado",0)} -> 10.264506 | E95: =C95-D95 -> 14.735494 | F95: =('Base de datos transacciones'!$H95)*$D95 -> 164.2321 | G95: ='Base de datos transacciones'!$H95*$C95 -> 400 | H95: =G95-F95 -> 235.7679
A96: {=XLOOKUP($B96,'Maestro de productos 2024'!$A$3:$A$163,'Maestro de productos 2024'!$B$3:$B$163,0)} -> ID-3824 | B96: Galletas chocochips | C96: {=XLOOKUP(B96,'Maestro de productos 2025'!$B$189:$B$196,'Maestro de productos 2025'!$D$189:$D$196,"No encontrado",0)} -> 10 | D96: {=XLOOKUP(B96,'Maestro de productos 2025'!$B$189:$B$196,'Maestro de productos 2025'!$E$189:$E$196,"No encontrado",0)} -> 4.071744 | E96: =C96-D96 -> 5.928256 | F96: =('Base de datos transacciones'!$H96)*$D96 -> 130.29581 | G96: ='Base de datos transacciones'!$H96*$C96 -> 320 | H96: =G96-F96 -> 189.70419 | I96: =SUM(G95:G96) -> 720 | J96: =((I96-I94)/I94) -> 0.17073171 | K96: =(I96-(SUM(F95:F96)))/I96 -> 0.59093346 | L96: =I96-(SUM(F95:F96)) -> 425.47209 | M96: =((L96-L94)/L94) -> 0.16100976 | N96: =SUM(G89:G96) -> 2635 | O96: =((N96-N88)/N88) -> -0.17398119 | P96: =(N96-SUM(F89:F96))/N96 -> 0.59245919 | Q96: =N96-(SUM(F89:F96)) -> 1561.13 | R96: =((Q96-Q88)/Q88) -> -0.17550893
A97: {=XLOOKUP($B97,'Maestro de productos 2024'!$A$3:$A$163,'Maestro de productos 2024'!$B$3:$B$163,0)} -> ID-3828 | B97: Muffins de yogurt | C97: {=XLOOKUP(B97,'Maestro de productos 2025'!$B$189:$B$196,'Maestro de productos 2025'!$D$189:$D$196,"No encontrado",0)} -> 21 | D97: {=XLOOKUP(B97,'Maestro de productos 2025'!$B$189:$B$196,'Maestro de productos 2025'!$E$189:$E$196,"No encontrado",0)} -> 8.3593511 | E97: =C97-D97 -> 12.640649 | F97: =('Base de datos transacciones'!$H97)*$D97 -> 200.62443 | G97: ='Base de datos transacciones'!$H97*$C97 -> 504 | H97: =G97-F97 -> 303.37557
A98: {=XLOOKUP($B98,'Maestro de productos 2024'!$A$3:$A$163,'Maestro de productos 2024'!$B$3:$B$163,0)} -> ID-3831 | B98: Muffin de chocolate | C98: {=XLOOKUP(B98,'Maestro de productos 2025'!$B$189:$B$196,'Maestro de productos 2025'!$D$189:$D$196,"No encontrado",0)} -> 20 | D98: {=XLOOKUP(B98,'Maestro de productos 2025'!$B$189:$B$196,'Maestro de productos 2025'!$E$189:$E$196,"No encontrado",0)} -> 7.8897601 | E98: =C98-D98 -> 12.11024 | F98: =('Base de datos transacciones'!$H98)*$D98 -> 94.677121 | G98: ='Base de datos transacciones'!$H98*$C98 -> 240 | H98: =G98-F98 -> 145.32288 | I98: =SUM(G97:G98) -> 744 | J98: =((I98-I96)/I96) -> 0.033333333 | K98: =(I98-(SUM(F97:F98)))/I98 -> 0.60308932 | L98: =I98-(SUM(F97:F98)) -> 448.69845 | M98: =((L98-L96)/L96) -> 0.054589626
A99: {=XLOOKUP($B99,'Maestro de productos 2024'!$A$3:$A$163,'Maestro de productos 2024'!$B$3:$B$163,0)} -> ID-3824 | B99: Galletas chocochips | C99: {=XLOOKUP(B99,'Maestro de productos 2025'!$B$189:$B$196,'Maestro de productos 2025'!$D$189:$D$196,"No encontrado",0)} -> 10 | D99: {=XLOOKUP(B99,'Maestro de productos 2025'!$B$189:$B$196,'Maestro de productos 2025'!$E$189:$E$196,"No encontrado",0)} -> 4.071744 | E99: =C99-D99 -> 5.928256 | F99: =('Base de datos transacciones'!$H99)*$D99 -> 122.15232 | G99: ='Base de datos transacciones'!$H99*$C99 -> 300 | H99: =G99-F99 -> 177.84768
A100: {=XLOOKUP($B100,'Maestro de productos 2024'!$A$3:$A$163,'Maestro de productos 2024'!$B$3:$B$163,0)} -> ID-3827 | B100: Galletas danesas | C100: {=XLOOKUP(B100,'Maestro de productos 2025'!$B$189:$B$196,'Maestro de productos 2025'!$D$189:$D$196,"No encontrado",0)} -> 7 | D100: {=XLOOKUP(B100,'Maestro de productos 2025'!$B$189:$B$196,'Maestro de productos 2025'!$E$189:$E$196,"No encontrado",0)} -> 3.1117795 | E100: =C100-D100 -> 3.8882205 | F100: =('Base de datos transacciones'!$H100)*$D100 -> 108.91228 | G100: ='Base de datos transacciones'!$H100*$C100 -> 245 | H100: =G100-F100 -> 136.08772 | I100: =SUM(G99:G100) -> 545 | J100: =((I100-I98)/I98) -> -0.26747312 | K100: =(I100-(SUM(F99:F100)))/I100 -> 0.57602825 | L100: =I100-(SUM(F99:F100)) -> 313.9354 | M100: =((L100-L98)/L98) -> -0.30034214
...

Sheet Dashboard de rentabilidad
B1: Selector de año: | C1: 2025
A4: ID | B4: Producto | C4: IT | D4: CV | E4: UB | F4: MGB | G4: GO | H4: UO | I4: Impuestos (1%RESICO) | J4: UN | K4: CantidadVendida | L4: Desperdicio(tasa) | M4: MixVtasQ | N4: MixVtas$ | O4: SMV
A5: {=XLOOKUP($B5,'Maestro de productos 2024'!$A$3:$A$163,'Maestro de productos 2024'!$B$3:$B$163,0)} -> ID-3824 | B5: ='Maestro de productos 2024'!$A$3 -> Galletas chocochips | C5: =IF($C$1="Todos",SUMIF('Base de datos transacciones'!$A$2:$A$162,$A5,'Base de datos transacciones'!$K$2:$K$162),SUMIFS('Base de datos transacciones'!$K$2:$K$162,'Base de datos transacciones'!$C$2:$C$162,$C$1,'Base de datos transacciones'!$A$2:$A$162,$A5)) -> 5790 | D5: =IF($C$1="Todos",SUMIF('Base de datos transacciones'!$A$2:$A$162,$A5,'Base de datos transacciones'!$J$2:$J$162),SUMIFS('Base de datos transacciones'!$J$2:$J$162,'Base de datos transacciones'!$C$2:$C$162,$C$1,'Base de datos transacciones'!$A$2:$A$162,$A5)) -> 2357.5398 | E5: =C5-D5 -> 3432.4602 | F5: =E5/C5 -> 0.5928256 | G5: =IF($C$1="Todos",(($C5*0.2)+'Maestro de productos 2024'!$I189+'Maestro de productos 2025'!$I189),IF($C$1=2024,(($C5*0.2)+'Maestro de productos 2024'!$I189),(($C5*0.2)+'Maestro de productos 2025'!$I189))) -> 1276.0806 | H5: =E5-G5 -> 2156.3797 | I5: =C5*0.01 -> 57.9 | J5: =H5-I5 -> 2098.4797 | K5: =IF($C$1="Todos",SUMIF('Base de datos transacciones'!$A$2:$A$162,$A5,'Base de datos transacciones'!$H$2:$H$162),SUMIFS('Base de datos transacciones'!$H$2:$H$162,'Base de datos transacciones'!$C$2:$C$162,$C$1,'Base de datos transacciones'!$A$2:$A$162,$A5)) -> 579 | L5: =IF($C$1="Todos",(($D$5-('Maestro de productos 2024'!$J$189+'Maestro de productos 2025'!$J$189))/$D$5),IF($C$1=2024,(($D$5-'Maestro de productos 2024'!$J$189)/$D$5),(($D$5-'Maestro de productos 2025'!$J$189)/$D$5))) -> -1.4559501 | M5: =K5/$K$13 -> 0.30361825 | N5: =C5/$C$13 -> 0.21307132 | O5: =IF($C$1="Todos",('Maestro de productos 2025'!$G$197*('Maestro de productos 2025'!L189-'Maestro de productos 2024'!L189)*'Maestro de productos 2024'!K189),IF($C$1=2024,($K$13*(M5-0.125)*'Maestro de productos 2024'!K189),($K$13*(M5-0.125)*'Maestro de productos 2025'!K189))) -> 2019.3122
A6: {=XLOOKUP($B6,'Maestro de productos 2024'!$A$3:$A$163,'Maestro de productos 2024'!$B$3:$B$163,0)} -> ID-3825 | B6: ='Maestro de productos 2024'!$A$26 -> Mini cheesecake | C6: =IF($C$1="Todos",SUMIF('Base de datos transacciones'!$A$2:$A$162,$A6,'Base de datos transacciones'!$K$2:$K$162),SUMIFS('Base de datos transacciones'!$K$2:$K$162,'Base de datos transacciones'!$C$2:$C$162,$C$1,'Base de datos transacciones'!$A$2:$A$162,$A6)) -> 3475 | D6: =IF($C$1="Todos",SUMIF('Base de datos transacciones'!$A$2:$A$162,$A6,'Base de datos transacciones'!$J$2:$J$162),SUMIFS('Base de datos transacciones'!$J$2:$J$162,'Base de datos transacciones'!$C$2:$C$162,$C$1,'Base de datos transacciones'!$A$2:$A$162,$A6)) -> 1426.7664 | E6: =C6-D6 -> 2048.2336 | F6: =E6/C6 -> 0.58941974 | G6: =IF($C$1="Todos",(($C6*0.2)+'Maestro de productos 2024'!$I190+'Maestro de productos 2025'!$I190),IF($C$1=2024,(($C6*0.2)+'Maestro de productos 2024'!$I190),(($C6*0.2)+'Maestro de productos 2025'!$I190))) -> 746.32253 | H6: =E6-G6 -> 1301.9111 | I6: =C6*0.01 -> 34.75 | J6: =H6-I6 -> 1267.1611 | K6: =IF($C$1="Todos",SUMIF('Base de datos transacciones'!$A$2:$A$162,$A6,'Base de datos transacciones'!$H$2:$H$162),SUMIFS('Base de datos transacciones'!$H$2:$H$162,'Base de datos transacciones'!$C$2:$C$162,$C$1,'Base de datos transacciones'!$A$2:$A$162,$A6)) -> 139 | L6: =IF($C$1="Todos",(($D$6-('Maestro de productos 2024'!$J$190+'Maestro de productos 2025'!$J$190))/$D$6),IF($C$1=2024,(($D$6-'Maestro de productos 2024'!$J$190)/$D$6),(($D$6-'Maestro de productos 2025'!$J$190)/$D$6))) -> -1.4355774 | M6: =K6/$K$13 -> 0.072889355 | N6: =C6/$C$13 -> 0.12787959 | O6: =IF($C$1="Todos",('Maestro de productos 2025'!$G$197*('Maestro de productos 2025'!L190-'Maestro de productos 2024'!L190)*'Maestro de productos 2024'!K190),IF($C$1=2024,($K$13*(M6-0.125)*'Maestro de productos 2024'!K190),($K$13*(M6-0.125)*'Maestro de productos 2025'!K190))) -> -1464.3397
A7: {=XLOOKUP($B7,'Maestro de productos 2024'!$A$3:$A$163,'Maestro de productos 2024'!$B$3:$B$163,0)} -> ID-3826 | B7: ='Maestro de productos 2024'!$A$51 -> Brownie triple chocolate | C7: =IF($C$1="Todos",SUMIF('Base de datos transacciones'!$A$2:$A$162,$A7,'Base de datos transacciones'!$K$2:$K$162),SUMIFS('Base de datos transacciones'!$K$2:$K$162,'Base de datos transacciones'!$C$2:$C$162,$C$1,'Base de datos transacciones'!$A$2:$A$162,$A7)) -> 3220 | D7: =IF($C$1="Todos",SUMIF('Base de datos transacciones'!$A$2:$A$162,$A7,'Base de datos transacciones'!$J$2:$J$162),SUMIFS('Base de datos transacciones'!$J$2:$J$162,'Base de datos transacciones'!$C$2:$C$162,$C$1,'Base de datos transacciones'!$A$2:$A$162,$A7)) -> 1299.7729 | E7: =C7-D7 -> 1920.2271 | F7: =E7/C7 -> 0.59634383 | G7: =IF($C$1="Todos",(($C7*0.2)+'Maestro de productos 2024'!$I191+'Maestro de productos 2025'!$I191),IF($C$1=2024,(($C7*0.2)+'Maestro de productos 2024'!$I191),(($C7*0.2)+'Maestro de productos 2025'!$I191))) -> 652.07312 | H7: =E7-G7 -> 1268.154 | I7: =C7*0.01 -> 32.2 | J7: =H7-I7 -> 1235.954 | K7: =IF($C$1="Todos",SUMIF('Base de datos transacciones'!$A$2:$A$162,$A7,'Base de datos transacciones'!$H$2:$H$162),SUMIFS('Base de datos transacciones'!$H$2:$H$162,'Base de datos transacciones'!$C$2:$C$162,$C$1,'Base de datos transacciones'!$A$2:$A$162,$A7)) -> 161 | L7: =IF($C$1="Todos",(($D$7-('Maestro de productos 2024'!$J$191+'Maestro de productos 2025'!$J$191))/$D$7),IF($C$1=2024,(($D$7-'Maestro de productos 2024'!$J$191)/$D$7),(($D$7-'Maestro de productos 2025'!$J$191)/$D$7))) -> -1.4773559 | M7: =K7/$K$13 -> 0.0844258 | N7: =C7/$C$13 -> 0.11849562 | O7: =IF($C$1="Todos",('Maestro de productos 2025'!$G$197*('Maestro de productos 2025'!L191-'Maestro de productos 2024'!L191)*'Maestro de productos 2024'!K191),IF($C$1=2024,($K$13*(M7-0.125)*'Maestro de productos 2024'!K191),($K$13*(M7-0.125)*'Maestro de productos 2025'!K191))) -> -922.84207
A8: {=XLOOKUP($B8,'Maestro de productos 2024'!$A$3:$A$163,'Maestro de productos 2024'!$B$3:$B$163,0)} -> ID-3827 | B8: ='Maestro de productos 2024'!$A$75 -> Galletas danesas | C8: =IF($C$1="Todos",SUMIF('Base de datos transacciones'!$A$2:$A$162,$A8,'Base de datos transacciones'!$K$2:$K$162),SUMIFS('Base de datos transacciones'!$K$2:$K$162,'Base de datos transacciones'!$C$2:$C$162,$C$1,'Base de datos transacciones'!$A$2:$A$162,$A8)) -> 2975 | D8: =IF($C$1="Todos",SUMIF('Base de datos transacciones'!$A$2:$A$162,$A8,'Base de datos transacciones'!$J$2:$J$162),SUMIFS('Base de datos transacciones'!$J$2:$J$162,'Base de datos transacciones'!$C$2:$C$162,$C$1,'Base de datos transacciones'!$A$2:$A$162,$A8)) -> 1322.5063 | E8: =C8-D8 -> 1652.4937 | F8: =E8/C8 -> 0.55546007 | G8: =IF($C$1="Todos",(($C8*0.2)+'Maestro de productos 2024'!$I192+'Maestro de productos 2025'!$I192),IF($C$1=2024,(($C8*0.2)+'Maestro de productos 2024'!$I192),(($C8*0.2)+'Maestro de productos 2025'!$I192))) -> 688.35339 | H8: =E8-G8 -> 964.14033 | I8: =C8*0.01 -> 29.75 | J8: =H8-I8 -> 934.39033 | K8: =IF($C$1="Todos",SUMIF('Base de datos transacciones'!$A$2:$A$162,$A8,'Base de datos transacciones'!$H$2:$H$162),SUMIFS('Base de datos transacciones'!$H$2:$H$162,'Base de datos transacciones'!$C$2:$C$162,$C$1,'Base de datos transacciones'!$A$2:$A$162,$A8)) -> 425 | L8: =IF($C$1="Todos",(($D$8-('Maestro de productos 2024'!$J$192+'Maestro de productos 2025'!$J$192))/$D$8),IF($C$1=2024,(($D$8-'Maestro de productos 2024'!$J$192)/$D$8),(($D$8-'Maestro de productos 2025'!$J$192)/$D$8))) -> -1.2495167 | M8: =K8/$K$13 -> 0.22286314 | N8: =C8/$C$13 -> 0.10947965 | O8: =IF($C$1="Todos",('Maestro de productos 2025'!$G$197*('Maestro de productos 2025'!L192-'Maestro de productos 2024'!L192)*'Maestro de productos 2024'!K192),IF($C$1=2024,($K$13*(M8-0.125)*'Maestro de productos 2024'!K192),($K$13*(M8-0.125)*'Maestro de productos 2025'!K192))) -> 725.63915
A9: {=XLOOKUP($B9,'Maestro de productos 2024'!$A$3:$A$163,'Maestro de productos 2024'!$B$3:$B$163,0)} -> ID-3828 | B9: ='Maestro de productos 2024'!$A$96 -> Muffins de yogurt | C9: =IF($C$1="Todos",SUMIF('Base de datos transacciones'!$A$2:$A$162,$A9,'Base de datos transacciones'!$K$2:$K$162),SUMIFS('Base de datos transacciones'!$K$2:$K$162,'Base de datos transacciones'!$C$2:$C$162,$C$1,'Base de datos transacciones'!$A$2:$A$162,$A9)) -> 7812 | D9: =IF($C$1="Todos",SUMIF('Base de datos transacciones'!$A$2:$A$162,$A9,'Base de datos transacciones'!$J$2:$J$162),SUMIFS('Base de datos transacciones'!$J$2:$J$162,'Base de datos transacciones'!$C$2:$C$162,$C$1,'Base de datos transacciones'!$A$2:$A$162,$A9)) -> 3109.6786 | E9: =C9-D9 -> 4702.3214 | F9: =E9/C9 -> 0.60193566 | G9: =IF($C$1="Todos",(($C9*0.2)+'Maestro de productos 2024'!$I193+'Maestro de productos 2025'!$I193),IF($C$1=2024,(($C9*0.2)+'Maestro de productos 2024'!$I193),(($C9*0.2)+'Maestro de productos 2025'!$I193))) -> 1562.4 | H9: =E9-G9 -> 3139.9214 | I9: =C9*0.01 -> 78.12 | J9: =H9-I9 -> 3061.8014 | K9: =IF($C$1="Todos",SUMIF('Base de datos transacciones'!$A$2:$A$162,$A9,'Base de datos transacciones'!$H$2:$H$162),SUMIFS('Base de datos transacciones'!$H$2:$H$162,'Base de datos transacciones'!$C$2:$C$162,$C$1,'Base de datos transacciones'!$A$2:$A$162,$A9)) -> 372 | L9: =IF($C$1="Todos",(($D$9-('Maestro de productos 2024'!$J$193+'Maestro de productos 2025'!$J$193))/$D$9),IF($C$1=2024,(($D$9-'Maestro de productos 2024'!$J$193)/$D$9),(($D$9-'Maestro de productos 2025'!$J$193)/$D$9))) -> -1.5121567 | M9: =K9/$K$13 -> 0.19507079 | N9: =C9/$C$13 -> 0.28748068 | O9: =IF($C$1="Todos",('Maestro de productos 2025'!$G$197*('Maestro de productos 2025'!L193-'Maestro de productos 2024'!L193)*'Maestro de productos 2024'!K193),IF($C$1=2024,($K$13*(M9-0.125)*'Maestro de productos 2024'!K193),($K$13*(M9-0.125)*'Maestro de productos 2025'!K193))) -> 1689.1067
A10: {=XLOOKUP($B10,'Maestro de productos 2024'!$A$3:$A$163,'Maestro de productos 2024'!$B$3:$B$163,0)} -> ID-3829 | B10: ='Maestro de productos 2024'!$A$119 -> Besos de nuez | C10: =IF($C$1="Todos",SUMIF('Base de datos transacciones'!$A$2:$A$162,$A10,'Base de datos transacciones'!$K$2:$K$162),SUMIFS('Base de datos transacciones'!$K$2:$K$162,'Base de datos transacciones'!$C$2:$C$162,$C$1,'Base de datos transacciones'!$A$2:$A$162,$A10)) -> 720 | D10: =IF($C$1="Todos",SUMIF('Base de datos transacciones'!$A$2:$A$162,$A10,'Base de datos transacciones'!$J$2:$J$162),SUMIFS('Base de datos transacciones'!$J$2:$J$162,'Base de datos transacciones'!$C$2:$C$162,$C$1,'Base de datos transacciones'!$A$2:$A$162,$A10)) -> 288.86949 | E10: =C10-D10 -> 431.13051 | F10: =E10/C10 -> 0.59879238 | G10: =IF($C$1="Todos",(($C10*0.2)+'Maestro de productos 2024'!$I194+'Maestro de productos 2025'!$I194),IF($C$1=2024,(($C10*0.2)+'Maestro de productos 2024'!$I194),(($C10*0.2)+'Maestro de productos 2025'!$I194))) -> 216.21737 | H10: =E10-G10 -> 214.91314 | I10: =C10*0.01 -> 7.2 | J10: =H10-I10 -> 207.71314 | K10: =IF($C$1="Todos",SUMIF('Base de datos transacciones'!$A$2:$A$162,$A10,'Base de datos transacciones'!$H$2:$H$162),SUMIFS('Base de datos transacciones'!$H$2:$H$162,'Base de datos transacciones'!$C$2:$C$162,$C$1,'Base de datos transacciones'!$A$2:$A$162,$A10)) -> 80 | L10: =IF($C$1="Todos",(($D$10-('Maestro de productos 2024'!$J$194+'Maestro de productos 2025'!$J$194))/$D$10),IF($C$1=2024,(($D$10-'Maestro de productos 2024'!$J$194)/$D$10),(($D$10-'Maestro de productos 2025'!$J$194)/$D$10))) -> -1.4924751 | M10: =K10/$K$13 -> 0.041950708 | N10: =C10/$C$13 -> 0.026495915 | O10: =IF($C$1="Todos",('Maestro de productos 2025'!$G$197*('Maestro de productos 2025'!L194-'Maestro de productos 2024'!L194)*'Maestro de productos 2024'!K194),IF($C$1=2024,($K$13*(M10-0.125)*'Maestro de productos 2024'!K194),($K$13*(M10-0.125)*'Maestro de productos 2025'!K194))) -> -853.50369
A11: {=XLOOKUP($B11,'Maestro de productos 2024'!$A$3:$A$163,'Maestro de productos 2024'!$B$3:$B$163,0)} -> ID-3830 | B11: ='Maestro de productos 2024'!$A$140 -> Flan de queso crema | C11: =IF($C$1="Todos",SUMIF('Base de datos transacciones'!$A$2:$A$162,$A11,'Base de datos transacciones'!$K$2:$K$162),SUMIFS('Base de datos transacciones'!$K$2:$K$162,'Base de datos transacciones'!$C$2:$C$162,$C$1,'Base de datos transacciones'!$A$2:$A$162,$A11)) -> 522 | D11: =IF($C$1="Todos",SUMIF('Base de datos transacciones'!$A$2:$A$162,$A11,'Base de datos transacciones'!$J$2:$J$162),SUMIFS('Base de datos transacciones'!$J$2:$J$162,'Base de datos transacciones'!$C$2:$C$162,$C$1,'Base de datos transacciones'!$A$2:$A$162,$A11)) -> 214.86375 | E11: =C11-D11 -> 307.13625 | F11: =E11/C11 -> 0.58838362 | G11: =IF($C$1="Todos",(($C11*0.2)+'Maestro de productos 2024'!$I195+'Maestro de productos 2025'!$I195),IF($C$1=2024,(($C11*0.2)+'Maestro de productos 2024'!$I195),(($C11*0.2)+'Maestro de productos 2025'!$I195))) -> 104.4 | H11: =E11-G11 -> 202.73625 | I11: =C11*0.01 -> 5.22 | J11: =H11-I11 -> 197.51625 | K11: =IF($C$1="Todos",SUMIF('Base de datos transacciones'!$A$2:$A$162,$A11,'Base de datos transacciones'!$H$2:$H$162),SUMIFS('Base de datos transacciones'!$H$2:$H$162,'Base de datos transacciones'!$C$2:$C$162,$C$1,'Base de datos transacciones'!$A$2:$A$162,$A11)) -> 18 | L11: =IF($C$1="Todos",(($D$11-('Maestro de productos 2024'!$J$195+'Maestro de productos 2025'!$J$195))/$D$11),IF($C$1=2024,(($D$11-'Maestro de productos 2024'!$J$195)/$D$11),(($D$11-'Maestro de productos 2025'!$J$195)/$D$11))) -> -1.4294466 | M11: =K11/$K$13 -> 0.0094389093 | N11: =C11/$C$13 -> 0.019209539 | O11: =IF($C$1="Todos",('Maestro de productos 2025'!$G$197*('Maestro de productos 2025'!L195-'Maestro de productos 2024'!L195)*'Maestro de productos 2024'!K195),IF($C$1=2024,($K$13*(M11-0.125)*'Maestro de productos 2024'!K195),($K$13*(M11-0.125)*'Maestro de productos 2025'!K195))) -> -3760.2862
A12: {=XLOOKUP($B12,'Maestro de productos 2024'!$A$3:$A$163,'Maestro de productos 2024'!$B$3:$B$163,0)} -> ID-3831 | B12: ='Maestro de productos 2024'!$A$163 -> Muffin de chocolate | C12: =IF($C$1="Todos",SUMIF('Base de datos transacciones'!$A$2:$A$162,$A12,'Base de datos transacciones'!$K$2:$K$162),SUMIFS('Base de datos transacciones'!$K$2:$K$162,'Base de datos transacciones'!$C$2:$C$162,$C$1,'Base de datos transacciones'!$A$2:$A$162,$A12)) -> 2660 | D12: =IF($C$1="Todos",SUMIF('Base de datos transacciones'!$A$2:$A$162,$A12,'Base de datos transacciones'!$J$2:$J$162),SUMIFS('Base de datos transacciones'!$J$2:$J$162,'Base de datos transacciones'!$C$2:$C$162,$C$1,'Base de datos transacciones'!$A$2:$A$162,$A12)) -> 1049.3381 | E12: =C12-D12 -> 1610.6619 | F12: =E12/C12 -> 0.605512 | G12: =IF($C$1="Todos",(($C12*0.2)+'Maestro de productos 2024'!$I196+'Maestro de productos 2025'!$I196),IF($C$1=2024,(($C12*0.2)+'Maestro de productos 2024'!$I196),(($C12*0.2)+'Maestro de productos 2025'!$I196))) -> 587.22832 | H12: =E12-G12 -> 1023.4336 | I12: =C12*0.01 -> 26.6 | J12: =H12-I12 -> 996.83359 | K12: =IF($C$1="Todos",SUMIF('Base de datos transacciones'!$A$2:$A$162,$A12,'Base de datos transacciones'!$H$2:$H$162),SUMIFS('Base de datos transacciones'!$H$2:$H$162,'Base de datos transacciones'!$C$2:$C$162,$C$1,'Base de datos transacciones'!$A$2:$A$162,$A12)) -> 133 | L12: =IF($C$1="Todos",(($D$12-('Maestro de productos 2024'!$J$196+'Maestro de productos 2025'!$J$196))/$D$12),IF($C$1=2024,(($D$12-'Maestro de productos 2024'!$J$196)/$D$12),(($D$12-'Maestro de productos 2025'!$J$196)/$D$12))) -> -1.5349313 | M12: =K12/$K$13 -> 0.069743052 | N12: =C12/$C$13 -> 0.097887687 | O12: =IF($C$1="Todos",('Maestro de productos 2025'!$G$197*('Maestro de productos 2025'!L196-'Maestro de productos 2024'!L196)*'Maestro de productos 2024'!K196),IF($C$1=2024,($K$13*(M12-0.125)*'Maestro de productos 2024'!K196),($K$13*(M12-0.125)*'Maestro de productos 2025'!K196))) -> -1276.1165
B13: Total | C13: =SUM(C5:C12) -> 27174 | D13: =SUM(D5:D12) -> 11069.335 | E13: =SUM(E5:E12) -> 16104.665 | F13: =E13/C13 -> 0.59264977 | G13: =SUM(G5:G12) -> 5833.0753 | H13: =SUM(H5:H12) -> 10271.589 | I13: =SUM(I5:I12) -> 271.74 | J13: =SUM(J5:J12) -> 9999.8494 | K13: =SUM(K5:K12) -> 1907
C30: IT | D30: CV | E30: MGB
B31: Promedio 2025 | C31: 3396.75 | D31: 1383.6669 | E31: =(C31-D31)/C31 -> 0.59264977
C33: =C31*1.1 -> 3736.425 | E33: =(C33-D31)/C33 -> 0.6296816
B35: Promedio 2024 | C35: 3448.875 | D35: 1277.6493 | E35: =(C31-D35)/C31 -> 0.62386124
A38: ID | B38: 2024 | C38: UB | D38: % Individual | E38: % Acumulado
A39: ID-3828 | B39: Muffins de yogurt | C39: 3962.068 | D39: =C39/$C$47 -> 0.22810089 | E39: =D39 -> 0.22810089
A40: ID-3824 | B40: Galletas chocochips | C40: 3764.2835 | D40: =C40/$C$47 -> 0.2167142 | E40: =E39+D40 -> 0.44481509
A41: ID-3826 | B41: Brownie Triple Chocolate | C41: 3185.3189 | D41: =C41/$C$47 -> 0.18338253 | E41: =E40+D41 -> 0.62819762
A42: ID-3825 | B42: Mini cheesecake | C42: 1920.5823 | D42: =C42/$C$47 -> 0.11057017 | E42: =E41+D42 -> 0.73876779
A43: ID-3829 | B43: Besos de nuez | C43: 1539.9001 | D43: =C43/$C$47 -> 0.088653847 | E43: =E42+D43 -> 0.82742164
A44: ID-3827 | B44: Galletas danesas | C44: 1286.7027 | D44: =C44/$C$47 -> 0.074076981 | E44: =E43+D44 -> 0.90149862
A45: ID-3830 | B45: Flan de queso crema | C45: 1167.2567 | D45: =C45/$C$47 -> 0.067200331 | E45: =E44+D45 -> 0.96869895
A46: ID-3831 | B46: Muffin de chocolate | C46: 543.69308 | D46: =C46/$C$47 -> 0.031301046 | E46: =E45+D46 -> 1
C47: =SUM(C39:C46) -> 17369.805
B48: 2025 | C48: UB | D48: % Individual | E48: % Acumulado
A49: ID-3828 | B49: Muffins de yogurt | C49: 4702.3214 | D49: =C49/$C$57 -> 0.29198505 | E49: =D49 -> 0.29198505 | M49: CV 2024 | N49: PV 2025 | O49: CantidadVendida2025 | P49: IT | Q49: TotalCOGS
A50: ID-3824 | B50: Galletas chocochips | C50: 3432.4602 | D50: =C50/$C$57 -> 0.21313454 | E50: =E49+D50 -> 0.50511959 | M50: 3.3375513 | N50: 10 | O50: 579 | P50: =N50*O50 -> 5790 | Q50: =M50*O50 -> 1932.4422
A51: ID-3826 | B51: Brownie Triple Chocolate | C51: 1920.2271 | D51: =C51/$C$57 -> 0.11923422 | E51: =E50+D51 -> 0.62435381 | M51: 7.6091462 | N51: 25 | O51: 139 | P51: =N51*O51 -> 3475 | Q51: =M51*O51 -> 1057.6713
A52: ID-3825 | B52: Mini cheesecake | C52: 2048.2336 | D52: =C52/$C$57 -> 0.12718263 | E52: =E51+D52 -> 0.75153644 | M52: 7.1039722 | N52: 20 | O52: 161 | P52: =N52*O52 -> 3220 | Q52: =M52*O52 -> 1143.7395
A53: ID-3827 | B53: Galletas danesas | C53: 1652.4937 | D53: =C53/$C$57 -> 0.10260963 | E53: =E52+D53 -> 0.85414607 | M53: 2.6234601 | N53: 7 | O53: 425 | P53: =N53*O53 -> 2975 | Q53: =M53*O53 -> 1114.9705
A54: ID-3831 | B54: Muffin de chocolate | C54: 1610.6619 | D54: =C54/$C$57 -> 0.10001214 | E54: =E53+D54 -> 0.9541582 | M54: 7.3010641 | N54: 21 | O54: 372 | P54: =N54*O54 -> 7812 | Q54: =M54*O54 -> 2715.9958
A55: ID-3829 | B55: Besos de nuez | C55: 431.13051 | D55: =C55/$C$57 -> 0.026770536 | E55: =E54+D55 -> 0.98092874 | M55: 2.9898436 | N55: 9 | O55: 80 | P55: =N55*O55 -> 720 | Q55: =M55*O55 -> 239.18749
A56: ID-3830 | B56: Flan de queso crema | C56: 307.13625 | D56: =C56/$C$57 -> 0.01907126 | E56: =E55+D56 -> 1 | M56: 10.936667 | N56: 29 | O56: 18 | P56: =N56*O56 -> 522 | Q56: =M56*O56 -> 196.86
C57: =SUM(C49:C56) -> 16104.665 | M57: 7.0549267 | N57: 20 | O57: 133 | P57: =N57*O57 -> 2660 | Q57: =M57*O57 -> 938.30526
B58: Todos | C58: UB | D58: % Individual | E58: % Acumulado | P58: =SUM(P50:P57) -> 27174 | Q58: =SUM(Q50:Q57) -> 9339.1722
A59: ID-3828 | B59: Muffins de yogurt | C59: 8664.3894 | D59: =C59/$C$67 -> 0.25883575 | E59: =D59 -> 0.25883575 | Q59: =(P58-Q58)/P58 -> 0.65631956
A60: ID-3824 | B60: Galletas chocochips | C60: 7196.7438 | D60: =C60/$C$67 -> 0.21499202 | E60: =D60+E59 -> 0.47382776
A61: ID-3826 | B61: Brownie Triple Chocolate | C61: 5105.546 | D61: =C61/$C$67 -> 0.15252059 | E61: =D61+E60 -> 0.62634835 | J61: 3.3375513 | K61: =J61*P61 -> 1885.7165 | L61: =Q61-K61 -> 3764.2835 | N61: 4.071744 | O61: 10 | P61: 565 | Q61: =O61*P61 -> 5650 | R61: =N61*P61 -> 2300.5354 | S61: =Q61-R61 -> 3349.4646
A62: ID-3825 | B62: Mini cheesecake | C62: 3968.8159 | D62: =C62/$C$67 -> 0.11856247 | E62: =D62+E61 -> 0.74491083 | J62: 7.6091462 | K62: =J62*P62 -> 1179.4177 | L62: =Q62-K62 -> 2695.5823 | N62: 10.264506 | O62: 25 | P62: 155 | Q62: =O62*P62 -> 3875 | R62: =N62*P62 -> 1590.9985 | S62: =Q62-R62 -> 2284.0015
A63: ID-3827 | B63: Galletas danesas | C63: 2939.1965 | D63: =C63/$C$67 -> 0.087804122 | E63: =D63+E62 -> 0.83271495 | J63: 7.1039722 | K63: =J63*P63 -> 1754.6811 | L63: =Q63-K63 -> 3185.3189 | N63: 8.0731235 | O63: 20 | P63: 247 | Q63: =O63*P63 -> 4940 | R63: =N63*P63 -> 1994.0615 | S63: =Q63-R63 -> 2945.9385
A64: ID-3831 | B64: Muffin de chocolate | C64: 2154.355 | D64: =C64/$C$67 -> 0.064358151 | E64: =D64+E63 -> 0.8970731 | J64: 2.6234601 | K64: =J64*P64 -> 771.29726 | L64: =Q64-K64 -> 1286.7027 | N64: 3.1117795 | O64: 7 | P64: 294 | Q64: =O64*P64 -> 2058 | R64: =N64*P64 -> 914.86317 | S64: =Q64-R64 -> 1143.1368
A65: ID-3829 | B65: Besos de nuez | C65: 1971.0306 | D65: =C65/$C$67 -> 0.058881607 | E65: =D65+E64 -> 0.9559547 | J65: 7.3010641 | K65: =J65*P65 -> 2277.932 | L65: =Q65-K65 -> 4274.068 | N65: 8.3593511 | O65: 21 | P65: 312 | Q65: =O65*P65 -> 6552 | R65: =N65*P65 -> 2608.1176 | S65: =Q65-R65 -> 3943.8824
A66: {=XLOOKUP($B66,'Maestro de productos 2024'!$A$3:$A$163,'Maestro de productos 2024'!$B$3:$B$163,0)} -> ID-3830 | B66: ='Maestro de productos 2024'!$A$140 -> Flan de queso crema | C66: 1474.3929 | D66: =C66/$C$67 -> 0.044045295 | E66: =D66+E65 -> 1 | J66: 2.9898436 | K66: =J66*P66 -> 1148.0999 | L66: =Q66-K66 -> 2307.9001 | N66: 3.6108686 | O66: 9 | P66: 384 | Q66: =O66*P66 -> 3456 | R66: =N66*P66 -> 1386.5735 | S66: =Q66-R66 -> 2069.4265
C67: =SUM(C59:C66) -> 33474.47 | J67: 10.936667 | K67: =J67*P67 -> 907.74333 | L67: =Q67-K67 -> 1499.2567 | N67: 11.936875 | O67: 29 | P67: 83 | Q67: =O67*P67 -> 2407 | R67: =N67*P67 -> 990.76063 | S67: =Q67-R67 -> 1416.2394
J68: 7.0549267 | K68: =J68*P68 -> 296.30692 | L68: =Q68-K68 -> 543.69308 | N68: 7.8897601 | O68: 20 | P68: 42 | Q68: =O68*P68 -> 840 | R68: =N68*P68 -> 331.36992 | S68: =Q68-R68 -> 508.63008
K69: =SUM(K61:K68) -> 10221.195 | L69: =Q69-K69 -> 19556.805 | M69: =L69/Q69 -> 0.65675348 | Q69: =SUM(Q61:Q68) -> 29778 | R69: =SUM(R61:R68) -> 12117.28 | S69: =Q69-R69 -> 17660.72 | T69: =S69/Q69 -> 0.59307945
T70: =T69-README!G14 -> 0.00042968401

Sheet Base de datos transacciones
A1: ID | B1: FechaDelPedido | C1: Año | D1: Mes | E1: Producto | F1: PV | G1: CV | H1: CantidadVendida | I1: CantidadNoVendida | J1: TotalCV | K1: IT | L1: Perdidas
A2: {=XLOOKUP($E2,'Maestro de productos 2024'!$A$3:$A$163,'Maestro de productos 2024'!$B$3:$B$163,0)} -> ID-3824 | B2: 45373 | C2: =YEAR(B2) -> 2024 | D2: =MONTH(B2) -> 3 | E2: Galletas chocochips | F2: {=XLOOKUP(E2,'Maestro de productos 2024'!$B$189:$B$196,'Maestro de productos 2024'!$D$189:$D$196,"No encontrado",0)} -> 10 | G2: {=XLOOKUP(E2,'Maestro de productos 2024'!$B$189:$B$196,'Maestro de productos 2024'!$E$189:$E$196,"No encontrado",0)} -> 3.3375513 | H2: 32 | I2: {=IF((XLOOKUP($E2,'Maestro de productos 2024'!$B$189:$B$196,'Maestro de productos 2024'!$C$189:$C$196,"No encontrado",0)-H2)<=0,"0",(VLOOKUP($E2,'Maestro de productos 2024'!$B$189:$C$196,2,0)-$H2))} -> 0 | J2: =($H2*$G2) -> 106.80164 | K2: =$F2*$H2 -> 320
A3: {=XLOOKUP($E3,'Maestro de productos 2024'!$A$3:$A$163,'Maestro de productos 2024'!$B$3:$B$163,0)} -> ID-3824 | B3: 45380 | C3: =YEAR(B3) -> 2024 | D3: =MONTH(B3) -> 3 | E3: Galletas chocochips | F3: {=XLOOKUP(E3,'Maestro de productos 2024'!$B$189:$B$196,'Maestro de productos 2024'!$D$189:$D$196,"No encontrado",0)} -> 10 | G3: {=XLOOKUP(E3,'Maestro de productos 2024'!$B$189:$B$196,'Maestro de productos 2024'!$E$189:$E$196,"No encontrado",0)} -> 3.3375513 | H3: 64 | I3: {=IF((XLOOKUP($E3,'Maestro de productos 2024'!$B$189:$B$196,'Maestro de productos 2024'!$C$189:$C$196,"No encontrado",0)-H3)<=0,"0",(VLOOKUP($E3,'Maestro de productos 2024'!$B$189:$C$196,2,0)-$H3))} -> 0 | J3: =($H3*$G3) -> 213.60328 | K3: =$F3*$H3 -> 640 | L3: =IF((F3*I3)=0," ",(F3*I3))
A4: {=XLOOKUP($E4,'Maestro de productos 2024'!$A$3:$A$163,'Maestro de productos 2024'!$B$3:$B$163,0)} -> ID-3826 | B4: 45387 | C4: =YEAR(B4) -> 2024 | D4: =MONTH(B4) -> 4 | E4: Brownie triple chocolate | F4: {=XLOOKUP(E4,'Maestro de productos 2024'!$B$189:$B$196,'Maestro de productos 2024'!$D$189:$D$196,"No encontrado",0)} -> 20 | G4: {=XLOOKUP(E4,'Maestro de productos 2024'!$B$189:$B$196,'Maestro de productos 2024'!$E$189:$E$196,"No encontrado",0)} -> 7.1039722 | H4: 18 | I4: {=IF((XLOOKUP($E4,'Maestro de productos 2024'!$B$189:$B$196,'Maestro de productos 2024'!$C$189:$C$196,"No encontrado",0)-H4)<=0,"0",(VLOOKUP($E4,'Maestro de productos 2024'!$B$189:$C$196,2,0)-$H4))} -> 0 | J4: =($H4*$G4) -> 127.8715 | K4: =$F4*$H4 -> 360
A5: {=XLOOKUP($E5,'Maestro de productos 2024'!$A$3:$A$163,'Maestro de productos 2024'!$B$3:$B$163,0)} -> ID-3827 | B5: 45394 | C5: =YEAR(B5) -> 2024 | D5: =MONTH(B5) -> 4 | E5: Galletas danesas | F5: {=XLOOKUP(E5,'Maestro de productos 2024'!$B$189:$B$196,'Maestro de productos 2024'!$D$189:$D$196,"No encontrado",0)} -> 7 | G5: {=XLOOKUP(E5,'Maestro de productos 2024'!$B$189:$B$196,'Maestro de productos 2024'!$E$189:$E$196,"No encontrado",0)} -> 2.6234601 | H5: 35 | I5: {=IF((XLOOKUP($E5,'Maestro de productos 2024'!$B$189:$B$196,'Maestro de productos 2024'!$C$189:$C$196,"No encontrado",0)-H5)<=0,"0",(VLOOKUP($E5,'Maestro de productos 2024'!$B$189:$C$196,2,0)-$H5))} -> 0 | J5: =($H5*$G5) -> 91.821103 | K5: =$F5*$H5 -> 245
A6: {=XLOOKUP($E6,'Maestro de productos 2024'!$A$3:$A$163,'Maestro de productos 2024'!$B$3:$B$163,0)} -> ID-3824 | B6: 45399 | C6: =YEAR(B6) -> 2024 | D6: =MONTH(B6) -> 4 | E6: Galletas chocochips | F6: {=XLOOKUP(E6,'Maestro de productos 2024'!$B$189:$B$196,'Maestro de productos 2024'!$D$189:$D$196,"No encontrado",0)} -> 10 | G6: {=XLOOKUP(E6,'Maestro de productos 2024'!$B$189:$B$196,'Maestro de productos 2024'!$E$189:$E$196,"No encontrado",0)} -> 3.3375513 | H6: 64 | I6: {=IF((XLOOKUP($E6,'Maestro de productos 2024'!$B$189:$B$196,'Maestro de productos 2024'!$C$189:$C$196,"No encontrado",0)-H6)<=0,"0",(VLOOKUP($E6,'Maestro de productos 2024'!$B$189:$C$196,2,0)-$H6))} -> 0 | J6: =($H6*$G6) -> 213.60328 | K6: =$F6*$H6 -> 640
A7: {=XLOOKUP($E7,'Maestro de productos 2024'!$A$3:$A$163,'Maestro de productos 2024'!$B$3:$B$163,0)} -> ID-3825 | B7: 45401 | C7: =YEAR(B7) -> 2024 | D7: =MONTH(B7) -> 4 | E7: Mini cheesecake | F7: {=XLOOKUP(E7,'Maestro de productos 2024'!$B$189:$B$196,'Maestro de productos 2024'!$D$189:$D$196,"No encontrado",0)} -> 20 | G7: {=XLOOKUP(E7,'Maestro de productos 2024'!$B$189:$B$196,'Maestro de productos 2024'!$E$189:$E$196,"No encontrado",0)} -> 7.6091462 | H7: 16 | I7: {=IF((XLOOKUP($E7,'Maestro de productos 2024'!$B$189:$B$196,'Maestro de productos 2024'!$C$189:$C$196,"No encontrado",0)-H7)<=0,"0",(VLOOKUP($E7,'Maestro de productos 2024'!$B$189:$C$196,2,0)-$H7))} -> 0 | J7: =($H7*$G7) -> 121.74634 | K7: =$F7*$H7 -> 320 | L7: =IF((F7*I7)=0," ",(F7*I7))
A8: {=XLOOKUP($E8,'Maestro de productos 2024'!$A$3:$A$163,'Maestro de productos 2024'!$B$3:$B$163,0)} -> ID-3826 | B8: 45406 | C8: =YEAR(B8) -> 2024 | D8: =MONTH(B8) -> 4 | E8: Brownie triple chocolate | F8: {=XLOOKUP(E8,'Maestro de productos 2024'!$B$189:$B$196,'Maestro de productos 2024'!$D$189:$D$196,"No encontrado",0)} -> 20 | G8: {=XLOOKUP(E8,'Maestro de productos 2024'!$B$189:$B$196,'Maestro de productos 2024'!$E$189:$E$196,"No encontrado",0)} -> 7.1039722 | H8: 36 | I8: {=IF((XLOOKUP($E8,'Maestro de productos 2024'!$B$189:$B$196,'Maestro de productos 2024'!$C$189:$C$196,"No encontrado",0)-H8)<=0,"0",(VLOOKUP($E8,'Maestro de productos 2024'!$B$189:$C$196,2,0)-$H8))} -> 0 | J8: =($H8*$G8) -> 255.743 | K8: =$F8*$H8 -> 720 | L8: =IF((F8*I8)=0," ",(F8*I8))
A9: {=XLOOKUP($E9,'Maestro de productos 2024'!$A$3:$A$163,'Maestro de productos 2024'!$B$3:$B$163,0)} -> ID-3827 | B9: 45408 | C9: =YEAR(B9) -> 2024 | D9: =MONTH(B9) -> 4 | E9: Galletas danesas | F9: {=XLOOKUP(E9,'Maestro de productos 2024'!$B$189:$B$196,'Maestro de productos 2024'!$D$189:$D$196,"No encontrado",0)} -> 7 | G9: {=XLOOKUP(E9,'Maestro de productos 2024'!$B$189:$B$196,'Maestro de productos 2024'!$E$189:$E$196,"No encontrado",0)} -> 2.6234601 | H9: 35 | I9: {=IF((XLOOKUP($E9,'Maestro de productos 2024'!$B$189:$B$196,'Maestro de productos 2024'!$C$189:$C$196,"No encontrado",0)-H9)<=0,"0",(VLOOKUP($E9,'Maestro de productos 2024'!$B$189:$C$196,2,0)-$H9))} -> 0 | J9: =($H9*$G9) -> 91.821103 | K9: =$F9*$H9 -> 245 | L9: =IF((F9*I9)=0," ",(F9*I9))
A10: {=XLOOKUP($E10,'Maestro de productos 2024'!$A$3:$A$163,'Maestro de productos 2024'!$B$3:$B$163,0)} -> ID-3828 | B10: 45413 | C10: =YEAR(B10) -> 2024 | D10: =MONTH(B10) -> 5 | E10: Muffins de yogurt | F10: {=XLOOKUP(E10,'Maestro de productos 2024'!$B$189:$B$196,'Maestro de productos 2024'!$D$189:$D$196,"No encontrado",0)} -> 20 | G10: {=XLOOKUP(E10,'Maestro de productos 2024'!$B$189:$B$196,'Maestro de productos 2024'!$E$189:$E$196,"No encontrado",0)} -> 7.3010641 | H10: 24 | I10: {=IF((XLOOKUP($E10,'Maestro de productos 2024'!$B$189:$B$196,'Maestro de productos 2024'!$C$189:$C$196,"No encontrado",0)-H10)<=0,"0",(VLOOKUP($E10,'Maestro de productos 2024'!$B$189:$C$196,2,0)-$H10))} -> 0 | J10: =($H10*$G10) -> 175.22554 | K10: =$F10*$H10 -> 480 | L10: =IF((F10*I10)=0," ",(F10*I10))
A11: {=XLOOKUP($E11,'Maestro de productos 2024'!$A$3:$A$163,'Maestro de productos 2024'!$B$3:$B$163,0)} -> ID-3824 | B11: 45415 | C11: =YEAR(B11) -> 2024 | D11: =MONTH(B11) -> 5 | E11: Galletas chocochips | F11: {=XLOOKUP(E11,'Maestro de productos 2024'!$B$189:$B$196,'Maestro de productos 2024'!$D$189:$D$196,"No encontrado",0)} -> 10 | G11: {=XLOOKUP(E11,'Maestro de productos 2024'!$B$189:$B$196,'Maestro de productos 2024'!$E$189:$E$196,"No encontrado",0)} -> 3.3375513 | H11: 30 | I11: {=IF((XLOOKUP($E11,'Maestro de productos 2024'!$B$189:$B$196,'Maestro de productos 2024'!$C$189:$C$196,"No encontrado",0)-H11)<=0,"0",(VLOOKUP($E11,'Maestro de productos 2024'!$B$189:$C$196,2,0)-$H11))} -> 2 | J11: =($H11*$G11) -> 100.12654 | K11: =$F11*$H11 -> 300 | L11: =IF((F11*I11)=0," ",(F11*I11)) -> 20
A12: {=XLOOKUP($E12,'Maestro de productos 2024'!$A$3:$A$163,'Maestro de productos 2024'!$B$3:$B$163,0)} -> ID-3825 | B12: 45420 | C12: =YEAR(B12) -> 2024 | D12: =MONTH(B12) -> 5 | E12: Mini cheesecake | F12: {=XLOOKUP(E12,'Maestro de productos 2024'!$B$189:$B$196,'Maestro de productos 2024'!$D$189:$D$196,"No encontrado",0)} -> 20 | G12: {=XLOOKUP(E12,'Maestro de productos 2024'!$B$189:$B$196,'Maestro de productos 2024'!$E$189:$E$196,"No encontrado",0)} -> 7.6091462 | H12: 16 | I12: {=IF((XLOOKUP($E12,'Maestro de productos 2024'!$B$189:$B$196,'Maestro de productos 2024'!$C$189:$C$196,"No encontrado",0)-H12)<=0,"0",(VLOOKUP($E12,'Maestro de productos 2024'!$B$189:$C$196,2,0)-$H12))} -> 0 | J12: =($H12*$G12) -> 121.74634 | K12: =$F12*$H12 -> 320 | L12: =IF((F12*I12)=0," ",(F12*I12))
A13: {=XLOOKUP($E13,'Maestro de productos 2024'!$A$3:$A$163,'Maestro de productos 2024'!$B$3:$B$163,0)} -> ID-3824 | B13: 45422 | C13: =YEAR(B13) -> 2024 | D13: =MONTH(B13) -> 5 | E13: Galletas chocochips | F13: {=XLOOKUP(E13,'Maestro de productos 2024'!$B$189:$B$196,'Maestro de productos 2024'!$D$189:$D$196,"No encontrado",0)} -> 10 | G13: {=XLOOKUP(E13,'Maestro de productos 2024'!$B$189:$B$196,'Maestro de productos 2024'!$E$189:$E$196,"No encontrado",0)} -> 3.3375513 | H13: 32 | I13: {=IF((XLOOKUP($E13,'Maestro de productos 2024'!$B$189:$B$196,'Maestro de productos 2024'!$C$189:$C$196,"No encontrado",0)-H13)<=0,"0",(VLOOKUP($E13,'Maestro de productos 2024'!$B$189:$C$196,2,0)-$H13))} -> 0 | J13: =($H13*$G13) -> 106.80164 | K13: =$F13*$H13 -> 320 | L13: =IF((F13*I13)=0," ",(F13*I13))
A14: {=XLOOKUP($E14,'Maestro de productos 2024'!$A$3:$A$163,'Maestro de productos 2024'!$B$3:$B$163,0)} -> ID-3826 | B14: 45427 | C14: =YEAR(B14) -> 2024 | D14: =MONTH(B14) -> 5 | E14: Brownie triple chocolate | F14: {=XLOOKUP(E14,'Maestro de productos 2024'!$B$189:$B$196,'Maestro de productos 2024'!$D$189:$D$196,"No encontrado",0)} -> 20 | G14: {=XLOOKUP(E14,'Maestro de productos 2024'!$B$189:$B$196,'Maestro de productos 2024'!$E$189:$E$196,"No encontrado",0)} -> 7.1039722 | H14: 18 | I14: {=IF((XLOOKUP($E14,'Maestro de productos 2024'!$B$189:$B$196,'Maestro de productos 2024'!$C$189:$C$196,"No encontrado",0)-H14)<=0,"0",(VLOOKUP($E14,'Maestro de productos 2024'!$B$189:$C$196,2,0)-$H14))} -> 0 | J14: =($H14*$G14) -> 127.8715 | K14: =$F14*$H14 -> 360 | L14: =IF((F14*I14)=0," ",(F14*I14))
A15: {=XLOOKUP($E15,'Maestro de productos 2024'!$A$3:$A$163,'Maestro de productos 2024'!$B$3:$B$163,0)} -> ID-3828 | B15: 45429 | C15: =YEAR(B15) -> 2024 | D15: =MONTH(B15) -> 5 | E15: Muffins de yogurt | F15: {=XLOOKUP(E15,'Maestro de productos 2024'!$B$189:$B$196,'Maestro de productos 2024'!$D$189:$D$196,"No encontrado",0)} -> 20 | G15: {=XLOOKUP(E15,'Maestro de productos 2024'!$B$189:$B$196,'Maestro de productos 2024'!$E$189:$E$196,"No encontrado",0)} -> 7.3010641 | H15: 24 | I15: {=IF((XLOOKUP($E15,'Maestro de productos 2024'!$B$189:$B$196,'Maestro de productos 2024'!$C$189:$C$196,"No encontrado",0)-H15)<=0,"0",(VLOOKUP($E15,'Maestro de productos 2024'!$B$189:$C$196,2,0)-$H15))} -> 0 | J15: =($H15*$G15) -> 175.22554 | K15: =$F15*$H15 -> 480 | L15: =IF((F15*I15)=0," ",(F15*I15))
A16: {=XLOOKUP($E16,'Maestro de productos 2024'!$A$3:$A$163,'Maestro de productos 2024'!$B$3:$B$163,0)} -> ID-3828 | B16: 45434 | C16: =YEAR(B16) -> 2024 | D16: =MONTH(B16) -> 5 | E16: Muffins de yogurt | F16: {=XLOOKUP(E16,'Maestro de productos 2024'!$B$189:$B$196,'Maestro de productos 2024'!$D$189:$D$196,"No encontrado",0)} -> 20 | G16: {=XLOOKUP(E16,'Maestro de productos 2024'!$B$189:$B$196,'Maestro de productos 2024'!$E$189:$E$196,"No encontrado",0)} -> 7.3010641 | H16: 12 | I16: {=IF((XLOOKUP($E16,'Maestro de productos 2024'!$B$189:$B$196,'Maestro de productos 2024'!$C$189:$C$196,"No encontrado",0)-H16)<=0,"0",(VLOOKUP($E16,'Maestro de productos 2024'!$B$189:$C$196,2,0)-$H16))} -> 0 | J16: =($H16*$G16) -> 87.612769 | K16: =$F16*$H16 -> 240 | L16: =IF((F16*I16)=0," ",(F16*I16))
A17: {=XLOOKUP($E17,'Maestro de productos 2024'!$A$3:$A$163,'Maestro de productos 2024'!$B$3:$B$163,0)} -> ID-3824 | B17: 45436 | C17: =YEAR(B17) -> 2024 | D17: =MONTH(B17) -> 5 | E17: Galletas chocochips | F17: {=XLOOKUP(E17,'Maestro de productos 2024'!$B$189:$B$196,'Maestro de productos 2024'!$D$189:$D$196,"No encontrado",0)} -> 10 | G17: {=XLOOKUP(E17,'Maestro de productos 2024'!$B$189:$B$196,'Maestro de productos 2024'!$E$189:$E$196,"No encontrado",0)} -> 3.3375513 | H17: 29 | I17: {=IF((XLOOKUP($E17,'Maestro de productos 2024'!$B$189:$B$196,'Maestro de productos 2024'!$C$189:$C$196,"No encontrado",0)-H17)<=0,"0",(VLOOKUP($E17,'Maestro de productos 2024'!$B$189:$C$196,2,0)-$H17))} -> 3 | J17: =($H17*$G17) -> 96.788987 | K17: =$F17*$H17 -> 290 | L17: =IF((F17*I17)=0," ",(F17*I17)) -> 30
A18: {=XLOOKUP($E18,'Maestro de productos 2024'!$A$3:$A$163,'Maestro de productos 2024'!$B$3:$B$163,0)} -> ID-3825 | B18: 45441 | C18: =YEAR(B18) -> 2024 | D18: =MONTH(B18) -> 5 | E18: Mini cheesecake | F18: {=XLOOKUP(E18,'Maestro de productos 2024'!$B$189:$B$196,'Maestro de productos 2024'!$D$189:$D$196,"No encontrado",0)} -> 20 | G18: {=XLOOKUP(E18,'Maestro de productos 2024'!$B$189:$B$196,'Maestro de productos 2024'!$E$189:$E$196,"No encontrado",0)} -> 7.6091462 | H18: 14 | I18: {=IF((XLOOKUP($E18,'Maestro de productos 2024'!$B$189:$B$196,'Maestro de productos 2024'!$C$189:$C$196,"No encontrado",0)-H18)<=0,"0",(VLOOKUP($E18,'Maestro de productos 2024'!$B$189:$C$196,2,0)-$H18))} -> 2 | J18: =($H18*$G18) -> 106.52805 | K18: =$F18*$H18 -> 280 | L18: =IF((F18*I18)=0," ",(F18*I18)) -> 40
... A78: {=XLOOKUP($E78,'Maestro de productos 2024'!$A$3:$A$163,'Maestro de productos 2024'!$B$3:$B$163,0)} -> ID-3825 | B78: 45653 | C78: =YEAR(B78) -> 2024 | D78: =MONTH(B78) -> 12 | E78: Mini cheesecake | F78: {=XLOOKUP(E78,'Maestro de productos 2024'!$B$189:$B$196,'Maestro de productos 2024'!$D$189:$D$196,"No encontrado",0)} -> 20 | G78: {=XLOOKUP(E78,'Maestro de productos 2024'!$B$189:$B$196,'Maestro de productos 2024'!$E$189:$E$196,"No encontrado",0)} -> 7.6091462 | H78: 16 | I78: {=IF((XLOOKUP($E78,'Maestro de productos 2024'!$B$189:$B$196,'Maestro de productos 2024'!$C$189:$C$196,"No encontrado",0)-H78)<=0,"0",(VLOOKUP($E78,'Maestro de productos 2024'!$B$189:$C$196,2,0)-$H78))} -> 0 | J78: =($H78*$G78) -> 121.74634 | K78: =$F78*$H78 -> 320 | L78: =IF((F78*I78)=0," ",(F78*I78))
A79: ID | B79: FechaDelPedido | C79: Año | D79: Mes | E79: Producto | F79: PV | G79: CV | H79: CantidadVendida | I79: CantidadNoVendida | J79: TotalCV | K79: IT | L79: Perdidas
A80: {=XLOOKUP($E80,'Maestro de productos 2024'!$A$3:$A$163,'Maestro de productos 2024'!$B$3:$B$163,0)} -> ID-3828 | B80: 45660 | C80: =YEAR(B80) -> 2025 | D80: =MONTH(B80) -> 1 | E80: Muffins de yogurt | F80: {=XLOOKUP(E80,'Maestro de productos 2025'!$B$189:$B$196,'Maestro de productos 2025'!$D$189:$D$196,"No encontrado",0)} -> 21 | G80: {=XLOOKUP(E80,'Maestro de productos 2025'!$B$189:$B$196,'Maestro de productos 2025'!$E$189:$E$196,"No encontrado",0)} -> 8.3593511 | H80: 24 | I80: {=IF((XLOOKUP($E80,'Maestro de productos 2025'!$B$189:$B$196,'Maestro de productos 2025'!$C$189:$C$196,"No encontrado",0)-H80)<=0,"0",(VLOOKUP($E80,'Maestro de productos 2025'!$B$189:$C$196,2,0)-$H80))} -> 0 | J80: =($H80*$G80) -> 200.62443 | K80: =$F80*$H80 -> 504 | L80: =IF((F80*I80)=0," ",(F80*I80))
A81: {=XLOOKUP($E81,'Maestro de productos 2024'!$A$3:$A$163,'Maestro de productos 2024'!$B$3:$B$163,0)} -> ID-3831 | B81: 45665 | C81: =YEAR(B81) -> 2025 | D81: =MONTH(B81) -> 1 | E81: Muffin de chocolate | F81: {=XLOOKUP(E81,'Maestro de productos 2025'!$B$189:$B$196,'Maestro de productos 2025'!$D$189:$D$196,"No encontrado",0)} -> 20 | G81: {=XLOOKUP(E81,'Maestro de productos 2025'!$B$189:$B$196,'Maestro de productos 2025'!$E$189:$E$196,"No encontrado",0)} -> 7.8897601 | H81: 14 | I81: {=IF((XLOOKUP($E81,'Maestro de productos 2025'!$B$189:$B$196,'Maestro de productos 2025'!$C$189:$C$196,"No encontrado",0)-H81)<=0,"0",(VLOOKUP($E81,'Maestro de productos 2025'!$B$189:$C$196,2,0)-$H81))} -> 0 | J81: =($H81*$G81) -> 110.45664 | K81: =$F81*$H81 -> 280 | L81: =IF((F81*I81)=0," ",(F81*I81))
A82: {=XLOOKUP($E82,'Maestro de productos 2024'!$A$3:$A$163,'Maestro de productos 2024'!$B$3:$B$163,0)} -> ID-3825 | B82: 45667 | C82: =YEAR(B82) -> 2025 | D82: =MONTH(B82) -> 1 | E82: Mini cheesecake | F82: {=XLOOKUP(E82,'Maestro de productos 2025'!$B$189:$B$196,'Maestro de productos 2025'!$D$189:$D$196,"No encontrado",0)} -> 25 | G82: {=XLOOKUP(E82,'Maestro de productos 2025'!$B$189:$B$196,'Maestro de productos 2025'!$E$189:$E$196,"No encontrado",0)} -> 10.264506 | H82: 16 | I82: {=IF((XLOOKUP($E82,'Maestro de productos 2025'!$B$189:$B$196,'Maestro de productos 2025'!$C$189:$C$196,"No encontrado",0)-H82)<=0,"0",(VLOOKUP($E82,'Maestro de productos 2025'!$B$189:$C$196,2,0)-$H82))} -> 0 | J82: =($H82*$G82) -> 164.2321 | K82: =$F82*$H82 -> 400 | L82: =IF((F82*I82)=0," ",(F82*I82))
A83: {=XLOOKUP($E83,'Maestro de productos 2024'!$A$3:$A$163,'Maestro de productos 2024'!$B$3:$B$163,0)} -> ID-3824 | B83: 45672 | C83: =YEAR(B83) -> 2025 | D83: =MONTH(B83) -> 1 | E83: Galletas chocochips | F83: {=XLOOKUP(E83,'Maestro de productos 2025'!$B$189:$B$196,'Maestro de productos 2025'!$D$189:$D$196,"No encontrado",0)} -> 10 | G83: {=XLOOKUP(E83,'Maestro de productos 2025'!$B$189:$B$196,'Maestro de productos 2025'!$E$189:$E$196,"No encontrado",0)} -> 4.071744 | H83: 25 | I83: {=IF((XLOOKUP($E83,'Maestro de productos 2025'!$B$189:$B$196,'Maestro de productos 2025'!$C$189:$C$196,"No encontrado",0)-H83)<=0,"0",(VLOOKUP($E83,'Maestro de productos 2025'!$B$189:$C$196,2,0)-$H83))} -> 7 | J83: =($H83*$G83) -> 101.7936 | K83: =$F83*$H83 -> 250 | L83: =IF((F83*I83)=0," ",(F83*I83)) -> 70
A84: {=XLOOKUP($E84,'Maestro de productos 2024'!$A$3:$A$163,'Maestro de productos 2024'!$B$3:$B$163,0)} -> ID-3829 | B84: 45674 | C84: =YEAR(B84) -> 2025 | D84: =MONTH(B84) -> 1 | E84: Besos de nuez | F84: {=XLOOKUP(E84,'Maestro de productos 2025'!$B$189:$B$196,'Maestro de productos 2025'!$D$189:$D$196,"No encontrado",0)} -> 9 | G84: {=XLOOKUP(E84,'Maestro de productos 2025'!$B$189:$B$196,'Maestro de productos 2025'!$E$189:$E$196,"No encontrado",0)} -> 3.6108686 | H84: 45 | I84: {=IF((XLOOKUP($E84,'Maestro de productos 2025'!$B$189:$B$196,'Maestro de productos 2025'!$C$189:$C$196,"No encontrado",0)-H84)<=0,"0",(VLOOKUP($E84,'Maestro de productos 2025'!$B$189:$C$196,2,0)-$H84))} -> 5 | J84: =($H84*$G84) -> 162.48909 | K84: =$F84*$H84 -> 405 | L84: =IF((F84*I84)=0," ",(F84*I84)) -> 45
A85: {=XLOOKUP($E85,'Maestro de productos 2024'!$A$3:$A$163,'Maestro de productos 2024'!$B$3:$B$163,0)} -> ID-3828 | B85: 45679 | C85: =YEAR(B85) -> 2025 | D85: =MONTH(B85) -> 1 | E85: Muffins de yogurt | F85: {=XLOOKUP(E85,'Maestro de productos 2025'!$B$189:$B$196,'Maestro de productos 2025'!$D$189:$D$196,"No encontrado",0)} -> 21 | G85: {=XLOOKUP(E85,'Maestro de productos 2025'!$B$189:$B$196,'Maestro de productos 2025'!$E$189:$E$196,"No encontrado",0)} -> 8.3593511 | H85: 12 | I85: {=IF((XLOOKUP($E85,'Maestro de productos 2025'!$B$189:$B$196,'Maestro de productos 2025'!$C$189:$C$196,"No encontrado",0)-H85)<=0,"0",(VLOOKUP($E85,'Maestro de productos 2025'!$B$189:$C$196,2,0)-$H85))} -> 0 | J85: =($H85*$G85) -> 100.31221 | K85: =$F85*$H85 -> 252 | L85: =IF((F85*I85)=0," ",(F85*I85))
A86: {=XLOOKUP($E86,'Maestro de productos 2024'!$A$3:$A$163,'Maestro de productos 2024'!$B$3:$B$163,0)} -> ID-3827 | B86: 45681 | C86: =YEAR(B86) -> 2025 | D86: =MONTH(B86) -> 1 | E86: Galletas danesas | F86: {=XLOOKUP(E86,'Maestro de productos 2025'!$B$189:$B$196,'Maestro de productos 2025'!$D$189:$D$196,"No encontrado",0)} -> 7 | G86: {=XLOOKUP(E86,'Maestro de productos 2025'!$B$189:$B$196,'Maestro de productos 2025'!$E$189:$E$196,"No encontrado",0)} -> 3.1117795 | H86: 31 | I86: {=IF((XLOOKUP($E86,'Maestro de productos 2025'!$B$189:$B$196,'Maestro de productos 2025'!$C$189:$C$196,"No encontrado",0)-H86)<=0,"0",(VLOOKUP($E86,'Maestro de productos 2025'!$B$189:$C$196,2,0)-$H86))} -> 4 | J86: =($H86*$G86) -> 96.465165 | K86: =$F86*$H86 -> 217 | L86: =IF((F86*I86)=0," ",(F86*I86)) -> 28
A87: {=XLOOKUP($E87,'Maestro de productos 2024'!$A$3:$A$163,'Maestro de productos 2024'!$B$3:$B$163,0)} -> ID-3830 | B87: 45686 | C87: =YEAR(B87) -> 2025 | D87: =MONTH(B87) -> 1 | E87: Flan de queso crema | F87: {=XLOOKUP(E87,'Maestro de productos 2025'!$B$189:$B$196,'Maestro de productos 2025'!$D$189:$D$196,"No encontrado",0)} -> 29 | G87: {=XLOOKUP(E87,'Maestro de productos 2025'!$B$189:$B$196,'Maestro de productos 2025'!$E$189:$E$196,"No encontrado",0)} -> 11.936875 | H87: 18 | I87: {=IF((XLOOKUP($E87,'Maestro de productos 2025'!$B$189:$B$196,'Maestro de productos 2025'!$C$189:$C$196,"No encontrado",0)-H87)<=0,"0",(VLOOKUP($E87,'Maestro de productos 2025'!$B$189:$C$196,2,0)-$H87))} -> 0 | J87: =($H87*$G87) -> 214.86375 | K87: =$F87*$H87 -> 522 | L87: =IF((F87*I87)=0," ",(F87*I87))
A88: {=XLOOKUP($E88,'Maestro de productos 2024'!$A$3:$A$163,'Maestro de productos 2024'!$B$3:$B$163,0)} -> ID-3826 | B88: 45688 | C88: =YEAR(B88) -> 2025 | D88: =MONTH(B88) -> 1 | E88: Brownie triple chocolate | F88: {=XLOOKUP(E88,'Maestro de productos 2025'!$B$189:$B$196,'Maestro de productos 2025'!$D$189:$D$196,"No encontrado",0)} -> 20 | G88: {=XLOOKUP(E88,'Maestro de productos 2025'!$B$189:$B$196,'Maestro de productos 2025'!$E$189:$E$196,"No encontrado",0)} -> 8.0731235 | H88: 18 | I88: {=IF((XLOOKUP($E88,'Maestro de productos 2025'!$B$189:$B$196,'Maestro de productos 2025'!$C$189:$C$196,"No encontrado",0)-H88)<=0,"0",(VLOOKUP($E88,'Maestro de productos 2025'!$B$189:$C$196,2,0)-$H88))} -> 0 | J88: =($H88*$G88) -> 145.31622 | K88: =$F88*$H88 -> 360 | L88: =IF((F88*I88)=0," ",(F88*I88))
A89: {=XLOOKUP($E89,'Maestro de productos 2024'!$A$3:$A$163,'Maestro de productos 2024'!$B$3:$B$163,0)} -> ID-3824 | B89: 45693 | C89: =YEAR(B89) -> 2025 | D89: =MONTH(B89) -> 2 | E89: Galletas chocochips | F89: {=XLOOKUP(E89,'Maestro de productos 2025'!$B$189:$B$196,'Maestro de productos 2025'!$D$189:$D$196,"No encontrado",0)} -> 10 | G89: {=XLOOKUP(E89,'Maestro de productos 2025'!$B$189:$B$196,'Maestro de productos 2025'!$E$189:$E$196,"No encontrado",0)} -> 4.071744 | H89: 32 | I89: {=IF((XLOOKUP($E89,'Maestro de productos 2025'!$B$189:$B$196,'Maestro de productos 2025'!$C$189:$C$196,"No encontrado",0)-H89)<=0,"0",(VLOOKUP($E89,'Maestro de productos 2025'!$B$189:$C$196,2,0)-$H89))} -> 0 | J89: =($H89*$G89) -> 130.29581 | K89: =$F89*$H89 -> 320 | L89: =IF((F89*I89)=0," ",(F89*I89))
A90: {=XLOOKUP($E90,'Maestro de productos 2024'!$A$3:$A$163,'Maestro de productos 2024'!$B$3:$B$163,0)} -> ID-3828 | B90: 45695 | C90: =YEAR(B90) -> 2025 | D90: =MONTH(B90) -> 2 | E90: Muffins de yogurt | F90: {=XLOOKUP(E90,'Maestro de productos 2025'!$B$189:$B$196,'Maestro de productos 2025'!$D$189:$D$196,"No encontrado",0)} -> 21 | G90: {=XLOOKUP(E90,'Maestro de productos 2025'!$B$189:$B$196,'Maestro de productos 2025'!$E$189:$E$196,"No encontrado",0)} -> 8.3593511 | H90: 24 | I90: {=IF((XLOOKUP($E90,'Maestro de productos 2025'!$B$189:$B$196,'Maestro de productos 2025'!$C$189:$C$196,"No encontrado",0)-H90)<=0,"0",(VLOOKUP($E90,'Maestro de productos 2025'!$B$189:$C$196,2,0)-$H90))} -> 0 | J90: =($H90*$G90) -> 200.62443 | K90: =$F90*$H90 -> 504 | L90: =IF((F90*I90)=0," ",(F90*I90))
A91: {=XLOOKUP($E91,'Maestro de productos 2024'!$A$3:$A$163,'Maestro de productos 2024'!$B$3:$B$163,0)} -> ID-3828 | B91: 45700 | C91: =YEAR(B91) -> 2025 | D91: =MONTH(B91) -> 2 | E91: Muffins de yogurt | F91: {=XLOOKUP(E91,'Maestro de productos 2025'!$B$189:$B$196,'Maestro de productos 2025'!$D$189:$D$196,"No encontrado",0)} -> 21 | G91: {=XLOOKUP(E91,'Maestro de productos 2025'!$B$189:$B$196,'Maestro de productos 2025'!$E$189:$E$196,"No encontrado",0)} -> 8.3593511 | H91: 12 | I91: {=IF((XLOOKUP($E91,'Maestro de productos 2025'!$B$189:$B$196,'Maestro de productos 2025'!$C$189:$C$196,"No encontrado",0)-H91)<=0,"0",(VLOOKUP($E91,'Maestro de productos 2025'!$B$189:$C$196,2,0)-$H91))} -> 0 | J91: =($H91*$G91) -> 100.31221 | K91: =$F91*$H91 -> 252 | L91: =IF((F91*I91)=0," ",(F91*I91))
... A95: {=XLOOKUP($E95,'Maestro de productos 2024'!$A$3:$A$163,'Maestro de productos 2024'!$B$3:$B$163,0)} -> ID-3825 | B95: 45714 | C95: =YEAR(B95) -> 2025 | D95: =MONTH(B95) -> 2 | E95: Mini cheesecake | F95: {=XLOOKUP(E95,'Maestro de productos 2025'!$B$189:$B$196,'Maestro de productos 2025'!$D$189:$D$196,"No encontrado",0)} -> 25 | G95: {=XLOOKUP(E95,'Maestro de productos 2025'!$B$189:$B$196,'Maestro de productos 2025'!$E$189:$E$196,"No encontrado",0)} -> 10.264506 | H95: 16 | I95: {=IF((XLOOKUP($E95,'Maestro de productos 2025'!$B$189:$B$196,'Maestro de productos 2025'!$C$189:$C$196,"No encontrado",0)-H95)<=0,"0",(VLOOKUP($E95,'Maestro de productos 2025'!$B$189:$C$196,2,0)-$H95))} -> 0 | J95: =($H95*$G95) -> 164.2321 | K95: =$F95*$H95 -> 400 | L95: =IF((F95*I95)=0," ",(F95*I95))
A96: {=XLOOKUP($E96,'Maestro de productos 2024'!$A$3:$A$163,'Maestro de productos 2024'!$B$3:$B$163,0)} -> ID-3824 | B96: 45716 | C96: =YEAR(B96) -> 2025 | D96: =MONTH(B96) -> 2 | E96: Galletas chocochips | F96: {=XLOOKUP(E96,'Maestro de productos 2025'!$B$189:$B$196,'Maestro de productos 2025'!$D$189:$D$196,"No encontrado",0)} -> 10 | G96: {=XLOOKUP(E96,'Maestro de productos 2025'!$B$189:$B$196,'Maestro de productos 2025'!$E$189:$E$196,"No encontrado",0)} -> 4.071744 | H96: 32 | I96: {=IF((XLOOKUP($E96,'Maestro de productos 2025'!$B$189:$B$196,'Maestro de productos 2025'!$C$189:$C$196,"No encontrado",0)-H96)<=0,"0",(VLOOKUP($E96,'Maestro de productos 2025'!$B$189:$C$196,2,0)-$H96))} -> 0 | J96: =($H96*$G96) -> 130.29581 | K96: =$F96*$H96 -> 320 | L96: =IF((F96*I96)=0," ",(F96*I96)) | N96: =SUM(I83+I93+I99+I104+I108+I111+I119+I132+I142+I147+I161) -> 29
A97: {=XLOOKUP($E97,'Maestro de productos 2024'!$A$3:$A$163,'Maestro de productos 2024'!$B$3:$B$163,0)} -> ID-3828 | B97: 45721 | C97: =YEAR(B97) -> 2025 | D97: =MONTH(B97) -> 3 | E97: Muffins de yogurt | F97: {=XLOOKUP(E97,'Maestro de productos 2025'!$B$189:$B$196,'Maestro de productos 2025'!$D$189:$D$196,"No encontrado",0)} -> 21 | G97: {=XLOOKUP(E97,'Maestro de productos 2025'!$B$189:$B$196,'Maestro de productos 2025'!$E$189:$E$196,"No encontrado",0)} -> 8.3593511 | H97: 24 | I97: {=IF((XLOOKUP($E97,'Maestro de productos 2025'!$B$189:$B$196,'Maestro de productos 2025'!$C$189:$C$196,"No encontrado",0)-H97)<=0,"0",(VLOOKUP($E97,'Maestro de productos 2025'!$B$189:$C$196,2,0)-$H97))} -> 0 | J97: =($H97*$G97) -> 200.62443 | K97: =$F97*$H97 -> 504 | L97: =IF((F97*I97)=0," ",(F97*I97))
A98: {=XLOOKUP($E98,'Maestro de productos 2024'!$A$3:$A$163,'Maestro de productos 2024'!$B$3:$B$163,0)} -> ID-3831 | B98: 45723 | C98: =YEAR(B98) -> 2025 | D98: =MONTH(B98) -> 3 | E98: Muffin de chocolate | F98: {=XLOOKUP(E98,'Maestro de productos 2025'!$B$189:$B$196,'Maestro de productos 2025'!$D$189:$D$196,"No encontrado",0)} -> 20 | G98: {=XLOOKUP(E98,'Maestro de productos 2025'!$B$189:$B$196,'Maestro de productos 2025'!$E$189:$E$196,"No encontrado",0)} -> 7.8897601 | H98: 12 | I98: {=IF((XLOOKUP($E98,'Maestro de productos 2025'!$B$189:$B$196,'Maestro de productos 2025'!$C$189:$C$196,"No encontrado",0)-H98)<=0,"0",(VLOOKUP($E98,'Maestro de productos 2025'!$B$189:$C$196,2,0)-$H98))} -> 2 | J98: =($H98*$G98) -> 94.677121 | K98: =$F98*$H98 -> 240 | L98: =IF((F98*I98)=0," ",(F98*I98)) -> 40
A99: {=XLOOKUP($E99,'Maestro de productos 2024'!$A$3:$A$163,'Maestro de productos 2024'!$B$3:$B$163,0)} -> ID-3824 | B99: 45728 | C99: =YEAR(B99) -> 2025 | D99: =MONTH(B99) -> 3 | E99: Galletas chocochips | F99: {=XLOOKUP(E99,'Maestro de productos 2025'!$B$189:$B$196,'Maestro de productos 2025'!$D$189:$D$196,"No encontrado",0)} -> 10 | G99: {=XLOOKUP(E99,'Maestro de productos 2025'!$B$189:$B$196,'Maestro de productos 2025'!$E$189:$E$196,"No encontrado",0)} -> 4.071744 | H99: 30 | I99: {=IF((XLOOKUP($E99,'Maestro de productos 2025'!$B$189:$B$196,'Maestro de productos 2025'!$C$189:$C$196,"No encontrado",0)-H99)<=0,"0",(VLOOKUP($E99,'Maestro de productos 2025'!$B$189:$C$196,2,0)-$H99))} -> 2 | J99: =($H99*$G99) -> 122.15232 | K99: =$F99*$H99 -> 300 | L99: =IF((F99*I99)=0," ",(F99*I99)) -> 20
A100: {=XLOOKUP($E100,'Maestro de productos 2024'!$A$3:$A$163,'Maestro de productos 2024'!$B$3:$B$163,0)} -> ID-3827 | B100: 45730 | C100: =YEAR(B100) -> 2025 | D100: =MONTH(B100) -> 3 | E100: Galletas danesas | F100: {=XLOOKUP(E100,'Maestro de productos 2025'!$B$189:$B$196,'Maestro de productos 2025'!$D$189:$D$196,"No encontrado",0)} -> 7 | G100: {=XLOOKUP(E100,'Maestro de productos 2025'!$B$189:$B$196,'Maestro de productos 2025'!$E$189:$E$196,"No encontrado",0)} -> 3.1117795 | H100: 35 | I100: {=IF((XLOOKUP($E100,'Maestro de productos 2025'!$B$189:$B$196,'Maestro de productos 2025'!$C$189:$C$196,"No encontrado",0)-H100)<=0,"0",(VLOOKUP($E100,'Maestro de productos 2025'!$B$189:$C$196,2,0)-$H100))} -> 0 | J100: =($H100*$G100) -> 108.91228 | K100: =$F100*$H100 -> 245 | L100: =IF((F100*I100)=0," ",(F100*I100))
A101: {=XLOOKUP($E101,'Maestro de productos 2024'!$A$3:$A$163,'Maestro de productos 2024'!$B$3:$B$163,0)} -> ID-3828 | B101: 45735 | C101: =YEAR(B101) -> 2025 | D101: =MONTH(B101) -> 3 | E101: Muffins de yogurt | F101: {=XLOOKUP(E101,'Maestro de productos 2025'!$B$189:$B$196,'Maestro de productos 2025'!$D$189:$D$196,"No encontrado",0)} -> 21 | G101: {=XLOOKUP(E101,'Maestro de productos 2025'!$B$189:$B$196,'Maestro de productos 2025'!$E$189:$E$196,"No encontrado",0)} -> 8.3593511 | H101: 12 | I101: {=IF((XLOOKUP($E101,'Maestro de productos 2025'!$B$189:$B$196,'Maestro de productos 2025'!$C$189:$C$196,"No encontrado",0)-H101)<=0,"0",(VLOOKUP($E101,'Maestro de productos 2025'!$B$189:$C$196,2,0)-$H101))} -> 0 | J101: =($H101*$G101) -> 100.31221 | K101: =$F101*$H101 -> 252 | L101: =IF((F101*I101)=0," ",(F101*I101))
A102: {=XLOOKUP($E102,'Maestro de productos 2024'!$A$3:$A$163,'Maestro de productos 2024'!$B$3:$B$163,0)} -> ID-3826 | B102: 45737 | C102: =YEAR(B102) -> 2025 | D102: =MONTH(B102) -> 3 | E102: Brownie triple chocolate | F102: {=XLOOKUP(E102,'Maestro de productos 2025'!$B$189:$B$196,'Maestro de productos 2025'!$D$189:$D$196,"No encontrado",0)} -> 20 | G102: {=XLOOKUP(E102,'Maestro de productos 2025'!$B$189:$B$196,'Maestro de productos 2025'!$E$189:$E$196,"No encontrado",0)} -> 8.0731235 | H102: 18 | I102: {=IF((XLOOKUP($E102,'Maestro de productos 2025'!$B$189:$B$196,'Maestro de productos 2025'!$C$189:$C$196,"No encontrado",0)-H102)<=0,"0",(VLOOKUP($E102,'Maestro de productos 2025'!$B$189:$C$196,2,0)-$H102))} -> 0 | J102: =($H102*$G102) -> 145.31622 | K102: =$F102*$H102 -> 360 | L102: =IF((F102*I102)=0," ",(F102*I102))
A103: {=XLOOKUP($E103,'Maestro de productos 2024'!$A$3:$A$163,'Maestro de productos 2024'!$B$3:$B$163,0)} -> ID-3825 | B103: 45742 | C103: =YEAR(B103) -> 2025 | D103: =MONTH(B103) -> 3 | E103: Mini cheesecake | F103: {=XLOOKUP(E103,'Maestro de productos 2025'!$B$189:$B$196,'Maestro de productos 2025'!$D$189:$D$196,"No encontrado",0)} -> 25 | G103: {=XLOOKUP(E103,'Maestro de productos 2025'!$B$189:$B$196,'Maestro de productos 2025'!$E$189:$E$196,"No encontrado",0)} -> 10.264506 | H103: 15 | I103: {=IF((XLOOKUP($E103,'Maestro de productos 2025'!$B$189:$B$196,'Maestro de productos 2025'!$C$189:$C$196,"No encontrado",0)-H103)<=0,"0",(VLOOKUP($E103,'Maestro de productos 2025'!$B$189:$C$196,2,0)-$H103))} -> 1 | J103: =($H103*$G103) -> 153.9676 | K103: =$F103*$H103 -> 375 | L103: =IF((F103*I103)=0," ",(F103*I103)) -> 25
A104: {=XLOOKUP($E104,'Maestro de productos 2024'!$A$3:$A$163,'Maestro de productos 2024'!$B$3:$B$163,0)} -> ID-3824 | B104: 45744 | C104: =YEAR(B104) -> 2025 | D104: =MONTH(B104) -> 3 | E104: Galletas chocochips | F104: {=XLOOKUP(E104,'Maestro de productos 2025'!$B$189:$B$196,'Maestro de productos 2025'!$D$189:$D$196,"No encontrado",0)} -> 10 | G104: {=XLOOKUP(E104,'Maestro de productos 2025'!$B$189:$B$196,'Maestro de productos 2025'!$E$189:$E$196,"No encontrado",0)} -> 4.071744 | H104: 31 | I104: {=IF((XLOOKUP($E104,'Maestro de productos 2025'!$B$189:$B$196,'Maestro de productos 2025'!$C$189:$C$196,"No encontrado",0)-H104)<=0,"0",(VLOOKUP($E104,'Maestro de productos 2025'!$B$189:$C$196,2,0)-$H104))} -> 1 | J104: =($H104*$G104) -> 126.22406 | K104: =$F104*$H104 -> 310 | L104: =IF((F104*I104)=0," ",(F104*I104)) -> 10
A105: {=XLOOKUP($E105,'Maestro de productos 2024'!$A$3:$A$163,'Maestro de productos 2024'!$B$3:$B$163,0)} -> ID-3828 | B105: 45749 | C105: =YEAR(B105) -> 2025 | D105: =MONTH(B105) -> 4 | E105: Muffins de yogurt | F105: {=XLOOKUP(E105,'Maestro de productos 2025'!$B$189:$B$196,'Maestro de productos 2025'!$D$189:$D$196,"No encontrado",0)} -> 21 | G105: {=XLOOKUP(E105,'Maestro de productos 2025'!$B$189:$B$196,'Maestro de productos 2025'!$E$189:$E$196,"No encontrado",0)} -> 8.3593511 | H105: 24 | I105: {=IF((XLOOKUP($E105,'Maestro de productos 2025'!$B$189:$B$196,'Maestro de productos 2025'!$C$189:$C$196,"No encontrado",0)-H105)<=0,"0",(VLOOKUP($E105,'Maestro de productos 2025'!$B$189:$C$196,2,0)-$H105))} -> 0 | J105: =($H105*$G105) -> 200.62443 | K105: =$F105*$H105 -> 504 | L105: =IF((F105*I105)=0," ",(F105*I105))
A106: {=XLOOKUP($E106,'Maestro de productos 2024'!$A$3:$A$163,'Maestro de productos 2024'!$B$3:$B$163,0)} -> ID-3831 | B106: 45751 | C106: =YEAR(B106) -> 2025 | D106: =MONTH(B106) -> 4 | E106: Muffin de chocolate | F106: {=XLOOKUP(E106,'Maestro de productos 2025'!$B$189:$B$196,'Maestro de productos 2025'!$D$189:$D$196,"No encontrado",0)} -> 20 | G106: {=XLOOKUP(E106,'Maestro de productos 2025'!$B$189:$B$196,'Maestro de productos 2025'!$E$189:$E$196,"No encontrado",0)} -> 7.8897601 | H106: 14 | I106: {=IF((XLOOKUP($E106,'Maestro de productos 2025'!$B$189:$B$196,'Maestro de productos 2025'!$C$189:$C$196,"No encontrado",0)-H106)<=0,"0",(VLOOKUP($E106,'Maestro de productos 2025'!$B$189:$C$196,2,0)-$H106))} -> 0 | J106: =($H106*$G106) -> 110.45664 | K106: =$F106*$H106 -> 280 | L106: =IF((F106*I106)=0," ",(F106*I106))
A107: {=XLOOKUP($E107,'Maestro de productos 2024'!$A$3:$A$163,'Maestro de productos 2024'!$B$3:$B$163,0)} -> ID-3827 | B107: 45756 | C107: =YEAR(B107) -> 2025 | D107: =MONTH(B107) -> 4 | E107: Galletas danesas | F107: {=XLOOKUP(E107,'Maestro de productos 2025'!$B$189:$B$196,'Maestro de productos 2025'!$D$189:$D$196,"No encontrado",0)} -> 7 | G107: {=XLOOKUP(E107,'Maestro de productos 2025'!$B$189:$B$196,'Maestro de productos 2025'!$E$189:$E$196,"No encontrado",0)} -> 3.1117795 | H107: 33 | I107: {=IF((XLOOKUP($E107,'Maestro de productos 2025'!$B$189:$B$196,'Maestro de productos 2025'!$C$189:$C$196,"No encontrado",0)-H107)<=0,"0",(VLOOKUP($E107,'Maestro de productos 2025'!$B$189:$C$196,2,0)-$H107))} -> 2 | J107: =($H107*$G107) -> 102.68872 | K107: =$F107*$H107 -> 231 | L107: =IF((F107*I107)=0," ",(F107*I107)) -> 14
A108: {=XLOOKUP($E108,'Maestro de productos 2024'!$A$3:$A$163,'Maestro de productos 2024'!$B$3:$B$163,0)} -> ID-3824 | B108: 45758 | C108: =YEAR(B108) -> 2025 | D108: =MONTH(B108) -> 4 | E108: Galletas chocochips | F108: {=XLOOKUP(E108,'Maestro de productos 2025'!$B$189:$B$196,'Maestro de productos 2025'!$D$189:$D$196,"No encontrado",0)} -> 10 | G108: {=XLOOKUP(E108,'Maestro de productos 2025'!$B$189:$B$196,'Maestro de productos 2025'!$E$189:$E$196,"No encontrado",0)} -> 4.071744 | H108: 31 | I108: {=IF((XLOOKUP($E108,'Maestro de productos 2025'!$B$189:$B$196,'Maestro de productos 2025'!$C$189:$C$196,"No encontrado",0)-H108)<=0,"0",(VLOOKUP($E108,'Maestro de productos 2025'!$B$189:$C$196,2,0)-$H108))} -> 1 | J108: =($H108*$G108) -> 126.22406 | K108: =$F108*$H108 -> 310 | L108: =IF((F108*I108)=0," ",(F108*I108)) -> 10
... A162: {=XLOOKUP($E162,'Maestro de productos 2024'!$A$3:$A$163,'Maestro de productos 2024'!$B$3:$B$163,0)} -> ID-3828 | B162: 45959 | C162: =YEAR(B162) -> 2025 | D162: =MONTH(B162) -> 10 | E162: Muffins de yogurt | F162: {=XLOOKUP(E162,'Maestro de productos 2025'!$B$189:$B$196,'Maestro de productos 2025'!$D$189:$D$196,"No encontrado",0)} -> 21 | G162: {=XLOOKUP(E162,'Maestro de productos 2025'!$B$189:$B$196,'Maestro de productos 2025'!$E$189:$E$196,"No encontrado",0)} -> 8.3593511 | H162: 24 | I162: {=IF((XLOOKUP($E162,'Maestro de productos 2025'!$B$189:$B$196,'Maestro de productos 2025'!$C$189:$C$196,"No encontrado",0)-H162)<=0,"0",(VLOOKUP($E162,'Maestro de productos 2025'!$B$189:$C$196,2,0)-$H162))} -> 0 | J162: =($H162*$G162) -> 200.62443 | K162: =$F162*$H162 -> 504 | L162: =IF((F162*I162)=0," ",(F162*I162))
H163: =SUM(H2:H162) -> 3989 | I163: =SUM(I2:I162) -> 157 | J163: =SUM(J2:J162) -> 21290.53 | K163: =SUM(K2:K162) -> 54765 | L163: =SUM(L2:L162) -> 1709

Sheet Lista
B1: 2025 | D1: 2024
B2: Presentación | C2: Costo | D2: Presentación | E2: Costo
A3: Agua | B3: 1 | C3: 10.5 | D3: 1 | E3: 1.35 | F3: =C3-E3 -> 9.15
A4: Azúcar | B4: 1 | C4: 38 | D4: 1 | E4: 22 | F4: =C4-E4 -> 16
A5: Azúcar glass | B5: 0.5 | C5: 25.9 | D5: 0.5 | E5: =44.5/2 -> 22.25 | F5: =C5-E5 -> 3.65
A6: Azúcar mascabado | B6: 1 | C6: 51.5 | D6: 1 | E6: 39 | F6: =C6-E6 -> 12.5
A7: Bicarbonato | B7: 1 | C7: 30 | D7: 1 | E7: 25 | F7: =C7-E7 -> 5
A8: Bolsas celofán | B8: 125 | C8: 22.01 | D8: 125 | E8: 22.01 | F8: =C8-E8 -> 0
A9: Brochetas | B9: 160 | C9: 27 | D9: 160 | E9: 27 | F9: =C9-E9 -> 0
A10: Capacillos #72 | B10: 500 | C10: 85 | D10: 500 | E10: 85 | F10: =C10-E10 -> 0
A11: Capacillos #73 | B11: 400 | C11: 95 | D11: 400 | E11: 95 | F11: =C11-E11 -> 0
A12: Capacillos #74 | B12: 400 | C12: 125 | D12: 400 | E12: 125 | F12: =C12-E12 -> 0
A13: Charola pavo | B13: 1 | C13: 35 | D13: 1 | E13: 35 | F13: =C13-E13 -> 0
A14: Chispas de chocolate | B14: 0.5 | C14: 79 | D14: 0.5 | E14: 54 | F14: =C14-E14 -> 25
A15: Cobertura sumbanana | B15: 0.5 | C15: 69 | D15: 0.5 | E15: 54.58 | F15: =C15-E15 -> 14.42
A16: Cobertura Turin trad 4032 | B16: 0.5 | C16: 122 | D16: 0.5 | E16: 102.62 | F16: =C16-E16 -> 19.38
A17: Coco tostado | B17: 1 | C17: 68 | D17: 1 | E17: 68 | F17: =C17-E17 -> 0
... A19: Contenedor pay | B19: 1 | C19: 20 | D19: 1 | E19: 20 | F19: =C19-E19 -> 0
A20: Domos | B20: pza | C20: 16 | D20: pza | E20: 16 | F20: =C20-E20 -> 0
A21: Duyas | B21: pza | C21: 50 | D21: pza | E21: 50 | F21: =C21-E21 -> 0
A22: Fécula de maíz | B22: 1 | C22: 153.125 | D22: 1 | E22: 21 | F22: =C22-E22 -> 132.125
A23: Frambuesa | B23: 0.5 | C23: 151.47059 | D23: 0.5 | E23: 50 | F23: =C23-E23 -> 101.47059
A24: Galletas María | B24: 0.17 | C24: 19.5 | D24: 0.17 | E24: 14.5 | F24: =C24-E24 -> 5
A25: Harina | B25: 1 | C25: 23 | D25: 1 | E25: =46/2 -> 23 | F25: =C25-E25 -> 0
A26: Huevos | B26: 30 | C26: 91 | D26: 30 | E26: 91 | F26: =C26-E26 -> 0
A27: Leche | B27: 1 | C27: 28 | D27: 1 | E27: 27.9 | F27: =C27-E27 -> 0.1
A28: Leche condensada | B28: 0.375 | C28: 31 | D28: 0.375 | E28: 24 | F28: =C28-E28 -> 7
A29: Leche en polvo | B29: 1 | C29: 181.52174 | D29: 1 | E29: 86 | F29: =C29-E29 -> 95.521739
A30: Leche evaporada | B30: 0.36 | C30: 23.5 | D30: 0.36 | E30: 18.9 | F30: =C30-E30 -> 4.6
A31: Levadura seca | B31: 0.055 | C31: 32 | D31: 0.055 | E31: 29.61 | F31: =C31-E31 -> 2.39
A32: Ligas | B32: 125 | C32: 17.01 | D32: 125 | E32: 17.01 | F32: =C32-E32 -> 0
A33: Limón | B33: 1 | C33: 57.9 | D33: 1 | E33: 50 | F33: =C33-E33 -> 7.9
A34: Mantequilla | B34: 1 | C34: 261.11111 | D34: 1 | E34: 245 | F34: =C34-E34 -> 16.111111 | H34: =G34*C34 -> 0
A35: Media crema | B35: 0.225 | C35: 20.5 | D35: 0.225 | E35: 16.9 | F35: =C35-E35 -> 3.6
A36: Nuez | B36: 1 | C36: 274 | D36: 1 | E36: 198 | F36: =C36-E36 -> 76
A37: Papel encerado Empack | B37: 1 | C37: 23 | D37: 1 | E37: 23 | F37: =C37-E37 -> 0
A38: Papel encerado estrella 5 pliegos | B38: 1 | C38: 15.85 | D38: 1 | E38: 15.85 | F38: =C38-E38 -> 0
A39: Polvo para hornear | B39: 1 | C39: 24 | D39: 1 | E39: 24 | F39: =C39-E39 -> 0
A40: Queso doble crema | B40: 1 | C40: 120 | D40: 1 | E40: 120 | F40: =C40-E40 -> 0
A41: Ramekins | B41: 1 | C41: 3 | D41: 1 | E41: 3 | F41: =C41-E41 -> 0
A42: Sal | B42: 0.65 | C42: 14.8 | D42: 0.65 | E42: 14.8 | F42: =C42-E42 -> 0
A43: Tapas | B43: 20 | C43: 36 | D43: 20 | E43: 36 | F43: =C43-E43 -> 0
A44: Vainilla | B44: 0.25 | C44: 24.5 | D44: 0.25 | E44: 24.5 | F44: =C44-E44 -> 0
A45: Yogurt natural | B45: 1 | C45: 57.222222 | D45: 1 | E45: 52 | F45: =C45-E45 -> 5.2222222

Sheet Maestro de productos 2025
A1: RECETAS
A3: Galletas chocochips | B3: {=XLOOKUP($A3,'Maestro de productos 2024'!$A$3:$A$163,'Maestro de productos 2024'!$B$3:$B$163,0)} -> ID-3824
A4: 32 | B4: pzas de .030 kg c/u
A5: Tiempo horneado: | B5: 17 min. aprox.
A6: Temperatura: | B6: 230°/250°C
A7: Ingrediente | B7: Presentación | C7: Cantidad | D7: Costo | E7: Precio | F7: CostoTeórico | G7: TasaDesperdicio
A8: Mantequilla | B8: =VLOOKUP(A8,Lista!$A$3:$E$45,2,FALSE()) -> 1 | C8: 0.15 | D8: =VLOOKUP(A8,Lista!$A$3:$E$45,3,FALSE()) -> 261.11111 | E8: =($C$8*$D$8)/$B$8 -> 39.166667 | F8: =($C$8*$D$8)/$B$8 -> 39.166667 | G8: =(E8-F8)/E8 -> 0
A9: Azúcar | B9: =VLOOKUP(A9,Lista!$A$3:$E$45,2,FALSE()) -> 1 | C9: 0.125 | D9: =VLOOKUP(A9,Lista!$A$3:$E$45,3,FALSE()) -> 38 | E9: =($C$9*$D$9)/$B$9 -> 4.75 | F9: =($C$9*$D$9)/$B$9 -> 4.75 | G9: =(E9-F9)/E9 -> 0
A10: Azúcar mascabado | B10: =VLOOKUP(A10,Lista!$A$3:$E$45,2,FALSE()) -> 1 | C10: 0.125 | D10: =VLOOKUP(A10,Lista!$A$3:$E$45,3,FALSE()) -> 51.5 | E10: =($C$10*$D$10)/$B$10 -> 6.4375 | F10: =($C$10*$D$10)/$B$10 -> 6.4375 | G10: =(E10-F10)/E10 -> 0
A11: Huevos | B11: =VLOOKUP(A11,Lista!$A$3:$E$45,2,FALSE()) -> 30 | C11: 1 | D11: =VLOOKUP(A11,Lista!$A$3:$E$45,3,FALSE()) -> 91 | E11: =($C$11*$D$11)/$B$11 -> 3.0333333 | F11: =($C$11*$D$11)/$B$11 -> 3.0333333 | G11: =(E11-F11)/E11 -> 0
A12: Vainilla | B12: =VLOOKUP(A12,Lista!$A$3:$E$45,2,FALSE()) -> 0.25 | C12: 0.015 | D12: =VLOOKUP(A12,Lista!$A$3:$E$45,3,FALSE()) -> 24.5 | E12: =($C$12*$D$12)/$B$12 -> 1.47 | F12: =($C$12*$D$12)/$B$12 -> 1.47 | G12: =(E12-F12)/E12 -> 0
A13: Bicarbonato | B13: =VLOOKUP(A13,Lista!$A$3:$E$45,2,FALSE()) -> 1 | C13: 0.003 | D13: =VLOOKUP(A13,Lista!$A$3:$E$45,3,FALSE()) -> 30 | E13: =($C$13*$D$13)/$B$13 -> 0.09 | F13: =($C$13*$D$13)/$B$13 -> 0.09 | G13: =(E13-F13)/E13 -> 0
A14: Sal | B14: =VLOOKUP(A14,Lista!$A$3:$E$45,2,FALSE()) -> 0.65 | C14: 0.003 | D14: =VLOOKUP(A14,Lista!$A$3:$E$45,3,FALSE()) -> 14.8 | E14: =($C$14*$D$14)/$B$14 -> 0.068307692 | F14: =($C$14*$D$14)/$B$14 -> 0.068307692 | G14: =(E14-F14)/E14 -> 0
A15: Nuez | B15: =VLOOKUP(A15,Lista!$A$3:$E$45,2,FALSE()) -> 1 | C15: 0.125 | D15: =VLOOKUP(A15,Lista!$A$3:$E$45,3,FALSE()) -> 274 | E15: =($C$15*$D$15)/$B$15 -> 34.25 | F15: =($C$15*$D$15)/$B$15 -> 34.25 | G15: =(E15-F15)/E15 -> 0
A16: Chispas de chocolate | B16: =VLOOKUP(A16,Lista!$A$3:$E$45,2,FALSE()) -> 0.5 | C16: 0.16 | D16: =VLOOKUP(A16,Lista!$A$3:$E$45,3,FALSE()) -> 79 | E16: =($C$16*$D$16)/$B$16 -> 25.28 | F16: =($C$16*$D$16)/$B$16 -> 25.28 | G16: =(E16-F16)/E16 -> 0
A17: Harina | B17: =VLOOKUP(A17,Lista!$A$3:$E$45,2,FALSE()) -> 1 | C17: 0.25 | D17: =VLOOKUP(A17,Lista!$A$3:$E$45,3,FALSE()) -> 23 | E17: =($C$17*$D$17)/$B$17 -> 5.75 | F17: =($C$17*$D$17)/$B$17 -> 5.75 | G17: =(E17-F17)/E17 -> 0
D18: SUB-TOTAL | E18: =SUM(E8:E17) -> 120.29581 | F18: =SUM(F8:F17) -> 120.29581 | G18: =($E$18-$F$18)/$E$18 -> 0
D19: TOTAL +$10 | E19: =E18+10 -> 130.29581 | F19: =F18+10 -> 130.29581
D20: VALOR TOTAL CAJA | E20: =E19*100/40 -> 325.73952 | F20: =F19*100/40 -> 325.73952
D21: C/U | E21: =E19/A4 -> 4.071744 | F21: =F19/A4 -> 4.071744
D22: VALOR TOTAL C/U | E22: =E21*100/40 -> 10.17936 | F22: =$F$21*100/40 -> 10.17936 | G22: =($E$22-$F$22)/$E$22 -> 0
D23: Precio venta | E23: =ROUNDDOWN($E$22,0) -> 10 | F23: =ROUNDDOWN($E$22,0) -> 10
A26: Mini cheesecake | B26: {=XLOOKUP($A26,'Maestro de productos 2024'!$A$3:$A$163,'Maestro de productos 2024'!$B$3:$B$163,0)} -> ID-3825
A27: 16 | B27: pzas
A28: Tiempo de horneado: | B28: 31 min. aprox.
A29: Temperatura: | B29: 230°/250°C
A30: Ingrediente | B30: Presentación | C30: Cantidad | D30: Costo | E30: Precio | F30: CostoTeórico | G30: TasaDesperdicio
A31: Galletas María | B31: =VLOOKUP(A31,Lista!$A$3:$E$45,2,FALSE()) -> 0.17 | C31: 0.15 | D31: =VLOOKUP(A31,Lista!$A$3:$E$45,3,FALSE()) -> 19.5 | E31: =($C$31*$D$31)/$B$31 -> 17.205882 | F31: =($C$31*$D$31)/$B$31 -> 17.205882 | G31: 0
A32: Mantequilla | B32: =VLOOKUP(A32,Lista!$A$3:$E$45,2,FALSE()) -> 1 | C32: 0.07 | D32: =VLOOKUP(A32,Lista!$A$3:$E$45,3,FALSE()) -> 261.11111 | E32: =($C$32*$D$32)/$B$32 -> 18.277778 | F32: =($C$32*$D$32)/$B$32 -> 18.277778 | G32: 0
A33: Queso doble crema | B33: =VLOOKUP(A33,Lista!$A$3:$E$45,2,FALSE()) -> 1 | C33: 0.3 | D33: =VLOOKUP(A33,Lista!$A$3:$E$45,3,FALSE()) -> 120 | E33: =($C$33*$D$33)/$B$33 -> 36 | F33: =($C$33*$D$33)/$B$33 -> 36 | G33: 0
A34: Azúcar | B34: =VLOOKUP(A34,Lista!$A$3:$E$45,2,FALSE()) -> 1 | C34: 0.15 | D34: =VLOOKUP(A34,Lista!$A$3:$E$45,3,FALSE()) -> 38 | E34: =($C$34*$D$34)/$B$34 -> 5.7 | F34: =($C$34*$D$34)/$B$34 -> 5.7 | G34: 0
A35: Huevos | B35: =VLOOKUP(A35,Lista!$A$3:$E$45,2,FALSE()) -> 30 | C35: 2 | D35: =VLOOKUP(A35,Lista!$A$3:$E$45,3,FALSE()) -> 91 | E35: =($C$35*$D$35)/$B$35 -> 6.0666667 | F35: =($C$35*$D$35)/$B$35 -> 6.0666667 | G35: 0
A36: Media crema | B36: =VLOOKUP(A36,Lista!$A$3:$E$45,2,FALSE()) -> 0.225 | C36: =(0.15+0.08) -> 0.23 | D36: =VLOOKUP(A36,Lista!$A$3:$E$45,3,FALSE()) -> 20.5 | E36: =($C$36*$D$36)/$B$36 -> 20.955556 | F36: =(0.15*$D$36)/$B$36 -> 13.666667 | G36: =(E36-((0.15*D36)/B36))/E36 -> 0.34782609
A37: Vainilla | B37: =VLOOKUP(A37,Lista!$A$3:$E$45,2,FALSE()) -> 0.25 | C37: 0.01 | D37: =VLOOKUP(A37,Lista!$A$3:$E$45,3,FALSE()) -> 24.5 | E37: =($C$37*$D$37)/$B$37 -> 0.98 | F37: =($C$37*$D$37)/$B$37 -> 0.98 | G37: 0
A38: Fécula de maíz | B38: =VLOOKUP(A38,Lista!$A$3:$E$45,2,FALSE()) -> 1 | C38: 0.01 | D38: =VLOOKUP(A38,Lista!$A$3:$E$45,3,FALSE()) -> 153.125 | E38: =($C$38*$D$38)/$B$38 -> 1.53125 | F38: =($C$38*$D$38)/$B$38 -> 1.53125 | G38: 0
A39: Limón | B39: =VLOOKUP(A39,Lista!$A$3:$E$45,2,FALSE()) -> 1 | C39: 0.015 | D39: =VLOOKUP(A39,Lista!$A$3:$E$45,3,FALSE()) -> 57.9 | E39: =($C$39*$D$39)/$B$39 -> 0.8685 | F39: =($C$39*$D$39)/$B$39 -> 0.8685 | G39: 0
A40: Frambuesa | B40: =VLOOKUP(A40,Lista!$A$3:$E$45,2,FALSE()) -> 0.5 | C40: =(0.115+0.03) -> 0.145 | D40: =VLOOKUP(A40,Lista!$A$3:$E$45,3,FALSE()) -> 151.47059 | E40: =($C$40*$D$40)/$B$40 -> 43.926471 | F40: =(0.115*$D$40)/$B$40 -> 34.838235 | G40: 0
A41: Capacillos #72 | B41: =VLOOKUP(A41,Lista!$A$3:$E$45,2,FALSE()) -> 500 | C41: 16 | D41: =VLOOKUP(A41,Lista!$A$3:$E$45,3,FALSE()) -> 85 | E41: =($C$41*$D$41)/$B$41 -> 2.72 | F41: =($C$41*$D$41)/$B$41 -> 2.72 | G41: 0
A42: Contenedor pay | B42: =VLOOKUP(A42,Lista!$A$3:$E$45,2,FALSE()) -> 1 | C42: 1 | D42: =VLOOKUP(A42,Lista!$A$3:$E$45,3,FALSE()) -> 20 | E42: =($C$42*$D$42)/$B$42 -> 20 | F42: =($C$42*$D$42)/$B$42 -> 20 | G42: 0
D43: SUB-TOTAL | E43: =SUM(E31:E41) -> 154.2321 | F43: =SUM(F31:F41) -> 137.85498 | G43: =($E$43-$F$43)/$E$43 -> 0.10618492
D44: TOTAL +$10 | E44: =E43+10 -> 164.2321 | F44: =F43+10 -> 147.85498
D45: VALOR TOTAL CAJA | E45: =(E44*100/40)+E42 -> 430.58026 | F45: =(F44*100/40)+F42 -> 389.63745
D46: C/U | E46: =E44/A27 -> 10.264506 | F46: =F44/A27 -> 9.2409362 | J46: =E43/A27 -> 9.6395064 | K46: =F43/A27 -> 8.6159362
D47: VALOR TOTAL C/U | E47: =E46*100/40 -> 25.661266 | F47: =$F$46*100/40 -> 23.10234 | G47: =($E$47-$F$47)/$E$47 -> 0.099719384 | K47: =(J46-K46)/J46 -> 0.10618492
D48: PRECIO FINAL | E48: =ROUNDDOWN($E$47,0) -> 25 | F48: =ROUNDDOWN(F47,0) -> 23
A51: Brownie triple chocolate | B51: {=XLOOKUP($A51,'Maestro de productos 2024'!$A$3:$A$163,'Maestro de productos 2024'!$B$3:$B$163,0)} -> ID-3826
A52: 18 | B52: pzas de .050 kg c/u
A53: Tiempo de horneado: | B53: 17 min. aprox.
A54: Temperatura: | B54: 230°/250° C
A55: Ingrediente | B55: Presentación | C55: Cantidad | D55: Costo | E55: Precio | F55: CostoTeórico | G55: TasaDesperdicio
A56: Mantequilla | B56: =VLOOKUP(A56,Lista!$A$3:$E$45,2,FALSE()) -> 1 | C56: 0.2 | D56: =VLOOKUP(A56,Lista!$A$3:$E$45,3,FALSE()) -> 261.11111 | E56: =($C$56*$D$56)/$B$56 -> 52.222222 | F56: =($C$56*$D$56)/$B$56 -> 52.222222 | G56: =(E56-F56)/E56 -> 0
A57: Azúcar | B57: =VLOOKUP(A57,Lista!$A$3:$E$45,2,FALSE()) -> 1 | C57: 0.2 | D57: =VLOOKUP(A57,Lista!$A$3:$E$45,3,FALSE()) -> 38 | E57: =($C$57*$D$57)/$B$57 -> 7.6 | F57: =($C$57*$D$57)/$B$57 -> 7.6 | G57: =(E57-F57)/E57 -> 0
A58: Harina | B58: =VLOOKUP(A58,Lista!$A$3:$E$45,2,FALSE()) -> 1 | C58: 0.113 | D58: =VLOOKUP(A58,Lista!$A$3:$E$45,3,FALSE()) -> 23 | E58: =($C$58*$D$58)/$B$58 -> 2.599 | F58: =($C$58*$D$58)/$B$58 -> 2.599 | G58: =(E58-F58)/E58 -> 0
A59: Cocoa | B59: =VLOOKUP(A59,Lista!$A$3:$E$45,2,FALSE()) -> 0.25 | C59: 0.038 | D59: =VLOOKUP(A59,Lista!$A$3:$E$45,3,FALSE()) -> 90 | E59: =($C$59*$D$59)/$B$59 -> 13.68 | F59: =($C$59*$D$59)/$B$59 -> 13.68 | G59: =(E59-F59)/E59 -> 0
A60: Vainilla | B60: =VLOOKUP(A60,Lista!$A$3:$E$45,2,FALSE()) -> 0.25 | C60: 0.008 | D60: =VLOOKUP(A60,Lista!$A$3:$E$45,3,FALSE()) -> 24.5 | E60: =($C$60*$D$60)/$B$60 -> 0.784 | F60: =($C$60*$D$60)/$B$60 -> 0.784 | G60: =(E60-F60)/E60 -> 0
A61: Huevos | B61: =VLOOKUP(A61,Lista!$A$3:$E$45,2,FALSE()) -> 30 | C61: 3 | D61: =VLOOKUP(A61,Lista!$A$3:$E$45,3,FALSE()) -> 91 | E61: =($C$61*$D$61)/$B$61 -> 9.1 | F61: =($C$61*$D$61)/$B$61 -> 9.1 | G61: =(E61-F61)/E61 -> 0
A62: Chispas de chocolate | B62: =VLOOKUP(A62,Lista!$A$3:$E$45,2,FALSE()) -> 0.5 | C62: 0.075 | D62: =VLOOKUP(A62,Lista!$A$3:$E$45,3,FALSE()) -> 79 | E62: =($C$62*$D$62)/$B$62 -> 11.85 | F62: =($C$62*$D$62)/$B$62 -> 11.85 | G62: =(E62-F62)/E62 -> 0
A63: Cobertura Turin trad 4032 | B63: =VLOOKUP(A63,Lista!$A$3:$E$45,2,FALSE()) -> 0.5 | C63: 0.075 | D63: =VLOOKUP(A63,Lista!$A$3:$E$45,3,FALSE()) -> 122 | E63: =($C$63*$D$63)/$B$63 -> 18.3 | F63: =($C$63*$D$63)/$B$63 -> 18.3 | G63: =(E63-F63)/E63 -> 0
A64: Nuez | B64: =VLOOKUP(A64,Lista!$A$3:$E$45,2,FALSE()) -> 1 | C64: 0.056 | D64: =VLOOKUP(A64,Lista!$A$3:$E$45,3,FALSE()) -> 274 | E64: =($C$64*$D$64)/$B$64 -> 15.344 | F64: =($C$64*$D$64)/$B$64 -> 15.344 | G64: =(E64-F64)/E64 -> 0
A65: Azúcar glass | B65: =VLOOKUP(A65,Lista!$A$3:$E$45,2,FALSE()) -> 0.5 | C65: 0.015 | D65: =VLOOKUP(A65,Lista!$A$3:$E$45,3,FALSE()) -> 25.9 | E65: =($C$65*$D$65)/$B$65 -> 0.777 | F65: =($C$65*$D$65)/$B$65 -> 0.777 | G65: =(E65-F65)/E65 -> 0
A66: Capacillos #72 | B66: =VLOOKUP(A66,Lista!$A$3:$E$45,2,FALSE()) -> 500 | C66: 18 | D66: =VLOOKUP(A66,Lista!$A$3:$E$45,3,FALSE()) -> 85 | E66: =($C$66*$D$66)/$B$66 -> 3.06 | F66: =($C$66*$D$66)/$B$66 -> 3.06 | G66: =(E66-F66)/E66 -> 0
D67: SUB-TOTAL | E67: =SUM(E56:E66) -> 135.31622 | F67: =SUM(F56:F66) -> 135.31622 | G67: =($E$67-$F$67)/$E$67 -> 0
D68: TOTAL +$10 | E68: =E67+10 -> 145.31622 | F68: =F67+10 -> 145.31622
D69: VALOR TOTAL CAJA | E69: =E68*100/40 -> 363.29056 | F69: =F68*100/40 -> 363.29056
D70: C/U | E70: =E68/A52 -> 8.0731235 | F70: =F68/A52 -> 8.0731235
D71: VALOR TOTAL C/U | E71: =E70*100/40 -> 20.182809 | F71: =$F$70*100/40 -> 20.182809 | G71: =($E$71-$F$71)/$E$71 -> 0
D72: PRECIO FINAL | E72: =ROUNDDOWN($E$71,0) -> 20 | F72: =ROUNDDOWN(F71,0) -> 20
A75: Galletas danesas | B75: {=XLOOKUP($A75,'Maestro de productos 2024'!$A$3:$A$163,'Maestro de productos 2024'!$B$3:$B$163,0)} -> ID-3827
A76: 35 | B76: pzas
A77: Tiempo de horneado: | B77: 17 min. aprox.
A78: Temperatura: | B78: 260°C
A79: Ingrediente | B79: Presentación | C79: Cantidad | D79: Costo | E79: Precio | F79: CostoTeórico | G79: TasaDesperdicio
A80: Harina | B80: =VLOOKUP(A80,Lista!$A$3:$E$45,2,FALSE()) -> 1 | C80: 0.27 | D80: =VLOOKUP(A80,Lista!$A$3:$E$45,3,FALSE()) -> 23 | E80: =($C$80*$D$80)/$B$80 -> 6.21 | F80: =($C$80*$D$80)/$B$80 -> 6.21 | G80: =(E80-F80)/E80 -> 0
A81: Fécula de maíz | B81: =VLOOKUP(A81,Lista!$A$3:$E$45,2,FALSE()) -> 1 | C81: 0.07 | D81: =VLOOKUP(A81,Lista!$A$3:$E$45,3,FALSE()) -> 153.125 | E81: =($C$81*$D$81)/$B$81 -> 10.71875 | F81: =($C$81*$D$81)/$B$81 -> 10.71875 | G81: =(E81-F81)/E81 -> 0
A82: Azúcar glass | B82: =VLOOKUP(A82,Lista!$A$3:$E$45,2,FALSE()) -> 0.5 | C82: 0.13 | D82: =VLOOKUP(A82,Lista!$A$3:$E$45,3,FALSE()) -> 25.9 | E82: =($C$82*$D$82)/$B$82 -> 6.734 | F82: =($C$82*$D$82)/$B$82 -> 6.734 | G82: =(E82-F82)/E82 -> 0
A83: Leche en polvo | B83: =VLOOKUP(A83,Lista!$A$3:$E$45,2,FALSE()) -> 1 | C83: 0.03 | D83: =VLOOKUP(A83,Lista!$A$3:$E$45,3,FALSE()) -> 181.52174 | E83: =($C$83*$D$83)/$B$83 -> 5.4456522 | F83: =($C$83*$D$83)/$B$83 -> 5.4456522 | G83: =(E83-F83)/E83 -> 0
A84: Sal | B84: =VLOOKUP(A84,Lista!$A$3:$E$45,2,FALSE()) -> 0.65 | C84: 0.001 | D84: =VLOOKUP(A84,Lista!$A$3:$E$45,3,FALSE()) -> 14.8 | E84: =($C$84*$D$84)/$B$84 -> 0.022769231 | F84: =($C$84*$D$84)/$B$84 -> 0.022769231 | G84: =(E84-F84)/E84 -> 0
A85: Mantequilla | B85: =VLOOKUP(A85,Lista!$A$3:$E$45,2,FALSE()) -> 1 | C85: 0.25 | D85: =VLOOKUP(A85,Lista!$A$3:$E$45,3,FALSE()) -> 261.11111 | E85: =($C$85*$D$85)/$B$85 -> 65.277778 | F85: =($C$85*$D$85)/$B$85 -> 65.277778 | G85: =(E85-F85)/E85 -> 0
A86: Huevos | B86: =VLOOKUP(A86,Lista!$A$3:$E$45,2,FALSE()) -> 30 | C86: 1 | D86: =VLOOKUP(A86,Lista!$A$3:$E$45,3,FALSE()) -> 91 | E86: =($C$86*$D$86)/$B$86 -> 3.0333333 | F86: =($C$86*$D$86)/$B$86 -> 3.0333333 | G86: =(E86-F86)/E86 -> 0
A87: Vainilla | B87: =VLOOKUP(A87,Lista!$A$3:$E$45,2,FALSE()) -> 0.25 | C87: 0.015 | D87: =VLOOKUP(A87,Lista!$A$3:$E$45,3,FALSE()) -> 24.5 | E87: =($C$87*$D$87)/$B$87 -> 1.47 | F87: =($C$87*$D$87)/$B$87 -> 1.47 | G87: =(E87-F87)/E87 -> 0
D88: SUB-TOTAL | E88: =SUM(E80:E87) -> 98.912283 | F88: =SUM(F80:F87) -> 98.912283 | G88: =($E$88-$F$88)/$E$88 -> 0
D89: TOTAL +$10 | E89: =E88+10 -> 108.91228 | F89: =F88+10 -> 108.91228
D90: VALOR TOTAL CAJA | E90: =E89*100/40 -> 272.28071 | F90: =F89*100/40 -> 272.28071
D91: C/U | E91: =E89/A76 -> 3.1117795 | F91: =F89/A76 -> 3.1117795
D92: VALOR TOTAL C/U | E92: =E91*100/40 -> 7.7794488 | F92: =$F$91*100/40 -> 7.7794488 | G92: =($E$92-$F$92)/$E$92 -> 0
D93: PRECIO FINAL | E93: =ROUNDDOWN($E$92,0) -> 7 | F93: =ROUNDDOWN(F92,0) -> 7
A96: Muffins de yogurt | B96: {=XLOOKUP($A96,'Maestro de productos 2024'!$A$3:$A$163,'Maestro de productos 2024'!$B$3:$B$163,0)} -> ID-3828
A97: 12 | B97: pzas
A98: Tiempo de horneado: | B98: 28 min. aprox.
A99: Temperatura: | B99: 260°C
A100: Ingrediente | B100: Presentación | C100: Cantidad | D100: Costo | E100: Precio | F100: CostoTeórico | G100: TasaDesperdicio
A101: Harina | B101: =VLOOKUP(A101,Lista!$A$3:$E$45,2,FALSE()) -> 1 | C101: 0.24 | D101: =VLOOKUP(A101,Lista!$A$3:$E$45,3,FALSE()) -> 23 | E101: =($C$101*$D$101)/$B$101 -> 5.52 | F101: =($C$101*$D$101)/$B$101 -> 5.52 | G101: =(E101-F101)/E101 -> 0
A102: Polvo para hornear | B102: =VLOOKUP(A102,Lista!$A$3:$E$45,2,FALSE()) -> 1 | C102: 0.015 | D102: =VLOOKUP(A102,Lista!$A$3:$E$45,3,FALSE()) -> 24 | E102: =($C$102*$D$102)/$B$102 -> 0.36 | F102: =($C$102*$D$102)/$B$102 -> 0.36 | G102: =(E102-F102)/E102 -> 0
A103: Huevos | B103: =VLOOKUP(A103,Lista!$A$3:$E$45,2,FALSE()) -> 30 | C103: 3 | D103: =VLOOKUP(A103,Lista!$A$3:$E$45,3,FALSE()) -> 91 | E103: =($C$103*$D$103)/$B$103 -> 9.1 | F103: =($C$103*$D$103)/$B$103 -> 9.1 | G103: =(E103-F103)/E103 -> 0
A104: Azúcar | B104: =VLOOKUP(A104,Lista!$A$3:$E$45,2,FALSE()) -> 1 | C104: 0.15 | D104: =VLOOKUP(A104,Lista!$A$3:$E$45,3,FALSE()) -> 38 | E104: =($C$104*$D$104)/$B$104 -> 5.7 | F104: =($C$104*$D$104)/$B$104 -> 5.7 | G104: =(E104-F104)/E104 -> 0
A105: Sal | B105: =VLOOKUP(A105,Lista!$A$3:$E$45,2,FALSE()) -> 0.65 | C105: 0.001 | D105: =VLOOKUP(A105,Lista!$A$3:$E$45,3,FALSE()) -> 14.8 | E105: =($C$105*$D$105)/$B$105 -> 0.022769231 | F105: =($C$105*$D$105)/$B$105 -> 0.022769231 | G105: =(E105-F105)/E105 -> 0
A106: Vainilla | B106: =VLOOKUP(A106,Lista!$A$3:$E$45,2,FALSE()) -> 0.25 | C106: 0.005 | D106: =VLOOKUP(A106,Lista!$A$3:$E$45,3,FALSE()) -> 24.5 | E106: =($C$106*$D$106)/$B$106 -> 0.49 | F106: =($C$106*$D$106)/$B$106 -> 0.49 | G106: =(E106-F106)/E106 -> 0
A107: Yogurt natural | B107: =VLOOKUP(A107,Lista!$A$3:$E$45,2,FALSE()) -> 1 | C107: =(0.13+0.005) -> 0.135 | D107: =VLOOKUP(A107,Lista!$A$3:$E$45,3,FALSE()) -> 57.222222 | E107: =($C$107*$D$107)/$B$107 -> 7.725 | F107: =(0.13*$D$107)/$B$107 -> 7.4388889 | G107: =(E107-F107)/E107 -> 0.037037037
A108: Mantequilla | B108: =VLOOKUP(A108,Lista!$A$3:$E$45,2,FALSE()) -> 1 | C108: 0.13 | D108: =VLOOKUP(A108,Lista!$A$3:$E$45,3,FALSE()) -> 261.11111 | E108: =($C$108*$D$108)/$B$108 -> 33.944444 | F108: =($C$108*$D$108)/$B$108 -> 33.944444 | G108: =(E108-F108)/E108 -> 0
A109: Chispas de chocolate | B109: =VLOOKUP(A109,Lista!$A$3:$E$45,2,FALSE()) -> 0.5 | C109: 0.15 | D109: =VLOOKUP(A109,Lista!$A$3:$E$45,3,FALSE()) -> 79 | E109: =($C$109*$D$109)/$B$109 -> 23.7 | F109: =($C$109*$D$109)/$B$109 -> 23.7 | G109: =(E109-F109)/E109 -> 0
...

Sheet Maestro de productos 2024
A1: RECETAS
A3: Galletas chocochips | B3: ID-3824
A4: 32 | B4: pzas de .030 kg c/u
A5: Tiempo horneado: | B5: 17 min. aprox.
A6: Temperatura: | B6: 230°/250°C
A7: Ingrediente | B7: Presentación | C7: Cantidad | D7: Costo | E7: Total | F7: CostoTeórico | G7: TasaDesperdicio
A8: Mantequilla | B8: =VLOOKUP(A8,Lista!$A$3:$E$45,4,FALSE()) -> 1 | C8: 0.15 | D8: =VLOOKUP($A8,Lista!$A$3:$E$45,5,FALSE()) -> 245 | E8: =($C$8*$D$8)/$B$8 -> 36.75 | F8: =($C$8*$D$8)/$B$8 -> 36.75 | G8: =(E8-F8)/E8 -> 0
A9: Azúcar | B9: =VLOOKUP(A9,Lista!$A$3:$E$45,4,FALSE()) -> 1 | C9: 0.125 | D9: =VLOOKUP($A9,Lista!$A$3:$E$45,5,FALSE()) -> 22 | E9: =($C$9*$D$9)/$B$9 -> 2.75 | F9: =($C$9*$D$9)/$B$9 -> 2.75 | G9: =(E9-F9)/E9 -> 0
A10: Azúcar mascabado | B10: =VLOOKUP(A10,Lista!$A$3:$E$45,4,FALSE()) -> 1 | C10: 0.125 | D10: =VLOOKUP($A10,Lista!$A$3:$E$45,5,FALSE()) -> 39 | E10: =($C$10*$D$10)/$B$10 -> 4.875 | F10: =($C$10*$D$10)/$B$10 -> 4.875 | G10: =(E10-F10)/E10 -> 0
A11: Huevos | B11: =VLOOKUP(A11,Lista!$A$3:$E$45,4,FALSE()) -> 30 | C11: 1 | D11: =VLOOKUP($A11,Lista!$A$3:$E$45,5,FALSE()) -> 91 | E11: =($C$11*$D$11)/$B$11 -> 3.0333333 | F11: =($C$11*$D$11)/$B$11 -> 3.0333333 | G11: =(E11-F11)/E11 -> 0
A12: Vainilla | B12: =VLOOKUP(A12,Lista!$A$3:$E$45,4,FALSE()) -> 0.25 | C12: 0.015 | D12: =VLOOKUP($A12,Lista!$A$3:$E$45,5,FALSE()) -> 24.5 | E12: =($C$12*$D$12)/$B$12 -> 1.47 | F12: =($C$12*$D$12)/$B$12 -> 1.47 | G12: =(E12-F12)/E12 -> 0
A13: Bicarbonato | B13: =VLOOKUP(A13,Lista!$A$3:$E$45,4,FALSE()) -> 1 | C13: 0.003 | D13: =VLOOKUP($A13,Lista!$A$3:$E$45,5,FALSE()) -> 25 | E13: =($C$13*$D$13)/$B$13 -> 0.075 | F13: =($C$13*$D$13)/$B$13 -> 0.075 | G13: =(E13-F13)/E13 -> 0
A14: Sal | B14: =VLOOKUP(A14,Lista!$A$3:$E$45,4,FALSE()) -> 0.65 | C14: 0.003 | D14: =VLOOKUP($A14,Lista!$A$3:$E$45,5,FALSE()) -> 14.8 | E14: =($C$14*$D$14)/$B$14 -> 0.068307692 | F14: =($C$14*$D$14)/$B$14 -> 0.068307692 | G14: =(E14-F14)/E14 -> 0
A15: Nuez | B15: =VLOOKUP(A15,Lista!$A$3:$E$45,4,FALSE()) -> 1 | C15: 0.125 | D15: =VLOOKUP($A15,Lista!$A$3:$E$45,5,FALSE()) -> 198 | E15: =($C$15*$D$15)/$B$15 -> 24.75 | F15: =($C$15*$D$15)/$B$15 -> 24.75 | G15: =(E15-F15)/E15 -> 0
A16: Chispas de chocolate | B16: =VLOOKUP(A16,Lista!$A$3:$E$45,4,FALSE()) -> 0.5 | C16: 0.16 | D16: =VLOOKUP($A16,Lista!$A$3:$E$45,5,FALSE()) -> 54 | E16: =($C$16*$D$16)/$B$16 -> 17.28 | F16: =($C$16*$D$16)/$B$16 -> 17.28 | G16: =(E16-F16)/E16 -> 0
A17: Harina | B17: =VLOOKUP(A17,Lista!$A$3:$E$45,4,FALSE()) -> 1 | C17: 0.25 | D17: =VLOOKUP($A17,Lista!$A$3:$E$45,5,FALSE()) -> 23 | E17: =($C$17*$D$17)/$B$17 -> 5.75 | F17: =($C$17*$D$17)/$B$17 -> 5.75 | G17: =(E17-F17)/E17 -> 0
D18: SUB-TOTAL | E18: =SUM(E8:E17) -> 96.801641 | F18: =SUM(F8:F17) -> 96.801641 | G18: =($E$18-$F$18)/$E$18 -> 0
D19: TOTAL +$10 | E19: =E18+10 -> 106.80164 | F19: =F18+10 -> 106.80164
D20: VALOR TOTAL CAJA | E20: =E19*100/40 -> 267.0041 | F20: =F19*100/40 -> 267.0041
D21: C/U | E21: =$E$19/$A$4 -> 3.3375513 | F21: =$E$19/$A$4 -> 3.3375513
D22: VALOR TOTAL C/U | E22: =E21*100/40 -> 8.3438782 | F22: =$F$21*100/40 -> 8.3438782 | G22: =($E$22-$F$22)/$E$22 -> 0
D23: PRECIO FINAL | E23: 10 | F23: 10
A26: Mini cheesecake | B26: ID-3825
A27: 16 | B27: pzas
A28: Tiempo de horneado: | B28: 31 min. aprox.
A29: Temperatura: | B29: 230°/250°C
A30: Ingrediente | B30: Presentación | C30: Cantidad a usar | D30: Costo | E30: Total | F30: CostoTeórico | G30: TasaDesperdicio
A31: Galletas María | B31: =VLOOKUP(A31,Lista!$A$3:$E$45,4,FALSE()) -> 0.17 | C31: 0.15 | D31: =VLOOKUP($A31,Lista!$A$3:$E$45,5,FALSE()) -> 14.5 | E31: =($C$31*$D$31)/$B$31 -> 12.794118 | F31: =($C$31*$D$31)/$B$31 -> 12.794118 | G31: =(E31-F31)/E31 -> 0
A32: Mantequilla | B32: =VLOOKUP(A32,Lista!$A$3:$E$45,4,FALSE()) -> 1 | C32: 0.07 | D32: =VLOOKUP($A32,Lista!$A$3:$E$45,5,FALSE()) -> 245 | E32: =($C$32*$D$32)/$B$32 -> 17.15 | F32: =($C$32*$D$32)/$B$32 -> 17.15 | G32: =(E32-F32)/E32 -> 0
A33: Queso doble crema | B33: =VLOOKUP(A33,Lista!$A$3:$E$45,4,FALSE()) -> 1 | C33: 0.3 | D33: =VLOOKUP($A33,Lista!$A$3:$E$45,5,FALSE()) -> 120 | E33: =($C$33*$D$33)/$B$33 -> 36 | F33: =($C$33*$D$33)/$B$33 -> 36 | G33: =(E33-F33)/E33 -> 0
A34: Azúcar | B34: =VLOOKUP(A34,Lista!$A$3:$E$45,4,FALSE()) -> 1 | C34: 0.15 | D34: =VLOOKUP($A34,Lista!$A$3:$E$45,5,FALSE()) -> 22 | E34: =($C$34*$D$34)/$B$34 -> 3.3 | F34: =($C$34*$D$34)/$B$34 -> 3.3 | G34: =(E34-F34)/E34 -> 0
A35: Huevos | B35: =VLOOKUP(A35,Lista!$A$3:$E$45,4,FALSE()) -> 30 | C35: 2 | D35: =VLOOKUP($A35,Lista!$A$3:$E$45,5,FALSE()) -> 91 | E35: =($C$35*$D$35)/$B$35 -> 6.0666667 | F35: =($C$35*$D$35)/$B$35 -> 6.0666667 | G35: =(E35-F35)/E35 -> 0
A36: Media crema | B36: =VLOOKUP(A36,Lista!$A$3:$E$45,4,FALSE()) -> 0.225 | C36: =0.15+0.08 -> 0.23 | D36: =VLOOKUP($A36,Lista!$A$3:$E$45,5,FALSE()) -> 16.9 | E36: =($C$36*$D$36)/$B$36 -> 17.275556 | F36: =(0.15*$D$36)/$B$36 -> 11.266667 | G36: =(E36-F36)/E36 -> 0.34782609
A37: Vainilla | B37: =VLOOKUP(A37,Lista!$A$3:$E$45,4,FALSE()) -> 0.25 | C37: 0.01 | D37: =VLOOKUP($A37,Lista!$A$3:$E$45,5,FALSE()) -> 24.5 | E37: =($C$37*$D$37)/$B$37 -> 0.98 | F37: =($C$37*$D$37)/$B$37 -> 0.98 | G37: =(E37-F37)/E37 -> 0
A38: Fécula de maíz | B38: =VLOOKUP(A38,Lista!$A$3:$E$45,4,FALSE()) -> 1 | C38: 0.01 | D38: =VLOOKUP($A38,Lista!$A$3:$E$45,5,FALSE()) -> 21 | E38: =($C$38*$D$38)/$B$38 -> 0.21 | F38: =($C$38*$D$38)/$B$38 -> 0.21 | G38: =(E38-F38)/E38 -> 0
A39: Limón | B39: =VLOOKUP(A39,Lista!$A$3:$E$45,4,FALSE()) -> 1 | C39: 0.015 | D39: =VLOOKUP($A39,Lista!$A$3:$E$45,5,FALSE()) -> 50 | E39: =($C$39*$D$39)/$B$39 -> 0.75 | F39: =($C$39*$D$39)/$B$39 -> 0.75 | G39: =(E39-F39)/E39 -> 0
A40: Frambuesa | B40: =VLOOKUP(A40,Lista!$A$3:$E$45,4,FALSE()) -> 0.5 | C40: =(0.115+0.03) -> 0.145 | D40: =VLOOKUP($A40,Lista!$A$3:$E$45,5,FALSE()) -> 50 | E40: =($C$40*$D$40)/$B$40 -> 14.5 | F40: =(0.115*$D$40)/$B$40 -> 11.5 | G40: =(E40-F40)/E40 -> 0.20689655
A41: Capacillos #72 | B41: =VLOOKUP(A41,Lista!$A$3:$E$45,4,FALSE()) -> 500 | C41: 16 | D41: =VLOOKUP($A41,Lista!$A$3:$E$45,5,FALSE()) -> 85 | E41: =($C$41*$D$41)/$B$41 -> 2.72 | F41: =($C$41*$D$41)/$B$41 -> 2.72 | G41: =(E41-F41)/E41 -> 0
A42: Contenedor pay | B42: =VLOOKUP(A42,Lista!$A$3:$E$45,4,FALSE()) -> 1 | C42: 1 | D42: =VLOOKUP($A42,Lista!$A$3:$E$45,5,FALSE()) -> 20 | E42: =($C$42*$D$42)/$B$42 -> 20 | F42: =($C$42*$D$42)/$B$42 -> 20 | G42: =(E42-F42)/E42 -> 0
D43: SUB-TOTAL | E43: =SUM(E31:E41) -> 111.74634 | F43: =SUM(F31:F41) -> 102.73745 | G43: =($E$43-$F$43)/$E$43 -> 0.080619096
C44: =0.225-0.15 -> 0.075 | D44: TOTAL +$10 | E44: =E43+10 -> 121.74634 | F44: =F43+10 -> 112.73745
D45: VALOR TOTAL CAJA | E45: =(E44*100/40)+E42 -> 324.36585 | F45: =(F44*100/40)+F42 -> 301.84363
D46: C/U | E46: =E44/A27 -> 7.6091462 | F46: =F44/A27 -> 7.0460907
D47: VALOR TOTAL C/U | E47: =E46*100/40 -> 19.022866 | F47: =$F$46*100/40 -> 17.615227
D48: PRECIO FINAL | E48: 20 | F48: 20
F50: =E46-F46 -> 0.56305556
A51: Brownie triple chocolate | B51: ID-3826
A52: 18 | B52: pzas de .050 kg c/u
A53: Tiempo de horneado: | B53: 17 min. aprox.
A54: Temperatura: | B54: 230°/250° C
A55: Ingrediente | B55: Presentación | C55: Cantidad | D55: Costo | E55: Total | F55: CostoTeórico | G55: TasaDesperdicio
A56: Mantequilla | B56: =VLOOKUP(A56,Lista!$A$3:$E$45,4,FALSE()) -> 1 | C56: 0.2 | D56: =VLOOKUP(A56,Lista!$A$3:$E$45,5,FALSE()) -> 245 | E56: =($C$56*$D$56)/$B$56 -> 49 | F56: =($C$56*$D$56)/$B$56 -> 49 | G56: =(E56-F56)/E56 -> 0
A57: Azúcar | B57: =VLOOKUP(A57,Lista!$A$3:$E$45,4,FALSE()) -> 1 | C57: 0.2 | D57: =VLOOKUP(A57,Lista!$A$3:$E$45,5,FALSE()) -> 22 | E57: =($C$57*$D$57)/$B$57 -> 4.4 | F57: =($C$57*$D$57)/$B$57 -> 4.4 | G57: =(E57-F57)/E57 -> 0
A58: Harina | B58: =VLOOKUP(A58,Lista!$A$3:$E$45,4,FALSE()) -> 1 | C58: 0.113 | D58: =VLOOKUP(A58,Lista!$A$3:$E$45,5,FALSE()) -> 23 | E58: =($C$58*$D$58)/$B$58 -> 2.599 | F58: =($C$58*$D$58)/$B$58 -> 2.599 | G58: =(E58-F58)/E58 -> 0
A59: Cocoa | B59: =VLOOKUP(A59,Lista!$A$3:$E$45,4,FALSE()) -> 0.25 | C59: 0.038 | D59: =VLOOKUP(A59,Lista!$A$3:$E$45,5,FALSE()) -> 90 | E59: =($C$59*$D$59)/$B$59 -> 13.68 | F59: =($C$59*$D$59)/$B$59 -> 13.68 | G59: =(E59-F59)/E59 -> 0
A60: Vainilla | B60: =VLOOKUP(A60,Lista!$A$3:$E$45,4,FALSE()) -> 0.25 | C60: 0.008 | D60: =VLOOKUP(A60,Lista!$A$3:$E$45,5,FALSE()) -> 24.5 | E60: =($C$60*$D$60)/$B$60 -> 0.784 | F60: =($C$60*$D$60)/$B$60 -> 0.784 | G60: =(E60-F60)/E60 -> 0
A61: Huevos | B61: =VLOOKUP(A61,Lista!$A$3:$E$45,4,FALSE()) -> 30 | C61: 3 | D61: =VLOOKUP(A61,Lista!$A$3:$E$45,5,FALSE()) -> 91 | E61: =($C$61*$D$61)/$B$61 -> 9.1 | F61: =($C$61*$D$61)/$B$61 -> 9.1 | G61: =(E61-F61)/E61 -> 0
A62: Chispas de chocolate | B62: =VLOOKUP(A62,Lista!$A$3:$E$45,4,FALSE()) -> 0.5 | C62: 0.075 | D62: =VLOOKUP(A62,Lista!$A$3:$E$45,5,FALSE()) -> 54 | E62: =($C$62*$D$62)/$B$62 -> 8.1 | F62: =($C$62*$D$62)/$B$62 -> 8.1 | G62: =(E62-F62)/E62 -> 0
A63: Cobertura Turin trad 4032 | B63: =VLOOKUP(A63,Lista!$A$3:$E$45,4,FALSE()) -> 0.5 | C63: 0.075 | D63: =VLOOKUP(A63,Lista!$A$3:$E$45,5,FALSE()) -> 102.62 | E63: =($C$63*$D$63)/$B$63 -> 15.393 | F63: =($C$63*$D$63)/$B$63 -> 15.393 | G63: =(E63-F63)/E63 -> 0
A64: Nuez | B64: =VLOOKUP(A64,Lista!$A$3:$E$45,4,FALSE()) -> 1 | C64: 0.056 | D64: =VLOOKUP(A64,Lista!$A$3:$E$45,5,FALSE()) -> 198 | E64: =($C$64*$D$64)/$B$64 -> 11.088 | F64: =($C$64*$D$64)/$B$64 -> 11.088 | G64: =(E64-F64)/E64 -> 0
A65: Azúcar glass | B65: =VLOOKUP(A65,Lista!$A$3:$E$45,4,FALSE()) -> 0.5 | C65: 0.015 | D65: =VLOOKUP(A65,Lista!$A$3:$E$45,5,FALSE()) -> 22.25 | E65: =($C$65*$D$65)/$B$65 -> 0.6675 | F65: =($C$65*$D$65)/$B$65 -> 0.6675 | G65: =(E65-F65)/E65 -> 0
A66: Capacillos #72 | B66: =VLOOKUP(A66,Lista!$A$3:$E$45,4,FALSE()) -> 500 | C66: 18 | D66: =VLOOKUP(A66,Lista!$A$3:$E$45,5,FALSE()) -> 85 | E66: =($C$66*$D$66)/$B$66 -> 3.06 | F66: =($C$66*$D$66)/$B$66 -> 3.06 | G66: =(E66-F66)/E66 -> 0
D67: SUB-TOTAL | E67: =SUM(E56:E66) -> 117.8715 | F67: =SUM(F56:F66) -> 117.8715 | G67: =($E$67-$F$67)/$E$67 -> 0
D68: TOTAL +$10 | E68: =E67+10 -> 127.8715 | F68: =F67+10 -> 127.8715
D69: VALOR TOTAL CAJA | E69: =E68*100/40 -> 319.67875 | F69: =F68*100/40 -> 319.67875
D70: C/U | E70: =E68/A52 -> 7.1039722 | F70: =F68/A52 -> 7.1039722
D71: VALOR TOTAL C/U | E71: =E70*100/40 -> 17.759931 | F71: =$F$70*100/40 -> 17.759931 | G71: =($E$71-$F$71)/$E$71 -> 0
D72: PRECIO FINAL | E72: 20 | F72: 20
A75: Galletas danesas | B75: ID-3827
A76: 35 | B76: pzas
A77: Tiempo de horneado: | B77: 17 min. aprox.
A78: Temperatura: | B78: 260°C
A79: Ingrediente | B79: Presentación | C79: Cantidad | D79: Costo | E79: Total | F79: CostoTeórico | G79: TasaDesperdicio
A80: Harina | B80: =VLOOKUP(A80,Lista!$A$3:$E$45,4,FALSE()) -> 1 | C80: 0.27 | D80: =VLOOKUP(A80,Lista!$A$3:$E$45,5,FALSE()) -> 23 | E80: =($C$80*$D$80)/$B$80 -> 6.21 | F80: =($C$80*$D$80)/$B$80 -> 6.21 | G80: 0
A81: Fécula de maíz | B81: =VLOOKUP(A81,Lista!$A$3:$E$45,4,FALSE()) -> 1 | C81: 0.07 | D81: =VLOOKUP(A81,Lista!$A$3:$E$45,5,FALSE()) -> 21 | E81: =($C$81*$D$81)/$B$81 -> 1.47 | F81: =($C$81*$D$81)/$B$81 -> 1.47 | G81: 0
A82: Azúcar glass | B82: =VLOOKUP(A82,Lista!$A$3:$E$45,4,FALSE()) -> 0.5 | C82: 0.13 | D82: =VLOOKUP(A82,Lista!$A$3:$E$45,5,FALSE()) -> 22.25 | E82: =($C$82*$D$82)/$B$82 -> 5.785 | F82: =($C$82*$D$82)/$B$82 -> 5.785 | G82: 0
A83: Leche en polvo | B83: =VLOOKUP(A83,Lista!$A$3:$E$45,4,FALSE()) -> 1 | C83: 0.03 | D83: =VLOOKUP(A83,Lista!$A$3:$E$45,5,FALSE()) -> 86 | E83: =($C$83*$D$83)/$B$83 -> 2.58 | F83: =($C$83*$D$83)/$B$83 -> 2.58 | G83: 0
A84: Sal | B84: =VLOOKUP(A84,Lista!$A$3:$E$45,4,FALSE()) -> 0.65 | C84: 0.001 | D84: =VLOOKUP(A84,Lista!$A$3:$E$45,5,FALSE()) -> 14.8 | E84: =($C$84*$D$84)/$B$84 -> 0.022769231 | F84: =($C$84*$D$84)/$B$84 -> 0.022769231 | G84: 0
A85: Mantequilla | B85: =VLOOKUP(A85,Lista!$A$3:$E$45,4,FALSE()) -> 1 | C85: 0.25 | D85: =VLOOKUP(A85,Lista!$A$3:$E$45,5,FALSE()) -> 245 | E85: =($C$85*$D$85)/$B$85 -> 61.25 | F85: =($C$85*$D$85)/$B$85 -> 61.25 | G85: 0
A86: Huevos | B86: =VLOOKUP(A86,Lista!$A$3:$E$45,4,FALSE()) -> 30 | C86: 1 | D86: =VLOOKUP(A86,Lista!$A$3:$E$45,5,FALSE()) -> 91 | E86: =($C$86*$D$86)/$B$86 -> 3.0333333 | F86: =($C$86*$D$86)/$B$86 -> 3.0333333 | G86: 0
A87: Vainilla | B87: =VLOOKUP(A87,Lista!$A$3:$E$45,4,FALSE()) -> 0.25 | C87: 0.015 | D87: =VLOOKUP(A87,Lista!$A$3:$E$45,5,FALSE()) -> 24.5 | E87: =($C$87*$D$87)/$B$87 -> 1.47 | F87: =($C$87*$D$87)/$B$87 -> 1.47 | G87: 0
D88: SUB-TOTAL | E88: =SUM(E80:E87) -> 81.821103 | F88: =SUM(F80:F87) -> 81.821103 | G88: =($E$88-$F$88)/$E$88 -> 0
D89: TOTAL +$10 | E89: =E88+10 -> 91.821103 | F89: =F88+10 -> 91.821103
D90: VALOR TOTAL CAJA | E90: =E89*100/40 -> 229.55276 | F90: =F89*100/40 -> 229.55276
D91: C/U | E91: =E89/A76 -> 2.6234601 | F91: =F89/A76 -> 2.6234601
D92: VALOR TOTAL C/U | E92: =E91*100/40 -> 6.5586502 | F92: =$F$91*100/40 -> 6.5586502 | G92: =($E$92-$F$92)/$E$92 -> 0
D93: PRECIO FINAL | E93: =ROUNDUP(E92,0) -> 7 | F93: =ROUNDUP(F92,0) -> 7
A96: Muffins de yogurt | B96: ID-3828
A97: 12 | B97: pzas
A98: Tiempo de horneado: | B98: 28 min. aprox.
A99: Temperatura: | B99: 260°C
A100: Ingrediente | B100: Presentación | C100: Cantidad | D100: Costo | E100: Total | F100: CostoTeórico | G100: TasaDesperdicio
A101: Harina | B101: =VLOOKUP(A101,Lista!$A$3:$E$45,4,FALSE()) -> 1 | C101: 0.24 | D101: =VLOOKUP(A101,Lista!$A$3:$E$45,5,FALSE()) -> 23 | E101: =($C$101*$D$101)/$B$101 -> 5.52 | F101: =($C$101*$D$101)/$B$101 -> 5.52 | G101: =(E101-F101)/E101 -> 0
A102: Polvo para hornear | B102: =VLOOKUP(A102,Lista!$A$3:$E$45,4,FALSE()) -> 1 | C102: 0.015 | D102: =VLOOKUP(A102,Lista!$A$3:$E$45,5,FALSE()) -> 24 | E102: =($C$102*$D$102)/$B$102 -> 0.36 | F102: =($C$102*$D$102)/$B$102 -> 0.36 | G102: =(E102-F102)/E102 -> 0
A103: Huevos | B103: =VLOOKUP(A103,Lista!$A$3:$E$45,4,FALSE()) -> 30 | C103: 3 | D103: =VLOOKUP(A103,Lista!$A$3:$E$45,5,FALSE()) -> 91 | E103: =($C$103*$D$103)/$B$103 -> 9.1 | F103: =($C$103*$D$103)/$B$103 -> 9.1 | G103: =(E103-F103)/E103 -> 0
A104: Azúcar | B104: =VLOOKUP(A104,Lista!$A$3:$E$45,4,FALSE()) -> 1 | C104: 0.15 | D104: =VLOOKUP(A104,Lista!$A$3:$E$45,5,FALSE()) -> 22 | E104: =($C$104*$D$104)/$B$104 -> 3.3 | F104: =($C$104*$D$104)/$B$104 -> 3.3 | G104: =(E104-F104)/E104 -> 0
A105: Sal | B105: =VLOOKUP(A105,Lista!$A$3:$E$45,4,FALSE()) -> 0.65 | C105: 0.001 | D105: =VLOOKUP(A105,Lista!$A$3:$E$45,5,FALSE()) -> 14.8 | E105: =($C$105*$D$105)/$B$105 -> 0.022769231 | F105: =($C$105*$D$105)/$B$105 -> 0.022769231 | G105: =(E105-F105)/E105 -> 0
A106: Vainilla | B106: =VLOOKUP(A106,Lista!$A$3:$E$45,4,FALSE()) -> 0.25 | C106: 0.005 | D106: =VLOOKUP(A106,Lista!$A$3:$E$45,5,FALSE()) -> 24.5 | E106: =($C$106*$D$106)/$B$106 -> 0.49 | F106: =($C$106*$D$106)/$B$106 -> 0.49 | G106: =(E106-F106)/E106 -> 0
A107: Yogurt natural | B107: =VLOOKUP(A107,Lista!$A$3:$E$45,4,FALSE()) -> 1 | C107: =(0.13+0.005) -> 0.135 | D107: =VLOOKUP(A107,Lista!$A$3:$E$45,5,FALSE()) -> 52 | E107: =($C$107*$D$107)/$B$107 -> 7.02 | F107: =(0.13*$D$107)/$B$107 -> 6.76 | G107: =(E107-F107)/E107 -> 0.037037037
A108: Mantequilla | B108: =VLOOKUP(A108,Lista!$A$3:$E$45,4,FALSE()) -> 1 | C108: 0.13 | D108: =VLOOKUP(A108,Lista!$A$3:$E$45,5,FALSE()) -> 245 | E108: =($C$108*$D$108)/$B$108 -> 31.85 | F108: =($C$108*$D$108)/$B$108 -> 31.85 | G108: =(E108-F108)/E108 -> 0
...
